Workbook

Sheet Summary
A1: Field-wise Validation Summary
A3: Field | B3: Precision | C3: Recall | D3: F1 Score | E3: Accuracy % (With Not Exist) | F3: Total Docs Tested | G3: No Of Docs With Data | H3: No Of Docs With Response
A4: Companies / company_name | B4: ='Field 1'!$L$3 | C4: ='Field 1'!$L$4 | D4: ='Field 1'!$L$5 | E4: ='Field 1'!$L$6 | F4: ='Field 1'!$L$7 | G4: ='Field 1'!$L$8 | H4: ='Field 1'!$L$9
A5: Companies / role_desc | B5: ='Field 2'!$L$3 | C5: ='Field 2'!$L$4 | D5: ='Field 2'!$L$5 | E5: ='Field 2'!$L$6 | F5: ='Field 2'!$L$7 | G5: ='Field 2'!$L$8 | H5: ='Field 2'!$L$9
A6: Lease_Comp_Details / act_1954_f | B6: ='Field 3'!$L$3 | C6: ='Field 3'!$L$4 | D6: ='Field 3'!$L$5 | E6: ='Field 3'!$L$6 | F6: ='Field 3'!$L$7 | G6: ='Field 3'!$L$8 | H6: ='Field 3'!$L$9
A7: Lease_Comp_Details / arrangement_end_action_status_reason_type_desc | B7: ='Field 4'!$L$3 | C7: ='Field 4'!$L$4 | D7: ='Field 4'!$L$5 | E7: ='Field 4'!$L$6 | F7: ='Field 4'!$L$7 | G7: ='Field 4'!$L$8 | H7: ='Field 4'!$L$9
A8: Lease_Comp_Details / arrangement_end_action_status_type_desc | B8: ='Field 5'!$L$3 | C8: ='Field 5'!$L$4 | D8: ='Field 5'!$L$5 | E8: ='Field 5'!$L$6 | F8: ='Field 5'!$L$7 | G8: ='Field 5'!$L$8 | H8: ='Field 5'!$L$9
A9: Lease_Comp_Details / arrangement_end_future_action_date | B9: ='Field 6'!$L$3 | C9: ='Field 6'!$L$4 | D9: ='Field 6'!$L$5 | E9: ='Field 6'!$L$6 | F9: ='Field 6'!$L$7 | G9: ='Field 6'!$L$8 | H9: ='Field 6'!$L$9
A10: Lease_Comp_Details / arrangement_end_future_action_type_desc | B10: ='Field 7'!$L$3 | C10: ='Field 7'!$L$4 | D10: ='Field 7'!$L$5 | E10: ='Field 7'!$L$6 | F10: ='Field 7'!$L$7 | G10: ='Field 7'!$L$8 | H10: ='Field 7'!$L$9
A11: Lease_Comp_Details / lease_arrangement_reason_type_desc | B11: ='Field 8'!$L$3 | C11: ='Field 8'!$L$4 | D11: ='Field 8'!$L$5 | E11: ='Field 8'!$L$6 | F11: ='Field 8'!$L$7 | G11: ='Field 8'!$L$8 | H11: ='Field 8'!$L$9
A12: Lease_Comp_Details / ref_lease_activity_type_desc | B12: ='Field 9'!$L$3 | C12: ='Field 9'!$L$4 | D12: ='Field 9'!$L$5 | E12: ='Field 9'!$L$6 | F12: ='Field 9'!$L$7 | G12: ='Field 9'!$L$8 | H12: ='Field 9'!$L$9
A13: Lease_Comp_Details / ref_lease_arrangement_type_desc | B13: ='Field 10'!$L$3 | C13: ='Field 10'!$L$4 | D13: ='Field 10'!$L$5 | E13: ='Field 10'!$L$6 | F13: ='Field 10'!$L$7 | G13: ='Field 10'!$L$8 | H13: ='Field 10'!$L$9
A14: Lease_Comp_Details / ref_total_leased_space_uom_desc | B14: ='Field 11'!$L$3 | C14: ='Field 11'!$L$4 | D14: ='Field 11'!$L$5 | E14: ='Field 11'!$L$6 | F14: ='Field 11'!$L$7 | G14: ='Field 11'!$L$8 | H14: ='Field 11'!$L$9
A15: Lease_Comp_Details / space_condition_type_desc | B15: ='Field 12'!$L$3 | C15: ='Field 12'!$L$4 | D15: ='Field 12'!$L$5 | E15: ='Field 12'!$L$6 | F15: ='Field 12'!$L$7 | G15: ='Field 12'!$L$8 | H15: ='Field 12'!$L$9
A16: Lease_Comp_Details / sublease_f | B16: ='Field 13'!$L$3 | C16: ='Field 13'!$L$4 | D16: ='Field 13'!$L$5 | E16: ='Field 13'!$L$6 | F16: ='Field 13'!$L$7 | G16: ='Field 13'!$L$8 | H16: ='Field 13'!$L$9
A17: Lease_Comp_Details / tenant_status_type_desc | B17: ='Field 14'!$L$3 | C17: ='Field 14'!$L$4 | D17: ='Field 14'!$L$5 | E17: ='Field 14'!$L$6 | F17: ='Field 14'!$L$7 | G17: ='Field 14'!$L$8 | H17: ='Field 14'!$L$9
A18: Lease_Comp_Details / total_leased_space | B18: ='Field 15'!$L$3 | C18: ='Field 15'!$L$4 | D18: ='Field 15'!$L$5 | E18: ='Field 15'!$L$6 | F18: ='Field 15'!$L$7 | G18: ='Field 15'!$L$8 | H18: ='Field 15'!$L$9
A19: Lease_Comp_Details / total_leased_space_estimated_f | B19: ='Field 16'!$L$3 | C19: ='Field 16'!$L$4 | D19: ='Field 16'!$L$5 | E19: ='Field 16'!$L$6 | F19: ='Field 16'!$L$7 | G19: ='Field 16'!$L$8 | H19: ='Field 16'!$L$9
A20: Property / property_name | B20: ='Field 17'!$L$3 | C20: ='Field 17'!$L$4 | D20: ='Field 17'!$L$5 | E20: ='Field 17'!$L$6 | F20: ='Field 17'!$L$7 | G20: ='Field 17'!$L$8 | H20: ='Field 17'!$L$9
A21: Terms / Arrangement_End_Date | B21: ='Field 18'!$L$3 | C21: ='Field 18'!$L$4 | D21: ='Field 18'!$L$5 | E21: ='Field 18'!$L$6 | F21: ='Field 18'!$L$7 | G21: ='Field 18'!$L$8 | H21: ='Field 18'!$L$9
A22: Terms / Arrangement_Signed_Date | B22: ='Field 19'!$L$3 | C22: ='Field 19'!$L$4 | D22: ='Field 19'!$L$5 | E22: ='Field 19'!$L$6 | F22: ='Field 19'!$L$7 | G22: ='Field 19'!$L$8 | H22: ='Field 19'!$L$9
A23: Terms / Arrangement_Start_Date | B23: ='Field 20'!$L$3 | C23: ='Field 20'!$L$4 | D23: ='Field 20'!$L$5 | E23: ='Field 20'!$L$6 | F23: ='Field 20'!$L$7 | G23: ='Field 20'!$L$8 | H23: ='Field 20'!$L$9
A24: Terms / Asking_Rent_Monthly | B24: ='Field 21'!$L$3 | C24: ='Field 21'!$L$4 | D24: ='Field 21'!$L$5 | E24: ='Field 21'!$L$6 | F24: ='Field 21'!$L$7 | G24: ='Field 21'!$L$8 | H24: ='Field 21'!$L$9
A25: Terms / Asking_Rent_Yearly | B25: ='Field 22'!$L$3 | C25: ='Field 22'!$L$4 | D25: ='Field 22'!$L$5 | E25: ='Field 22'!$L$6 | F25: ='Field 22'!$L$7 | G25: ='Field 22'!$L$8 | H25: ='Field 22'!$L$9
A26: Terms / Cost_per_Reserved_Parking_Space | B26: ='Field 23'!$L$3 | C26: ='Field 23'!$L$4 | D26: ='Field 23'!$L$5 | E26: ='Field 23'!$L$6 | F26: ='Field 23'!$L$7 | G26: ='Field 23'!$L$8 | H26: ='Field 23'!$L$9
A27: Terms / Effective_Rent_Monthly | B27: ='Field 24'!$L$3 | C27: ='Field 24'!$L$4 | D27: ='Field 24'!$L$5 | E27: ='Field 24'!$L$6 | F27: ='Field 24'!$L$7 | G27: ='Field 24'!$L$8 | H27: ='Field 24'!$L$9
A28: Terms / Effective_Rent_Yearly | B28: ='Field 25'!$L$3 | C28: ='Field 25'!$L$4 | D28: ='Field 25'!$L$5 | E28: ='Field 25'!$L$6 | F28: ='Field 25'!$L$7 | G28: ='Field 25'!$L$8 | H28: ='Field 25'!$L$9
A29: Terms / Lease_Term | B29: ='Field 26'!$L$3 | C29: ='Field 26'!$L$4 | D29: ='Field 26'!$L$5 | E29: ='Field 26'!$L$6 | F29: ='Field 26'!$L$7 | G29: ='Field 26'!$L$8 | H29: ='Field 26'!$L$9
A30: Terms / Number_Of_Month_Free_Rent | B30: ='Field 27'!$L$3 | C30: ='Field 27'!$L$4 | D30: ='Field 27'!$L$5 | E30: ='Field 27'!$L$6 | F30: ='Field 27'!$L$7 | G30: ='Field 27'!$L$8 | H30: ='Field 27'!$L$9
A31: Terms / Occupancy_Date | B31: ='Field 28'!$L$3 | C31: ='Field 28'!$L$4 | D31: ='Field 28'!$L$5 | E31: ='Field 28'!$L$6 | F31: ='Field 28'!$L$7 | G31: ='Field 28'!$L$8 | H31: ='Field 28'!$L$9
A32: Terms / Option_Notes | B32: ='Field 29'!$L$3 | C32: ='Field 29'!$L$4 | D32: ='Field 29'!$L$5 | E32: ='Field 29'!$L$6 | F32: ='Field 29'!$L$7 | G32: ='Field 29'!$L$8 | H32: ='Field 29'!$L$9
A33: Terms / Ref_asking_rent_monthly_uom_desc | B33: ='Field 30'!$L$3 | C33: ='Field 30'!$L$4 | D33: ='Field 30'!$L$5 | E33: ='Field 30'!$L$6 | F33: ='Field 30'!$L$7 | G33: ='Field 30'!$L$8 | H33: ='Field 30'!$L$9
A34: Terms / Ref_asking_rent_yearly_uom_desc | B34: ='Field 31'!$L$3 | C34: ='Field 31'!$L$4 | D34: ='Field 31'!$L$5 | E34: ='Field 31'!$L$6 | F34: ='Field 31'!$L$7 | G34: ='Field 31'!$L$8 | H34: ='Field 31'!$L$9
A35: Terms / Ref_cost_per_reserved_parking_space_uom_desc | B35: ='Field 32'!$L$3 | C35: ='Field 32'!$L$4 | D35: ='Field 32'!$L$5 | E35: ='Field 32'!$L$6 | F35: ='Field 32'!$L$7 | G35: ='Field 32'!$L$8 | H35: ='Field 32'!$L$9
A36: Terms / Ref_effective_rent_monthly_uom_desc | B36: ='Field 33'!$L$3 | C36: ='Field 33'!$L$4 | D36: ='Field 33'!$L$5 | E36: ='Field 33'!$L$6 | F36: ='Field 33'!$L$7 | G36: ='Field 33'!$L$8 | H36: ='Field 33'!$L$9
A37: Terms / Ref_effective_rent_yearly_uom_desc | B37: ='Field 34'!$L$3 | C37: ='Field 34'!$L$4 | D37: ='Field 34'!$L$5 | E37: ='Field 34'!$L$6 | F37: ='Field 34'!$L$7 | G37: ='Field 34'!$L$8 | H37: ='Field 34'!$L$9
A38: Terms / Ref_lease_term_uom_desc | B38: ='Field 35'!$L$3 | C38: ='Field 35'!$L$4 | D38: ='Field 35'!$L$5 | E38: ='Field 35'!$L$6 | F38: ='Field 35'!$L$7 | G38: ='Field 35'!$L$8 | H38: ='Field 35'!$L$9
A39: Terms / Ref_service_charge_per_area_value_price_uom_desc | B39: ='Field 36'!$L$3 | C39: ='Field 36'!$L$4 | D39: ='Field 36'!$L$5 | E39: ='Field 36'!$L$6 | F39: ='Field 36'!$L$7 | G39: ='Field 36'!$L$8 | H39: ='Field 36'!$L$9
A40: Terms / Ref_tenant_improvement_allowance_uom_desc | B40: ='Field 37'!$L$3 | C40: ='Field 37'!$L$4 | D40: ='Field 37'!$L$5 | E40: ='Field 37'!$L$6 | F40: ='Field 37'!$L$7 | G40: ='Field 37'!$L$8 | H40: ='Field 37'!$L$9
A41: Terms / Reserved_Parking_Spaces | B41: ='Field 38'!$L$3 | C41: ='Field 38'!$L$4 | D41: ='Field 38'!$L$5 | E41: ='Field 38'!$L$6 | F41: ='Field 38'!$L$7 | G41: ='Field 38'!$L$8 | H41: ='Field 38'!$L$9
A42: Terms / Service_Charge_Per_Area_Value | B42: ='Field 39'!$L$3 | C42: ='Field 39'!$L$4 | D42: ='Field 39'!$L$5 | E42: ='Field 39'!$L$6 | F42: ='Field 39'!$L$7 | G42: ='Field 39'!$L$8 | H42: ='Field 39'!$L$9
A43: Terms / Tenant_Improvement_Allowance | B43: ='Field 40'!$L$3 | C43: ='Field 40'!$L$4 | D43: ='Field 40'!$L$5 | E43: ='Field 40'!$L$6 | F43: ='Field 40'!$L$7 | G43: ='Field 40'!$L$8 | H43: ='Field 40'!$L$9
A44: floor_suite / arrangement_space_area | B44: ='Field 41'!$L$3 | C44: ='Field 41'!$L$4 | D44: ='Field 41'!$L$5 | E44: ='Field 41'!$L$6 | F44: ='Field 41'!$L$7 | G44: ='Field 41'!$L$8 | H44: ='Field 41'!$L$9
A45: floor_suite / floor_number | B45: ='Field 42'!$L$3 | C45: ='Field 42'!$L$4 | D45: ='Field 42'!$L$5 | E45: ='Field 42'!$L$6 | F45: ='Field 42'!$L$7 | G45: ='Field 42'!$L$8 | H45: ='Field 42'!$L$9
A46: floor_suite / full_floor_f | B46: ='Field 43'!$L$3 | C46: ='Field 43'!$L$4 | D46: ='Field 43'!$L$5 | E46: ='Field 43'!$L$6 | F46: ='Field 43'!$L$7 | G46: ='Field 43'!$L$8 | H46: ='Field 43'!$L$9
A47: floor_suite / ref_arrangement_space_area_uom_desc | B47: ='Field 44'!$L$3 | C47: ='Field 44'!$L$4 | D47: ='Field 44'!$L$5 | E47: ='Field 44'!$L$6 | F47: ='Field 44'!$L$7 | G47: ='Field 44'!$L$8 | H47: ='Field 44'!$L$9
A48: floor_suite / suite_number | B48: ='Field 45'!$L$3 | C48: ='Field 45'!$L$4 | D48: ='Field 45'!$L$5 | E48: ='Field 45'!$L$6 | F48: ='Field 45'!$L$7 | G48: ='Field 45'!$L$8 | H48: ='Field 45'!$L$9
A49: floor_suite / tenancy_status_desc | B49: ='Field 46'!$L$3 | C49: ='Field 46'!$L$4 | D49: ='Field 46'!$L$5 | E49: ='Field 46'!$L$6 | F49: ='Field 46'!$L$7 | G49: ='Field 46'!$L$8 | H49: ='Field 46'!$L$9
A50: floor_suite / tenancy_status_reason_desc | B50: ='Field 47'!$L$3 | C50: ='Field 47'!$L$4 | D50: ='Field 47'!$L$5 | E50: ='Field 47'!$L$6 | F50: ='Field 47'!$L$7 | G50: ='Field 47'!$L$8 | H50: ='Field 47'!$L$9
A51: floor_suite / tenancy_status_reason_notes | B51: ='Field 48'!$L$3 | C51: ='Field 48'!$L$4 | D51: ='Field 48'!$L$5 | E51: ='Field 48'!$L$6 | F51: ='Field 48'!$L$7 | G51: ='Field 48'!$L$8 | H51: ='Field 48'!$L$9
A52: lease_break / arrangement_option_executor_type_desc | B52: ='Field 49'!$L$3 | C52: ='Field 49'!$L$4 | D52: ='Field 49'!$L$5 | E52: ='Field 49'!$L$6 | F52: ='Field 49'!$L$7 | G52: ='Field 49'!$L$8 | H52: ='Field 49'!$L$9
A53: lease_break / arrangement_option_start_date | B53: ='Field 50'!$L$3 | C53: ='Field 50'!$L$4 | D53: ='Field 50'!$L$5 | E53: ='Field 50'!$L$6 | F53: ='Field 50'!$L$7 | G53: ='Field 50'!$L$8 | H53: ='Field 50'!$L$9
A54: measurements / asking_rent_yearly | B54: ='Field 51'!$L$3 | C54: ='Field 51'!$L$4 | D54: ='Field 51'!$L$5 | E54: ='Field 51'!$L$6 | F54: ='Field 51'!$L$7 | G54: ='Field 51'!$L$8 | H54: ='Field 51'!$L$9
A55: measurements / asking_rent_yearly_uom | B55: ='Field 52'!$L$3 | C55: ='Field 52'!$L$4 | D55: ='Field 52'!$L$5 | E55: ='Field 52'!$L$6 | F55: ='Field 52'!$L$7 | G55: ='Field 52'!$L$8 | H55: ='Field 52'!$L$9
A56: measurements / property_element_type_desc | B56: ='Field 53'!$L$3 | C56: ='Field 53'!$L$4 | D56: ='Field 53'!$L$5 | E56: ='Field 53'!$L$6 | F56: ='Field 53'!$L$7 | G56: ='Field 53'!$L$8 | H56: ='Field 53'!$L$9
A57: measurements / property_measurement_notes | B57: ='Field 54'!$L$3 | C57: ='Field 54'!$L$4 | D57: ='Field 54'!$L$5 | E57: ='Field 54'!$L$6 | F57: ='Field 54'!$L$7 | G57: ='Field 54'!$L$8 | H57: ='Field 54'!$L$9
A58: measurements / property_measurement_size | B58: ='Field 55'!$L$3 | C58: ='Field 55'!$L$4 | D58: ='Field 55'!$L$5 | E58: ='Field 55'!$L$6 | F58: ='Field 55'!$L$7 | G58: ='Field 55'!$L$8 | H58: ='Field 55'!$L$9
A59: measurements / property_measurement_size_uom | B59: ='Field 56'!$L$3 | C59: ='Field 56'!$L$4 | D59: ='Field 56'!$L$5 | E59: ='Field 56'!$L$6 | F59: ='Field 56'!$L$7 | G59: ='Field 56'!$L$8 | H59: ='Field 56'!$L$9
A60: parking / number_parking_space | B60: ='Field 57'!$L$3 | C60: ='Field 57'!$L$4 | D60: ='Field 57'!$L$5 | E60: ='Field 57'!$L$6 | F60: ='Field 57'!$L$7 | G60: ='Field 57'!$L$8 | H60: ='Field 57'!$L$9
A61: parking / parking_comments | B61: ='Field 58'!$L$3 | C61: ='Field 58'!$L$4 | D61: ='Field 58'!$L$5 | E61: ='Field 58'!$L$6 | F61: ='Field 58'!$L$7 | G61: ='Field 58'!$L$8 | H61: ='Field 58'!$L$9
A62: parking / parking_cost_monthly | B62: ='Field 59'!$L$3 | C62: ='Field 59'!$L$4 | D62: ='Field 59'!$L$5 | E62: ='Field 59'!$L$6 | F62: ='Field 59'!$L$7 | G62: ='Field 59'!$L$8 | H62: ='Field 59'!$L$9
A63: parking / parking_cost_monthly_uom | B63: ='Field 60'!$L$3 | C63: ='Field 60'!$L$4 | D63: ='Field 60'!$L$5 | E63: ='Field 60'!$L$6 | F63: ='Field 60'!$L$7 | G63: ='Field 60'!$L$8 | H63: ='Field 60'!$L$9
A64: parking / parking_cost_yearly | B64: ='Field 61'!$L$3 | C64: ='Field 61'!$L$4 | D64: ='Field 61'!$L$5 | E64: ='Field 61'!$L$6 | F64: ='Field 61'!$L$7 | G64: ='Field 61'!$L$8 | H64: ='Field 61'!$L$9
A65: parking / parking_cost_yearly_uom | B65: ='Field 62'!$L$3 | C65: ='Field 62'!$L$4 | D65: ='Field 62'!$L$5 | E65: ='Field 62'!$L$6 | F65: ='Field 62'!$L$7 | G65: ='Field 62'!$L$8 | H65: ='Field 62'!$L$9
A66: parking / parking_sub_type_desc | B66: ='Field 63'!$L$3 | C66: ='Field 63'!$L$4 | D66: ='Field 63'!$L$5 | E66: ='Field 63'!$L$6 | F66: ='Field 63'!$L$7 | G66: ='Field 63'!$L$8 | H66: ='Field 63'!$L$9
A67: parking / parking_type_desc | B67: ='Field 64'!$L$3 | C67: ='Field 64'!$L$4 | D67: ='Field 64'!$L$5 | E67: ='Field 64'!$L$6 | F67: ='Field 64'!$L$7 | G67: ='Field 64'!$L$8 | H67: ='Field 64'!$L$9

Sheet Page Summary
A1: Field-wise Page Number Summary
A3: Field | B3: Precision | C3: Recall | D3: F1 Score | E3: Accuracy % (With Not Exist) | F3: Total Docs Tested | G3: No Of Docs With Manual Pg | H3: No Of Docs With Response Pg
A4: Companies / company_name | B4: ='Field 1'!$O$3 | C4: ='Field 1'!$O$4 | D4: ='Field 1'!$O$5 | E4: ='Field 1'!$O$6 | F4: ='Field 1'!$O$7 | G4: ='Field 1'!$O$8 | H4: ='Field 1'!$O$9
A5: Companies / role_desc | B5: ='Field 2'!$O$3 | C5: ='Field 2'!$O$4 | D5: ='Field 2'!$O$5 | E5: ='Field 2'!$O$6 | F5: ='Field 2'!$O$7 | G5: ='Field 2'!$O$8 | H5: ='Field 2'!$O$9
A6: Lease_Comp_Details / act_1954_f | B6: ='Field 3'!$O$3 | C6: ='Field 3'!$O$4 | D6: ='Field 3'!$O$5 | E6: ='Field 3'!$O$6 | F6: ='Field 3'!$O$7 | G6: ='Field 3'!$O$8 | H6: ='Field 3'!$O$9
A7: Lease_Comp_Details / arrangement_end_action_status_reason_type_desc | B7: ='Field 4'!$O$3 | C7: ='Field 4'!$O$4 | D7: ='Field 4'!$O$5 | E7: ='Field 4'!$O$6 | F7: ='Field 4'!$O$7 | G7: ='Field 4'!$O$8 | H7: ='Field 4'!$O$9
A8: Lease_Comp_Details / arrangement_end_action_status_type_desc | B8: ='Field 5'!$O$3 | C8: ='Field 5'!$O$4 | D8: ='Field 5'!$O$5 | E8: ='Field 5'!$O$6 | F8: ='Field 5'!$O$7 | G8: ='Field 5'!$O$8 | H8: ='Field 5'!$O$9
A9: Lease_Comp_Details / arrangement_end_future_action_date | B9: ='Field 6'!$O$3 | C9: ='Field 6'!$O$4 | D9: ='Field 6'!$O$5 | E9: ='Field 6'!$O$6 | F9: ='Field 6'!$O$7 | G9: ='Field 6'!$O$8 | H9: ='Field 6'!$O$9
A10: Lease_Comp_Details / arrangement_end_future_action_type_desc | B10: ='Field 7'!$O$3 | C10: ='Field 7'!$O$4 | D10: ='Field 7'!$O$5 | E10: ='Field 7'!$O$6 | F10: ='Field 7'!$O$7 | G10: ='Field 7'!$O$8 | H10: ='Field 7'!$O$9
A11: Lease_Comp_Details / lease_arrangement_reason_type_desc | B11: ='Field 8'!$O$3 | C11: ='Field 8'!$O$4 | D11: ='Field 8'!$O$5 | E11: ='Field 8'!$O$6 | F11: ='Field 8'!$O$7 | G11: ='Field 8'!$O$8 | H11: ='Field 8'!$O$9
A12: Lease_Comp_Details / ref_lease_activity_type_desc | B12: ='Field 9'!$O$3 | C12: ='Field 9'!$O$4 | D12: ='Field 9'!$O$5 | E12: ='Field 9'!$O$6 | F12: ='Field 9'!$O$7 | G12: ='Field 9'!$O$8 | H12: ='Field 9'!$O$9
A13: Lease_Comp_Details / ref_lease_arrangement_type_desc | B13: ='Field 10'!$O$3 | C13: ='Field 10'!$O$4 | D13: ='Field 10'!$O$5 | E13: ='Field 10'!$O$6 | F13: ='Field 10'!$O$7 | G13: ='Field 10'!$O$8 | H13: ='Field 10'!$O$9
A14: Lease_Comp_Details / ref_total_leased_space_uom_desc | B14: ='Field 11'!$O$3 | C14: ='Field 11'!$O$4 | D14: ='Field 11'!$O$5 | E14: ='Field 11'!$O$6 | F14: ='Field 11'!$O$7 | G14: ='Field 11'!$O$8 | H14: ='Field 11'!$O$9
A15: Lease_Comp_Details / space_condition_type_desc | B15: ='Field 12'!$O$3 | C15: ='Field 12'!$O$4 | D15: ='Field 12'!$O$5 | E15: ='Field 12'!$O$6 | F15: ='Field 12'!$O$7 | G15: ='Field 12'!$O$8 | H15: ='Field 12'!$O$9
A16: Lease_Comp_Details / sublease_f | B16: ='Field 13'!$O$3 | C16: ='Field 13'!$O$4 | D16: ='Field 13'!$O$5 | E16: ='Field 13'!$O$6 | F16: ='Field 13'!$O$7 | G16: ='Field 13'!$O$8 | H16: ='Field 13'!$O$9
A17: Lease_Comp_Details / tenant_status_type_desc | B17: ='Field 14'!$O$3 | C17: ='Field 14'!$O$4 | D17: ='Field 14'!$O$5 | E17: ='Field 14'!$O$6 | F17: ='Field 14'!$O$7 | G17: ='Field 14'!$O$8 | H17: ='Field 14'!$O$9
A18: Lease_Comp_Details / total_leased_space | B18: ='Field 15'!$O$3 | C18: ='Field 15'!$O$4 | D18: ='Field 15'!$O$5 | E18: ='Field 15'!$O$6 | F18: ='Field 15'!$O$7 | G18: ='Field 15'!$O$8 | H18: ='Field 15'!$O$9
A19: Lease_Comp_Details / total_leased_space_estimated_f | B19: ='Field 16'!$O$3 | C19: ='Field 16'!$O$4 | D19: ='Field 16'!$O$5 | E19: ='Field 16'!$O$6 | F19: ='Field 16'!$O$7 | G19: ='Field 16'!$O$8 | H19: ='Field 16'!$O$9
A20: Property / property_name | B20: ='Field 17'!$O$3 | C20: ='Field 17'!$O$4 | D20: ='Field 17'!$O$5 | E20: ='Field 17'!$O$6 | F20: ='Field 17'!$O$7 | G20: ='Field 17'!$O$8 | H20: ='Field 17'!$O$9
A21: Terms / Arrangement_End_Date | B21: ='Field 18'!$O$3 | C21: ='Field 18'!$O$4 | D21: ='Field 18'!$O$5 | E21: ='Field 18'!$O$6 | F21: ='Field 18'!$O$7 | G21: ='Field 18'!$O$8 | H21: ='Field 18'!$O$9
A22: Terms / Arrangement_Signed_Date | B22: ='Field 19'!$O$3 | C22: ='Field 19'!$O$4 | D22: ='Field 19'!$O$5 | E22: ='Field 19'!$O$6 | F22: ='Field 19'!$O$7 | G22: ='Field 19'!$O$8 | H22: ='Field 19'!$O$9
A23: Terms / Arrangement_Start_Date | B23: ='Field 20'!$O$3 | C23: ='Field 20'!$O$4 | D23: ='Field 20'!$O$5 | E23: ='Field 20'!$O$6 | F23: ='Field 20'!$O$7 | G23: ='Field 20'!$O$8 | H23: ='Field 20'!$O$9
A24: Terms / Asking_Rent_Monthly | B24: ='Field 21'!$O$3 | C24: ='Field 21'!$O$4 | D24: ='Field 21'!$O$5 | E24: ='Field 21'!$O$6 | F24: ='Field 21'!$O$7 | G24: ='Field 21'!$O$8 | H24: ='Field 21'!$O$9
A25: Terms / Asking_Rent_Yearly | B25: ='Field 22'!$O$3 | C25: ='Field 22'!$O$4 | D25: ='Field 22'!$O$5 | E25: ='Field 22'!$O$6 | F25: ='Field 22'!$O$7 | G25: ='Field 22'!$O$8 | H25: ='Field 22'!$O$9
A26: Terms / Cost_per_Reserved_Parking_Space | B26: ='Field 23'!$O$3 | C26: ='Field 23'!$O$4 | D26: ='Field 23'!$O$5 | E26: ='Field 23'!$O$6 | F26: ='Field 23'!$O$7 | G26: ='Field 23'!$O$8 | H26: ='Field 23'!$O$9
A27: Terms / Effective_Rent_Monthly | B27: ='Field 24'!$O$3 | C27: ='Field 24'!$O$4 | D27: ='Field 24'!$O$5 | E27: ='Field 24'!$O$6 | F27: ='Field 24'!$O$7 | G27: ='Field 24'!$O$8 | H27: ='Field 24'!$O$9
A28: Terms / Effective_Rent_Yearly | B28: ='Field 25'!$O$3 | C28: ='Field 25'!$O$4 | D28: ='Field 25'!$O$5 | E28: ='Field 25'!$O$6 | F28: ='Field 25'!$O$7 | G28: ='Field 25'!$O$8 | H28: ='Field 25'!$O$9
A29: Terms / Lease_Term | B29: ='Field 26'!$O$3 | C29: ='Field 26'!$O$4 | D29: ='Field 26'!$O$5 | E29: ='Field 26'!$O$6 | F29: ='Field 26'!$O$7 | G29: ='Field 26'!$O$8 | H29: ='Field 26'!$O$9
A30: Terms / Number_Of_Month_Free_Rent | B30: ='Field 27'!$O$3 | C30: ='Field 27'!$O$4 | D30: ='Field 27'!$O$5 | E30: ='Field 27'!$O$6 | F30: ='Field 27'!$O$7 | G30: ='Field 27'!$O$8 | H30: ='Field 27'!$O$9
A31: Terms / Occupancy_Date | B31: ='Field 28'!$O$3 | C31: ='Field 28'!$O$4 | D31: ='Field 28'!$O$5 | E31: ='Field 28'!$O$6 | F31: ='Field 28'!$O$7 | G31: ='Field 28'!$O$8 | H31: ='Field 28'!$O$9
A32: Terms / Option_Notes | B32: ='Field 29'!$O$3 | C32: ='Field 29'!$O$4 | D32: ='Field 29'!$O$5 | E32: ='Field 29'!$O$6 | F32: ='Field 29'!$O$7 | G32: ='Field 29'!$O$8 | H32: ='Field 29'!$O$9
A33: Terms / Ref_asking_rent_monthly_uom_desc | B33: ='Field 30'!$O$3 | C33: ='Field 30'!$O$4 | D33: ='Field 30'!$O$5 | E33: ='Field 30'!$O$6 | F33: ='Field 30'!$O$7 | G33: ='Field 30'!$O$8 | H33: ='Field 30'!$O$9
A34: Terms / Ref_asking_rent_yearly_uom_desc | B34: ='Field 31'!$O$3 | C34: ='Field 31'!$O$4 | D34: ='Field 31'!$O$5 | E34: ='Field 31'!$O$6 | F34: ='Field 31'!$O$7 | G34: ='Field 31'!$O$8 | H34: ='Field 31'!$O$9
A35: Terms / Ref_cost_per_reserved_parking_space_uom_desc | B35: ='Field 32'!$O$3 | C35: ='Field 32'!$O$4 | D35: ='Field 32'!$O$5 | E35: ='Field 32'!$O$6 | F35: ='Field 32'!$O$7 | G35: ='Field 32'!$O$8 | H35: ='Field 32'!$O$9
A36: Terms / Ref_effective_rent_monthly_uom_desc | B36: ='Field 33'!$O$3 | C36: ='Field 33'!$O$4 | D36: ='Field 33'!$O$5 | E36: ='Field 33'!$O$6 | F36: ='Field 33'!$O$7 | G36: ='Field 33'!$O$8 | H36: ='Field 33'!$O$9
A37: Terms / Ref_effective_rent_yearly_uom_desc | B37: ='Field 34'!$O$3 | C37: ='Field 34'!$O$4 | D37: ='Field 34'!$O$5 | E37: ='Field 34'!$O$6 | F37: ='Field 34'!$O$7 | G37: ='Field 34'!$O$8 | H37: ='Field 34'!$O$9
A38: Terms / Ref_lease_term_uom_desc | B38: ='Field 35'!$O$3 | C38: ='Field 35'!$O$4 | D38: ='Field 35'!$O$5 | E38: ='Field 35'!$O$6 | F38: ='Field 35'!$O$7 | G38: ='Field 35'!$O$8 | H38: ='Field 35'!$O$9
A39: Terms / Ref_service_charge_per_area_value_price_uom_desc | B39: ='Field 36'!$O$3 | C39: ='Field 36'!$O$4 | D39: ='Field 36'!$O$5 | E39: ='Field 36'!$O$6 | F39: ='Field 36'!$O$7 | G39: ='Field 36'!$O$8 | H39: ='Field 36'!$O$9
A40: Terms / Ref_tenant_improvement_allowance_uom_desc | B40: ='Field 37'!$O$3 | C40: ='Field 37'!$O$4 | D40: ='Field 37'!$O$5 | E40: ='Field 37'!$O$6 | F40: ='Field 37'!$O$7 | G40: ='Field 37'!$O$8 | H40: ='Field 37'!$O$9
A41: Terms / Reserved_Parking_Spaces | B41: ='Field 38'!$O$3 | C41: ='Field 38'!$O$4 | D41: ='Field 38'!$O$5 | E41: ='Field 38'!$O$6 | F41: ='Field 38'!$O$7 | G41: ='Field 38'!$O$8 | H41: ='Field 38'!$O$9
A42: Terms / Service_Charge_Per_Area_Value | B42: ='Field 39'!$O$3 | C42: ='Field 39'!$O$4 | D42: ='Field 39'!$O$5 | E42: ='Field 39'!$O$6 | F42: ='Field 39'!$O$7 | G42: ='Field 39'!$O$8 | H42: ='Field 39'!$O$9
A43: Terms / Tenant_Improvement_Allowance | B43: ='Field 40'!$O$3 | C43: ='Field 40'!$O$4 | D43: ='Field 40'!$O$5 | E43: ='Field 40'!$O$6 | F43: ='Field 40'!$O$7 | G43: ='Field 40'!$O$8 | H43: ='Field 40'!$O$9
A44: floor_suite / arrangement_space_area | B44: ='Field 41'!$O$3 | C44: ='Field 41'!$O$4 | D44: ='Field 41'!$O$5 | E44: ='Field 41'!$O$6 | F44: ='Field 41'!$O$7 | G44: ='Field 41'!$O$8 | H44: ='Field 41'!$O$9
A45: floor_suite / floor_number | B45: ='Field 42'!$O$3 | C45: ='Field 42'!$O$4 | D45: ='Field 42'!$O$5 | E45: ='Field 42'!$O$6 | F45: ='Field 42'!$O$7 | G45: ='Field 42'!$O$8 | H45: ='Field 42'!$O$9
A46: floor_suite / full_floor_f | B46: ='Field 43'!$O$3 | C46: ='Field 43'!$O$4 | D46: ='Field 43'!$O$5 | E46: ='Field 43'!$O$6 | F46: ='Field 43'!$O$7 | G46: ='Field 43'!$O$8 | H46: ='Field 43'!$O$9
A47: floor_suite / ref_arrangement_space_area_uom_desc | B47: ='Field 44'!$O$3 | C47: ='Field 44'!$O$4 | D47: ='Field 44'!$O$5 | E47: ='Field 44'!$O$6 | F47: ='Field 44'!$O$7 | G47: ='Field 44'!$O$8 | H47: ='Field 44'!$O$9
A48: floor_suite / suite_number | B48: ='Field 45'!$O$3 | C48: ='Field 45'!$O$4 | D48: ='Field 45'!$O$5 | E48: ='Field 45'!$O$6 | F48: ='Field 45'!$O$7 | G48: ='Field 45'!$O$8 | H48: ='Field 45'!$O$9
A49: floor_suite / tenancy_status_desc | B49: ='Field 46'!$O$3 | C49: ='Field 46'!$O$4 | D49: ='Field 46'!$O$5 | E49: ='Field 46'!$O$6 | F49: ='Field 46'!$O$7 | G49: ='Field 46'!$O$8 | H49: ='Field 46'!$O$9
A50: floor_suite / tenancy_status_reason_desc | B50: ='Field 47'!$O$3 | C50: ='Field 47'!$O$4 | D50: ='Field 47'!$O$5 | E50: ='Field 47'!$O$6 | F50: ='Field 47'!$O$7 | G50: ='Field 47'!$O$8 | H50: ='Field 47'!$O$9
A51: floor_suite / tenancy_status_reason_notes | B51: ='Field 48'!$O$3 | C51: ='Field 48'!$O$4 | D51: ='Field 48'!$O$5 | E51: ='Field 48'!$O$6 | F51: ='Field 48'!$O$7 | G51: ='Field 48'!$O$8 | H51: ='Field 48'!$O$9
A52: lease_break / arrangement_option_executor_type_desc | B52: ='Field 49'!$O$3 | C52: ='Field 49'!$O$4 | D52: ='Field 49'!$O$5 | E52: ='Field 49'!$O$6 | F52: ='Field 49'!$O$7 | G52: ='Field 49'!$O$8 | H52: ='Field 49'!$O$9
A53: lease_break / arrangement_option_start_date | B53: ='Field 50'!$O$3 | C53: ='Field 50'!$O$4 | D53: ='Field 50'!$O$5 | E53: ='Field 50'!$O$6 | F53: ='Field 50'!$O$7 | G53: ='Field 50'!$O$8 | H53: ='Field 50'!$O$9
A54: measurements / asking_rent_yearly | B54: ='Field 51'!$O$3 | C54: ='Field 51'!$O$4 | D54: ='Field 51'!$O$5 | E54: ='Field 51'!$O$6 | F54: ='Field 51'!$O$7 | G54: ='Field 51'!$O$8 | H54: ='Field 51'!$O$9
A55: measurements / asking_rent_yearly_uom | B55: ='Field 52'!$O$3 | C55: ='Field 52'!$O$4 | D55: ='Field 52'!$O$5 | E55: ='Field 52'!$O$6 | F55: ='Field 52'!$O$7 | G55: ='Field 52'!$O$8 | H55: ='Field 52'!$O$9
A56: measurements / property_element_type_desc | B56: ='Field 53'!$O$3 | C56: ='Field 53'!$O$4 | D56: ='Field 53'!$O$5 | E56: ='Field 53'!$O$6 | F56: ='Field 53'!$O$7 | G56: ='Field 53'!$O$8 | H56: ='Field 53'!$O$9
A57: measurements / property_measurement_notes | B57: ='Field 54'!$O$3 | C57: ='Field 54'!$O$4 | D57: ='Field 54'!$O$5 | E57: ='Field 54'!$O$6 | F57: ='Field 54'!$O$7 | G57: ='Field 54'!$O$8 | H57: ='Field 54'!$O$9
A58: measurements / property_measurement_size | B58: ='Field 55'!$O$3 | C58: ='Field 55'!$O$4 | D58: ='Field 55'!$O$5 | E58: ='Field 55'!$O$6 | F58: ='Field 55'!$O$7 | G58: ='Field 55'!$O$8 | H58: ='Field 55'!$O$9
A59: measurements / property_measurement_size_uom | B59: ='Field 56'!$O$3 | C59: ='Field 56'!$O$4 | D59: ='Field 56'!$O$5 | E59: ='Field 56'!$O$6 | F59: ='Field 56'!$O$7 | G59: ='Field 56'!$O$8 | H59: ='Field 56'!$O$9
A60: parking / number_parking_space | B60: ='Field 57'!$O$3 | C60: ='Field 57'!$O$4 | D60: ='Field 57'!$O$5 | E60: ='Field 57'!$O$6 | F60: ='Field 57'!$O$7 | G60: ='Field 57'!$O$8 | H60: ='Field 57'!$O$9
A61: parking / parking_comments | B61: ='Field 58'!$O$3 | C61: ='Field 58'!$O$4 | D61: ='Field 58'!$O$5 | E61: ='Field 58'!$O$6 | F61: ='Field 58'!$O$7 | G61: ='Field 58'!$O$8 | H61: ='Field 58'!$O$9
A62: parking / parking_cost_monthly | B62: ='Field 59'!$O$3 | C62: ='Field 59'!$O$4 | D62: ='Field 59'!$O$5 | E62: ='Field 59'!$O$6 | F62: ='Field 59'!$O$7 | G62: ='Field 59'!$O$8 | H62: ='Field 59'!$O$9
A63: parking / parking_cost_monthly_uom | B63: ='Field 60'!$O$3 | C63: ='Field 60'!$O$4 | D63: ='Field 60'!$O$5 | E63: ='Field 60'!$O$6 | F63: ='Field 60'!$O$7 | G63: ='Field 60'!$O$8 | H63: ='Field 60'!$O$9
A64: parking / parking_cost_yearly | B64: ='Field 61'!$O$3 | C64: ='Field 61'!$O$4 | D64: ='Field 61'!$O$5 | E64: ='Field 61'!$O$6 | F64: ='Field 61'!$O$7 | G64: ='Field 61'!$O$8 | H64: ='Field 61'!$O$9
A65: parking / parking_cost_yearly_uom | B65: ='Field 62'!$O$3 | C65: ='Field 62'!$O$4 | D65: ='Field 62'!$O$5 | E65: ='Field 62'!$O$6 | F65: ='Field 62'!$O$7 | G65: ='Field 62'!$O$8 | H65: ='Field 62'!$O$9
A66: parking / parking_sub_type_desc | B66: ='Field 63'!$O$3 | C66: ='Field 63'!$O$4 | D66: ='Field 63'!$O$5 | E66: ='Field 63'!$O$6 | F66: ='Field 63'!$O$7 | G66: ='Field 63'!$O$8 | H66: ='Field 63'!$O$9
A67: parking / parking_type_desc | B67: ='Field 64'!$O$3 | C67: ='Field 64'!$O$4 | D67: ='Field 64'!$O$5 | E67: ='Field 64'!$O$6 | F67: ='Field 64'!$O$7 | G67: ='Field 64'!$O$8 | H67: ='Field 64'!$O$9

Sheet Token Summary
A1: Token Consumption Summary
A3: Metric | B3: Value
A4: Run ID | B4: abstract-method-2-20261007-152636
A5: Flow | B5: abstract
A6: Total Documents | B6: 35
A7: Documents With Token Data | B7: 35
A8: Total Unique Fields | B8: 64
A9: Total LLM Tokens | B9: 52142171
A10: Total Embedding Tokens | B10: 6836420
A11: Total Tokens | B11: 58978591
A12: Total API Calls | B12: 2905
A13: Total Cost (USD) | B13: 41.674336
A14: Avg Cost / Document (USD) | B14: 1.1906953
A15: Avg Tokens / Document | B15: 1685103
A16: Unpriced Models | B16: None

Sheet Token by Model
A1: Token Consumption by Model
A3: Model | B3: Type | C3: Calls | D3: Prompt Tokens | E3: Cached Tokens | F3: Completion Tokens | G3: Thought Tokens | H3: Embedding Tokens | I3: Total Tokens | J3: Prompt USD/M | K3: Cached USD/M | L3: Completion USD/M | M3: Thoughts USD/M | N3: Embedding USD/M | O3: Cost (USD)
A4: gemini-2.5-flash | B4: LLM | C4: 1190 | D4: 22229725 | E4: 1931128 | F4: 800801 | G4: 0 | H4: 0 | I4: 23030526 | J4: 0.3 | K4: 0.03 | L4: 2.5 | M4: 2.5 | N4: - | O4: 8.1495154
A5: gpt-4.1 | B5: LLM | C5: 1715 | D5: 28903603 | E5: 17890304 | F5: 208042 | G5: 0 | H5: 0 | I5: 29111645 | J5: 2 | K5: 0.5 | L5: 8 | M5: 0 | N5: - | O5: 32.636086
A6: text-embedding-3-large | B6: Embedding | C6: 0 | D6: 0 | E6: 0 | F6: 0 | G6: 0 | H6: 6836420 | I6: 6836420 | J6: - | K6: - | L6: - | M6: - | N6: 0.13 | O6: 0.8887346
A7: TOTAL | C7: 2905 | D7: 51133328 | E7: 19821432 | F7: 1008843 | G7: 0 | H7: 6836420 | I7: 58978591 | O7: 41.674336

Sheet Token by Document
A1: Token Consumption by Document
A3: Document | B3: Fields Extracted | C3: API Calls | D3: LLM Tokens | E3: Embedding Tokens | F3: Total Tokens | G3: Cost (USD)
A4: 20181204 Huurovereenkomst (GETEKEND).PDF | B4: 49 | C4: 83 | D4: 834470 | E4: 52240 | F4: 886710 | G4: 0.73602885
A5: 2024.10.30_Office Rental Agreement Labs_Gruyter Fabriek.pdf | B5: 50 | C5: 83 | D5: 1547491 | E5: 172100 | F5: 1719591 | G5: 1.150876
A6: 20240606_HOK AKD - EDGE Eindhoven execution version.pdf | B6: 61 | C6: 83 | D6: 1156274 | E6: 81945 | F6: 1238219 | G6: 1.0404708
A7: 20250117_HOK Duke Strategies - Hambaken A.05.09 DEF FULLY SIGNED.pdf | B7: 59 | C7: 83 | D7: 755829 | E7: 43825 | F7: 799654 | G7: 0.68759779
A8: 20251216 Lease agreement ASPEN - signed.pdf | B8: 47 | C8: 83 | D8: 2318729 | E8: 809225 | F8: 3127954 | G8: 1.6603155
A9: 20260220 Huurovereenkomst signed 20-02-2026.pdf | B9: 61 | C9: 83 | D9: 1419257 | E9: 176110 | F9: 1595367 | G9: 1.1557177
A10: 20260629 HOK ADHDcentraal BV (1).pdf | B10: 60 | C10: 83 | D10: 1658829 | E10: 205635 | F10: 1864464 | G10: 1.3063745
A11: 20260807_Happy_Village_B.V._Lease_Maasstadweg_tekenversie_incl._bijlagen en-GB.pdf | B11: 52 | C11: 83 | D11: 1888487 | E11: 224065 | F11: 2112552 | G11: 1.5257897
A12: 20260810 HOK ClustR BV.pdf | B12: 57 | C12: 83 | D12: 1518601 | E12: 205610 | F12: 1724211 | G12: 1.2413751
A13: 20270801 - Getekende Allonge II Advario BV.pdf | B13: 56 | C13: 83 | D13: 932565 | E13: 73810 | F13: 1006375 | G13: 0.84872898
A14: 240119 HOVK Spoorlaan 446-448 Tilburg signed.pdf | B14: 54 | C14: 83 | D14: 1401388 | E14: 154760 | F14: 1556148 | G14: 1.078759
A15: 27001 Rijksvastgoedbedrijf Huurovereenkomst - __27-01-2026_9-07-56.pdf | B15: 60 | C15: 83 | D15: 1396866 | E15: 122050 | F15: 1518916 | G15: 1.2680421
... A39: TOTAL | B39: 64 | C39: 2905 | D39: 52142171 | E39: 6836420 | F39: 58978591 | G39: 41.674336

Sheet Field 1
A1: Doc Name | B1: Manual Data | C1: Response Data | D1: Result | E1: Manual Pg | F1: Response Pg No | G1: Pg Result | H1: Confidence | K1: SUMMARY SHEET | N1: PAGE SUMMARY SHEET
A2: 20181204 Huurovereenkomst (GETEKEND).PDF | C2: Herbax Novum B.V. | H2: 0.95 | K2: Metrics | L2: Percentage | N2: Metrics | O2: Percentage
A3: 2024.10.30_Office Rental Agreement Labs_Gruyter Fabriek.pdf | C3: N.V. Bossche Investerings-Maatschappij h.o.d.n. De Gruyter Fabriek | H3: 0.95 | K3: Precision | L3: =IFERROR(COUNTIFS(D2:D36,"TP")/(COUNTIFS(D2:D36,"TP")+COUNTIFS(D2:D36,"FP")),0) | N3: Precision | O3: =IFERROR(COUNTIFS(G2:G36,"TP")/(COUNTIFS(G2:G36,"TP")+COUNTIFS(G2:G36,"FP")),0)
A4: 20240606_HOK AKD - EDGE Eindhoven execution version.pdf | C4: EDGE TECHNOLOGIES DEVELOPMENT 1 B.V. | H4: 0.95 | K4: Recall | L4: =IFERROR(COUNTIFS(D2:D36,"TP")/(COUNTIFS(D2:D36,"TP")+COUNTIFS(D2:D36,"FN")),0) | N4: Recall | O4: =IFERROR(COUNTIFS(G2:G36,"TP")/(COUNTIFS(G2:G36,"TP")+COUNTIFS(G2:G36,"FN")),0)
A5: 20250117_HOK Duke Strategies - Hambaken A.05.09 DEF FULLY SIGNED.pdf | C5: Campus Hambaken B.V. | H5: 0.95 | K5: F1 Score | L5: =IFERROR(2*COUNTIFS(D2:D36,"TP")/(2*COUNTIFS(D2:D36,"TP")+COUNTIFS(D2:D36,"FP")+COUNTIFS(D2:D36,"FN")),0) | N5: F1 Score | O5: =IFERROR(2*COUNTIFS(G2:G36,"TP")/(2*COUNTIFS(G2:G36,"TP")+COUNTIFS(G2:G36,"FP")+COUNTIFS(G2:G36,"FN")),0)
A6: 20251216 Lease agreement ASPEN - signed.pdf | C6: Pivot Park Vastgoed B.V. | H6: 0.95 | K6: Accuracy % (With Not Exist) | L6: =IFERROR((COUNTIF(D2:D36,"TP")+COUNTIF(D2:D36,"TN"))/SUM(COUNTIF(D2:D36,{"TP","TN","FP","FN"})),0) | N6: Accuracy % (With Not Exist) | O6: =IFERROR((COUNTIF(G2:G36,"TP")+COUNTIF(G2:G36,"TN"))/SUM(COUNTIF(G2:G36,{"TP","TN","FP","FN"})),0)
A7: 20260220 Huurovereenkomst signed 20-02-2026.pdf | C7: Bond Park C.V. | H7: 0.95 | K7: Total Docs Tested | L7: =COUNTA(A2:A36) | N7: Total Docs Tested | O7: =COUNTA(A2:A36)
A8: 20260629 HOK ADHDcentraal BV (1).pdf | C8: ADHDcentraal B.V. | H8: 0.95 | K8: No Of Docs With Data | L8: =COUNTIFS(B2:B36,"<>",B2:B36,"<>N/A",B2:B36,"<>Not Present In the Document",B2:B36,"<>Not Found",B2:B36,"<>i dont know",B2:B36,"<>i don't know") | N8: No Of Docs With Manual Pg | O8: =COUNTIFS(E2:E36,"<>",E2:E36,"<>N/A",E2:E36,"<>Not Present In the Document",E2:E36,"<>Not Found",E2:E36,"<>i dont know",E2:E36,"<>i don't know")
A9: 20260807_Happy_Village_B.V._Lease_Maasstadweg_tekenversie_incl._bijlagen en-GB.pdf | C9: Nightingale Rotterdam I B.V. | H9: 0.95 | K9: No Of Docs With Response | L9: =COUNTIFS(C2:C36,"<>") | N9: No Of Docs With Response Pg | O9: =COUNTIFS(F2:F36,"<>")
A10: 20260810 HOK ClustR BV.pdf | C10: Campus Hambaken B.V. | H10: 0.95 | K10: Highlighted rows = file(s) not in the annotation sheet; excluded from all metrics above.
A11: 20270801 - Getekende Allonge II Advario BV.pdf | C11: Stichting Bouwinvest Dutch Institutional Office Fund | H11: 0.95 | K11: Validation Rules Example
A12: 240119 HOVK Spoorlaan 446-448 Tilburg signed.pdf | C12: DAF TEI Manager B.V. | H12: 0.95 | K12: Manual Data | L12: Response Data | M12: Result
A13: 27001 Rijksvastgoedbedrijf Huurovereenkomst - __27-01-2026_9-07-56.pdf | C13: NSI Kantoren BV | H13: 0.95 | K13: 100 | L13: 100 | M13: TP
A14: CBRE_AT_Services_ENG_-_RITUALS_CBRE signed.pdf | C14: Rituals Cosmetics Enterprise B.V. | H14: 0.95 | L14: 100 | M14: FP
A15: CBRE_Engagement_Letter_Alnylam_20260525_CLEAN_Version_signed all.pdf | C15: Alnylam Italy S.r.l. | H15: 0.95 | K15: 100 | L15: 200 | M15: FP
A16: COMPL DEF Huurovereenkomst - Skybox - Pepperl+Fuchs - 20260204.pdf | C16: ComfortZone Vastgoed III B.V. | H16: 0.96958763 | K16: 100 | M16: FN
A17: COMPL Huurovereenkomst - Stichting CCE - Kantoorgebouw Metzpoint I Dr. Holtroplaan - Fully Signed.pdf | C17: Foxhouse Invest B.V. | H17: 0.95 | M17: TN
A18: COMPL Regel Partners - HOVK - Luchthavenweg 81 - 20260728.pdf | C18: Stichting Juridisch Eigenaar Benkey Vastgoed | H18: 0.95
A19: COMPL_-_Onderhuurovereenkomst_Zelfstroom_B.V._-_50five_B.V._-_kantoorgebouw_Riva_-_05032026.pdf | C19: Zelfstroom B.V. | H19: 0.95 | K19: Field: | L19: Companies / company_name
A20: Den Bosch, Ruwekampweg 4, HOVK getekend.pdf | C20: S.F.M. Duijndam | H20: 0.96476684
A21: FULLY SIGNED - COMPL Huurovereenkomst - Heijmans - Hugo de Grootlaan 23 's-Hertogenbosch V2 30-9-2025.pdf | C21: 2Contact Groep B.V. | H21: 0.95
A22: FULLY SIGNED - DEF_COMPL_Huurovereenkomst_Robo_Charge_-_Campus_Offices_-_20260220.pdf | C22: Campus Hambaken B.V. | H22: 0.95
A23: FULLY SIGNED - Onderhuurovereenkomst Aartshertogenlaan 223, `s-Hertogenbosch - Koning Willem I College B.V. 2606202.pdf | C23: Luzac Opleidingen B.V. | H23: 0.95
A24: FULLY SIGNED COMPL_DEF_Huurovereenkomst_Bond_Bergschot_Breda.pdf | C24: Bergschot Breda B.V. | H24: 0.95
A25: FullySigned_Allonge_II_Virtual_Vaults_Nederland.pdf | C25: Newomij International V B.V. | H25: 0.95
A26: FullySigned_Lease_Agreement_Neste_EDGE_Coolsingel.pdf | C26: EDGE Development 8 B.V. | H26: 0.95
A27: HOK Waalhaven Group (signed).pdf | C27: M7 EREIP V Lux Dutch Holdco S.a r.l. | H27: 0.95
A28: Hovk Avans (3e+4e+5e verd.) 20140425.pdf | C28: TMW Pramerica Property Investments GmbH | H28: 0.96958763
A29: HOVK Power4People 2025.pdf | C29: OFY Breda B.V. | H29: 0.95
A30: Huurovereenkomst (Semmie Group B.V.) - Wilhelminasingel 19, Breda.pdf | C30: Het Malieveld B.V. | H30: 0.95
A31: Huurovereenkomst - proces-verbaal van oplevering - sleuteloverdracht - Kennedyplein 101 - getekend.pdf | C31: Gemeente Eindhoven | H31: 0.95
... A36: MWO CBRE SPA (ITALY) CBRE_090724.pdf | C36: Amazon EU S.a r.l. | H36: 0.96958763

Sheet Field 2
A1: Doc Name | B1: Manual Data | C1: Response Data | D1: Result | E1: Manual Pg | F1: Response Pg No | G1: Pg Result | H1: Confidence | K1: SUMMARY SHEET | N1: PAGE SUMMARY SHEET
A2: 20181204 Huurovereenkomst (GETEKEND).PDF | C2: LEGAL OWNER | H2: 0.95 | K2: Metrics | L2: Percentage | N2: Metrics | O2: Percentage
A3: 2024.10.30_Office Rental Agreement Labs_Gruyter Fabriek.pdf | C3: LEGAL OWNER | H3: 0.95 | K3: Precision | L3: =IFERROR(COUNTIFS(D2:D36,"TP")/(COUNTIFS(D2:D36,"TP")+COUNTIFS(D2:D36,"FP")),0) | N3: Precision | O3: =IFERROR(COUNTIFS(G2:G36,"TP")/(COUNTIFS(G2:G36,"TP")+COUNTIFS(G2:G36,"FP")),0)
A4: 20240606_HOK AKD - EDGE Eindhoven execution version.pdf | C4: LEGAL OWNER | H4: 0.95 | K4: Recall | L4: =IFERROR(COUNTIFS(D2:D36,"TP")/(COUNTIFS(D2:D36,"TP")+COUNTIFS(D2:D36,"FN")),0) | N4: Recall | O4: =IFERROR(COUNTIFS(G2:G36,"TP")/(COUNTIFS(G2:G36,"TP")+COUNTIFS(G2:G36,"FN")),0)
A5: 20250117_HOK Duke Strategies - Hambaken A.05.09 DEF FULLY SIGNED.pdf | C5: LEGAL OWNER | H5: 0.95 | K5: F1 Score | L5: =IFERROR(2*COUNTIFS(D2:D36,"TP")/(2*COUNTIFS(D2:D36,"TP")+COUNTIFS(D2:D36,"FP")+COUNTIFS(D2:D36,"FN")),0) | N5: F1 Score | O5: =IFERROR(2*COUNTIFS(G2:G36,"TP")/(2*COUNTIFS(G2:G36,"TP")+COUNTIFS(G2:G36,"FP")+COUNTIFS(G2:G36,"FN")),0)
A6: 20251216 Lease agreement ASPEN - signed.pdf | C6: LEGAL OWNER | H6: 0.95 | K6: Accuracy % (With Not Exist) | L6: =IFERROR((COUNTIF(D2:D36,"TP")+COUNTIF(D2:D36,"TN"))/SUM(COUNTIF(D2:D36,{"TP","TN","FP","FN"})),0) | N6: Accuracy % (With Not Exist) | O6: =IFERROR((COUNTIF(G2:G36,"TP")+COUNTIF(G2:G36,"TN"))/SUM(COUNTIF(G2:G36,{"TP","TN","FP","FN"})),0)
A7: 20260220 Huurovereenkomst signed 20-02-2026.pdf | C7: LEGAL OWNER | H7: 0.95 | K7: Total Docs Tested | L7: =COUNTA(A2:A36) | N7: Total Docs Tested | O7: =COUNTA(A2:A36)
A8: 20260629 HOK ADHDcentraal BV (1).pdf | C8: TENANT | H8: 0.95 | K8: No Of Docs With Data | L8: =COUNTIFS(B2:B36,"<>",B2:B36,"<>N/A",B2:B36,"<>Not Present In the Document",B2:B36,"<>Not Found",B2:B36,"<>i dont know",B2:B36,"<>i don't know") | N8: No Of Docs With Manual Pg | O8: =COUNTIFS(E2:E36,"<>",E2:E36,"<>N/A",E2:E36,"<>Not Present In the Document",E2:E36,"<>Not Found",E2:E36,"<>i dont know",E2:E36,"<>i don't know")
A9: 20260807_Happy_Village_B.V._Lease_Maasstadweg_tekenversie_incl._bijlagen en-GB.pdf | C9: LEGAL OWNER | H9: 0.95 | K9: No Of Docs With Response | L9: =COUNTIFS(C2:C36,"<>") | N9: No Of Docs With Response Pg | O9: =COUNTIFS(F2:F36,"<>")
A10: 20260810 HOK ClustR BV.pdf | C10: LEGAL OWNER | H10: 0.95 | K10: Highlighted rows = file(s) not in the annotation sheet; excluded from all metrics above.
A11: 20270801 - Getekende Allonge II Advario BV.pdf | C11: LEGAL OWNER | H11: 0.95 | K11: Validation Rules Example
A12: 240119 HOVK Spoorlaan 446-448 Tilburg signed.pdf | C12: LEGAL OWNER | H12: 0.95 | K12: Manual Data | L12: Response Data | M12: Result
A13: 27001 Rijksvastgoedbedrijf Huurovereenkomst - __27-01-2026_9-07-56.pdf | C13: LEGAL OWNER | H13: 0.95 | K13: 100 | L13: 100 | M13: TP
A14: CBRE_AT_Services_ENG_-_RITUALS_CBRE signed.pdf | C14: TENANT | H14: 0.95 | L14: 100 | M14: FP
A15: CBRE_Engagement_Letter_Alnylam_20260525_CLEAN_Version_signed all.pdf | C15: TENANT | H15: 0.95 | K15: 100 | L15: 200 | M15: FP
A16: COMPL DEF Huurovereenkomst - Skybox - Pepperl+Fuchs - 20260204.pdf | C16: LEGAL OWNER | H16: 0.96958763 | K16: 100 | M16: FN
A17: COMPL Huurovereenkomst - Stichting CCE - Kantoorgebouw Metzpoint I Dr. Holtroplaan - Fully Signed.pdf | C17: LEGAL OWNER | H17: 0.95 | M17: TN
A18: COMPL Regel Partners - HOVK - Luchthavenweg 81 - 20260728.pdf | C18: LEGAL OWNER | H18: 0.95
A19: COMPL_-_Onderhuurovereenkomst_Zelfstroom_B.V._-_50five_B.V._-_kantoorgebouw_Riva_-_05032026.pdf | C19: LEGAL OWNER | H19: 0.95 | K19: Field: | L19: Companies / role_desc
A20: Den Bosch, Ruwekampweg 4, HOVK getekend.pdf | C20: LEGAL OWNER | H20: 0.96476684
A21: FULLY SIGNED - COMPL Huurovereenkomst - Heijmans - Hugo de Grootlaan 23 's-Hertogenbosch V2 30-9-2025.pdf | C21: LEGAL OWNER | H21: 0.95
A22: FULLY SIGNED - DEF_COMPL_Huurovereenkomst_Robo_Charge_-_Campus_Offices_-_20260220.pdf | C22: LEGAL OWNER | H22: 0.95
A23: FULLY SIGNED - Onderhuurovereenkomst Aartshertogenlaan 223, `s-Hertogenbosch - Koning Willem I College B.V. 2606202.pdf | C23: LEGAL OWNER | H23: 0.95
A24: FULLY SIGNED COMPL_DEF_Huurovereenkomst_Bond_Bergschot_Breda.pdf | C24: LEGAL OWNER | H24: 0.95
A25: FullySigned_Allonge_II_Virtual_Vaults_Nederland.pdf | C25: LEGAL OWNER | H25: 0.95
A26: FullySigned_Lease_Agreement_Neste_EDGE_Coolsingel.pdf | C26: LEGAL OWNER | H26: 0.95
A27: HOK Waalhaven Group (signed).pdf | C27: LEGAL OWNER | H27: 0.95
A28: Hovk Avans (3e+4e+5e verd.) 20140425.pdf | C28: LEGAL OWNER | H28: 0.96958763
A29: HOVK Power4People 2025.pdf | C29: LEGAL OWNER | H29: 0.95
A30: Huurovereenkomst (Semmie Group B.V.) - Wilhelminasingel 19, Breda.pdf | C30: LEGAL OWNER | H30: 0.95
A31: Huurovereenkomst - proces-verbaal van oplevering - sleuteloverdracht - Kennedyplein 101 - getekend.pdf | C31: LEGAL OWNER | H31: 0.95
... A36: MWO CBRE SPA (ITALY) CBRE_090724.pdf | C36: LEGAL OWNER | H36: 0.96958763

Sheet Field 3
A1: Doc Name | B1: Manual Data | C1: Response Data | D1: Result | E1: Manual Pg | F1: Response Pg No | G1: Pg Result | H1: Confidence | K1: SUMMARY SHEET | N1: PAGE SUMMARY SHEET
A2: 20181204 Huurovereenkomst (GETEKEND).PDF | C2: N | H2: 0.95287958 | K2: Metrics | L2: Percentage | N2: Metrics | O2: Percentage
A3: 2024.10.30_Office Rental Agreement Labs_Gruyter Fabriek.pdf | C3: N | H3: 0.95287958 | K3: Precision | L3: =IFERROR(COUNTIFS(D2:D36,"TP")/(COUNTIFS(D2:D36,"TP")+COUNTIFS(D2:D36,"FP")),0) | N3: Precision | O3: =IFERROR(COUNTIFS(G2:G36,"TP")/(COUNTIFS(G2:G36,"TP")+COUNTIFS(G2:G36,"FP")),0)
A4: 20240606_HOK AKD - EDGE Eindhoven execution version.pdf | C4: N | H4: 0.97435897 | K4: Recall | L4: =IFERROR(COUNTIFS(D2:D36,"TP")/(COUNTIFS(D2:D36,"TP")+COUNTIFS(D2:D36,"FN")),0) | N4: Recall | O4: =IFERROR(COUNTIFS(G2:G36,"TP")/(COUNTIFS(G2:G36,"TP")+COUNTIFS(G2:G36,"FN")),0)
A5: 20250117_HOK Duke Strategies - Hambaken A.05.09 DEF FULLY SIGNED.pdf | C5: N | H5: 0.95287958 | K5: F1 Score | L5: =IFERROR(2*COUNTIFS(D2:D36,"TP")/(2*COUNTIFS(D2:D36,"TP")+COUNTIFS(D2:D36,"FP")+COUNTIFS(D2:D36,"FN")),0) | N5: F1 Score | O5: =IFERROR(2*COUNTIFS(G2:G36,"TP")/(2*COUNTIFS(G2:G36,"TP")+COUNTIFS(G2:G36,"FP")+COUNTIFS(G2:G36,"FN")),0)
A6: 20251216 Lease agreement ASPEN - signed.pdf | C6: N | H6: 0.95011601 | K6: Accuracy % (With Not Exist) | L6: =IFERROR((COUNTIF(D2:D36,"TP")+COUNTIF(D2:D36,"TN"))/SUM(COUNTIF(D2:D36,{"TP","TN","FP","FN"})),0) | N6: Accuracy % (With Not Exist) | O6: =IFERROR((COUNTIF(G2:G36,"TP")+COUNTIF(G2:G36,"TN"))/SUM(COUNTIF(G2:G36,{"TP","TN","FP","FN"})),0)
A7: 20260220 Huurovereenkomst signed 20-02-2026.pdf | C7: N | H7: 0.95011601 | K7: Total Docs Tested | L7: =COUNTA(A2:A36) | N7: Total Docs Tested | O7: =COUNTA(A2:A36)
A8: 20260629 HOK ADHDcentraal BV (1).pdf | C8: N | H8: 0.912 | K8: No Of Docs With Data | L8: =COUNTIFS(B2:B36,"<>",B2:B36,"<>N/A",B2:B36,"<>Not Present In the Document",B2:B36,"<>Not Found",B2:B36,"<>i dont know",B2:B36,"<>i don't know") | N8: No Of Docs With Manual Pg | O8: =COUNTIFS(E2:E36,"<>",E2:E36,"<>N/A",E2:E36,"<>Not Present In the Document",E2:E36,"<>Not Found",E2:E36,"<>i dont know",E2:E36,"<>i don't know")
A9: 20260807_Happy_Village_B.V._Lease_Maasstadweg_tekenversie_incl._bijlagen en-GB.pdf | C9: N | H9: 0.95287958 | K9: No Of Docs With Response | L9: =COUNTIFS(C2:C36,"<>") | N9: No Of Docs With Response Pg | O9: =COUNTIFS(F2:F36,"<>")
A10: 20260810 HOK ClustR BV.pdf | C10: N | H10: 0.95287958 | K10: Highlighted rows = file(s) not in the annotation sheet; excluded from all metrics above.
A11: 20270801 - Getekende Allonge II Advario BV.pdf | C11: N | H11: 0.95011601 | K11: Validation Rules Example
A12: 240119 HOVK Spoorlaan 446-448 Tilburg signed.pdf | C12: N | H12: 1 | K12: Manual Data | L12: Response Data | M12: Result
A13: 27001 Rijksvastgoedbedrijf Huurovereenkomst - __27-01-2026_9-07-56.pdf | C13: N | H13: 0.95287958 | K13: 100 | L13: 100 | M13: TP
A14: CBRE_AT_Services_ENG_-_RITUALS_CBRE signed.pdf | C14: N | H14: 0.95287958 | L14: 100 | M14: FP
A15: CBRE_Engagement_Letter_Alnylam_20260525_CLEAN_Version_signed all.pdf | C15: N | H15: 0.95287958 | K15: 100 | L15: 200 | M15: FP
A16: COMPL DEF Huurovereenkomst - Skybox - Pepperl+Fuchs - 20260204.pdf | C16: N | H16: 1 | K16: 100 | M16: FN
A17: COMPL Huurovereenkomst - Stichting CCE - Kantoorgebouw Metzpoint I Dr. Holtroplaan - Fully Signed.pdf | M17: TN
A18: COMPL Regel Partners - HOVK - Luchthavenweg 81 - 20260728.pdf | C18: N | H18: 0.92966361
A19: COMPL_-_Onderhuurovereenkomst_Zelfstroom_B.V._-_50five_B.V._-_kantoorgebouw_Riva_-_05032026.pdf | C19: N | H19: 0.98455902 | K19: Field: | L19: Lease_Comp_Details / act_1954_f
A20: Den Bosch, Ruwekampweg 4, HOVK getekend.pdf | C20: N | H20: 1
A21: FULLY SIGNED - COMPL Huurovereenkomst - Heijmans - Hugo de Grootlaan 23 's-Hertogenbosch V2 30-9-2025.pdf | C21: N | H21: 0.95287958
A22: FULLY SIGNED - DEF_COMPL_Huurovereenkomst_Robo_Charge_-_Campus_Offices_-_20260220.pdf | C22: N | H22: 0.95011601
A23: FULLY SIGNED - Onderhuurovereenkomst Aartshertogenlaan 223, `s-Hertogenbosch - Koning Willem I College B.V. 2606202.pdf | C23: N | H23: 0.96067416
A24: FULLY SIGNED COMPL_DEF_Huurovereenkomst_Bond_Bergschot_Breda.pdf | C24: N | H24: 1
A25: FullySigned_Allonge_II_Virtual_Vaults_Nederland.pdf | C25: Y | H25: 1
A26: FullySigned_Lease_Agreement_Neste_EDGE_Coolsingel.pdf | C26: N | H26: 0.95287958
A27: HOK Waalhaven Group (signed).pdf | C27: N | H27: 0.95287958
A28: Hovk Avans (3e+4e+5e verd.) 20140425.pdf | C28: N | H28: 0.95011601
A29: HOVK Power4People 2025.pdf | C29: N | H29: 0.95287958
A30: Huurovereenkomst (Semmie Group B.V.) - Wilhelminasingel 19, Breda.pdf | C30: N | H30: 1
A31: Huurovereenkomst - proces-verbaal van oplevering - sleuteloverdracht - Kennedyplein 101 - getekend.pdf | C31: N | H31: 0.9795376
... A36: MWO CBRE SPA (ITALY) CBRE_090724.pdf | C36: N | H36: 0.95287958

Sheet Field 4
A1: Doc Name | B1: Manual Data | C1: Response Data | D1: Result | E1: Manual Pg | F1: Response Pg No | G1: Pg Result | H1: Confidence | K1: SUMMARY SHEET | N1: PAGE SUMMARY SHEET
A2: 20181204 Huurovereenkomst (GETEKEND).PDF | C2: Contract Terms | H2: 0.98206751 | K2: Metrics | L2: Percentage | N2: Metrics | O2: Percentage
A3: 2024.10.30_Office Rental Agreement Labs_Gruyter Fabriek.pdf | C3: Contract Terms | H3: 0.42192103 | K3: Precision | L3: =IFERROR(COUNTIFS(D2:D36,"TP")/(COUNTIFS(D2:D36,"TP")+COUNTIFS(D2:D36,"FP")),0) | N3: Precision | O3: =IFERROR(COUNTIFS(G2:G36,"TP")/(COUNTIFS(G2:G36,"TP")+COUNTIFS(G2:G36,"FP")),0)
A4: 20240606_HOK AKD - EDGE Eindhoven execution version.pdf | C4: Contract Terms | H4: 0.9795376 | K4: Recall | L4: =IFERROR(COUNTIFS(D2:D36,"TP")/(COUNTIFS(D2:D36,"TP")+COUNTIFS(D2:D36,"FN")),0) | N4: Recall | O4: =IFERROR(COUNTIFS(G2:G36,"TP")/(COUNTIFS(G2:G36,"TP")+COUNTIFS(G2:G36,"FN")),0)
A5: 20250117_HOK Duke Strategies - Hambaken A.05.09 DEF FULLY SIGNED.pdf | C5: Contract Terms | H5: 0.9795376 | K5: F1 Score | L5: =IFERROR(2*COUNTIFS(D2:D36,"TP")/(2*COUNTIFS(D2:D36,"TP")+COUNTIFS(D2:D36,"FP")+COUNTIFS(D2:D36,"FN")),0) | N5: F1 Score | O5: =IFERROR(2*COUNTIFS(G2:G36,"TP")/(2*COUNTIFS(G2:G36,"TP")+COUNTIFS(G2:G36,"FP")+COUNTIFS(G2:G36,"FN")),0)
A6: 20251216 Lease agreement ASPEN - signed.pdf | C6: Contract Terms | H6: 0.9795376 | K6: Accuracy % (With Not Exist) | L6: =IFERROR((COUNTIF(D2:D36,"TP")+COUNTIF(D2:D36,"TN"))/SUM(COUNTIF(D2:D36,{"TP","TN","FP","FN"})),0) | N6: Accuracy % (With Not Exist) | O6: =IFERROR((COUNTIF(G2:G36,"TP")+COUNTIF(G2:G36,"TN"))/SUM(COUNTIF(G2:G36,{"TP","TN","FP","FN"})),0)
A7: 20260220 Huurovereenkomst signed 20-02-2026.pdf | C7: Contract Terms | H7: 0.98206751 | K7: Total Docs Tested | L7: =COUNTA(A2:A36) | N7: Total Docs Tested | O7: =COUNTA(A2:A36)
A8: 20260629 HOK ADHDcentraal BV (1).pdf | C8: Contract Terms | H8: 0.98206751 | K8: No Of Docs With Data | L8: =COUNTIFS(B2:B36,"<>",B2:B36,"<>N/A",B2:B36,"<>Not Present In the Document",B2:B36,"<>Not Found",B2:B36,"<>i dont know",B2:B36,"<>i don't know") | N8: No Of Docs With Manual Pg | O8: =COUNTIFS(E2:E36,"<>",E2:E36,"<>N/A",E2:E36,"<>Not Present In the Document",E2:E36,"<>Not Found",E2:E36,"<>i dont know",E2:E36,"<>i don't know")
A9: 20260807_Happy_Village_B.V._Lease_Maasstadweg_tekenversie_incl._bijlagen en-GB.pdf | C9: Contract Terms | H9: 0.98455902 | K9: No Of Docs With Response | L9: =COUNTIFS(C2:C36,"<>") | N9: No Of Docs With Response Pg | O9: =COUNTIFS(F2:F36,"<>")
A10: 20260810 HOK ClustR BV.pdf | C10: Contract Terms | H10: 0.98206751 | K10: Highlighted rows = file(s) not in the annotation sheet; excluded from all metrics above.
A11: 20270801 - Getekende Allonge II Advario BV.pdf | C11: Contract Terms | H11: 0.98455902 | K11: Validation Rules Example
A12: 240119 HOVK Spoorlaan 446-448 Tilburg signed.pdf | C12: Contract Terms | H12: 0.98455902 | K12: Manual Data | L12: Response Data | M12: Result
A13: 27001 Rijksvastgoedbedrijf Huurovereenkomst - __27-01-2026_9-07-56.pdf | C13: Contract Terms | H13: 0.98206751 | K13: 100 | L13: 100 | M13: TP
A14: CBRE_AT_Services_ENG_-_RITUALS_CBRE signed.pdf | C14: Contract Terms | H14: 0.9795376 | L14: 100 | M14: FP
A15: CBRE_Engagement_Letter_Alnylam_20260525_CLEAN_Version_signed all.pdf | C15: Contract Terms | H15: 0.98206751 | K15: 100 | L15: 200 | M15: FP
A16: COMPL DEF Huurovereenkomst - Skybox - Pepperl+Fuchs - 20260204.pdf | C16: Contract Terms | H16: 0.9795376 | K16: 100 | M16: FN
A17: COMPL Huurovereenkomst - Stichting CCE - Kantoorgebouw Metzpoint I Dr. Holtroplaan - Fully Signed.pdf | C17: Contract Terms | H17: 0.44646423 | M17: TN
A18: COMPL Regel Partners - HOVK - Luchthavenweg 81 - 20260728.pdf | C18: Contract Terms | H18: 0.98206751
A19: COMPL_-_Onderhuurovereenkomst_Zelfstroom_B.V._-_50five_B.V._-_kantoorgebouw_Riva_-_05032026.pdf | C19: Contract Terms | H19: 0.98455902 | K19: Field: | L19: Lease_Comp_Details / arrangement_end_action_status_reason_type_desc
A20: Den Bosch, Ruwekampweg 4, HOVK getekend.pdf | C20: Contract Terms | H20: 0.98206751
A21: FULLY SIGNED - COMPL Huurovereenkomst - Heijmans - Hugo de Grootlaan 23 's-Hertogenbosch V2 30-9-2025.pdf | C21: Contract Terms | H21: 0.98206751
A22: FULLY SIGNED - DEF_COMPL_Huurovereenkomst_Robo_Charge_-_Campus_Offices_-_20260220.pdf | C22: Contract Terms | H22: 0.98455902
A23: FULLY SIGNED - Onderhuurovereenkomst Aartshertogenlaan 223, `s-Hertogenbosch - Koning Willem I College B.V. 2606202.pdf | C23: Contract Terms | H23: 0.98455902
A24: FULLY SIGNED COMPL_DEF_Huurovereenkomst_Bond_Bergschot_Breda.pdf | C24: Contract Terms | H24: 0.9795376
A25: FullySigned_Allonge_II_Virtual_Vaults_Nederland.pdf | C25: Occupier Has Renewed/Regeared | H25: 0.98206751
A26: FullySigned_Lease_Agreement_Neste_EDGE_Coolsingel.pdf | C26: Contract Terms | H26: 0.9795376
A27: HOK Waalhaven Group (signed).pdf | C27: Contract Terms | H27: 0.98206751
A28: Hovk Avans (3e+4e+5e verd.) 20140425.pdf | C28: Contract Terms | H28: 0.97435897
A29: HOVK Power4People 2025.pdf | C29: Contract Terms | H29: 0.98206751
A30: Huurovereenkomst (Semmie Group B.V.) - Wilhelminasingel 19, Breda.pdf | C30: Contract Terms | H30: 0.98206751
A31: Huurovereenkomst - proces-verbaal van oplevering - sleuteloverdracht - Kennedyplein 101 - getekend.pdf | C31: Contract Terms | H31: 0.98206751
... A36: MWO CBRE SPA (ITALY) CBRE_090724.pdf | C36: Contract Terms | H36: 0.98206751

Sheet Field 5
A1: Doc Name | B1: Manual Data | C1: Response Data | D1: Result | E1: Manual Pg | F1: Response Pg No | G1: Pg Result | H1: Confidence | K1: SUMMARY SHEET | N1: PAGE SUMMARY SHEET
A2: 20181204 Huurovereenkomst (GETEKEND).PDF | C2: To Expire | H2: 0.35829616 | K2: Metrics | L2: Percentage | N2: Metrics | O2: Percentage
A3: 2024.10.30_Office Rental Agreement Labs_Gruyter Fabriek.pdf | C3: To Expire | H3: 0.98455902 | K3: Precision | L3: =IFERROR(COUNTIFS(D2:D36,"TP")/(COUNTIFS(D2:D36,"TP")+COUNTIFS(D2:D36,"FP")),0) | N3: Precision | O3: =IFERROR(COUNTIFS(G2:G36,"TP")/(COUNTIFS(G2:G36,"TP")+COUNTIFS(G2:G36,"FP")),0)
A4: 20240606_HOK AKD - EDGE Eindhoven execution version.pdf | C4: To Expire | H4: 0.98206751 | K4: Recall | L4: =IFERROR(COUNTIFS(D2:D36,"TP")/(COUNTIFS(D2:D36,"TP")+COUNTIFS(D2:D36,"FN")),0) | N4: Recall | O4: =IFERROR(COUNTIFS(G2:G36,"TP")/(COUNTIFS(G2:G36,"TP")+COUNTIFS(G2:G36,"FN")),0)
A5: 20250117_HOK Duke Strategies - Hambaken A.05.09 DEF FULLY SIGNED.pdf | C5: To Expire | H5: 0.35829616 | K5: F1 Score | L5: =IFERROR(2*COUNTIFS(D2:D36,"TP")/(2*COUNTIFS(D2:D36,"TP")+COUNTIFS(D2:D36,"FP")+COUNTIFS(D2:D36,"FN")),0) | N5: F1 Score | O5: =IFERROR(2*COUNTIFS(G2:G36,"TP")/(2*COUNTIFS(G2:G36,"TP")+COUNTIFS(G2:G36,"FP")+COUNTIFS(G2:G36,"FN")),0)
A6: 20251216 Lease agreement ASPEN - signed.pdf | C6: To Expire | H6: 0.98206751 | K6: Accuracy % (With Not Exist) | L6: =IFERROR((COUNTIF(D2:D36,"TP")+COUNTIF(D2:D36,"TN"))/SUM(COUNTIF(D2:D36,{"TP","TN","FP","FN"})),0) | N6: Accuracy % (With Not Exist) | O6: =IFERROR((COUNTIF(G2:G36,"TP")+COUNTIF(G2:G36,"TN"))/SUM(COUNTIF(G2:G36,{"TP","TN","FP","FN"})),0)
A7: 20260220 Huurovereenkomst signed 20-02-2026.pdf | C7: To Expire | H7: 0.35829616 | K7: Total Docs Tested | L7: =COUNTA(A2:A36) | N7: Total Docs Tested | O7: =COUNTA(A2:A36)
A8: 20260629 HOK ADHDcentraal BV (1).pdf | C8: To Expire | H8: 0.98206751 | K8: No Of Docs With Data | L8: =COUNTIFS(B2:B36,"<>",B2:B36,"<>N/A",B2:B36,"<>Not Present In the Document",B2:B36,"<>Not Found",B2:B36,"<>i dont know",B2:B36,"<>i don't know") | N8: No Of Docs With Manual Pg | O8: =COUNTIFS(E2:E36,"<>",E2:E36,"<>N/A",E2:E36,"<>Not Present In the Document",E2:E36,"<>Not Found",E2:E36,"<>i dont know",E2:E36,"<>i don't know")
A9: 20260807_Happy_Village_B.V._Lease_Maasstadweg_tekenversie_incl._bijlagen en-GB.pdf | C9: To Expire | H9: 0.9795376 | K9: No Of Docs With Response | L9: =COUNTIFS(C2:C36,"<>") | N9: No Of Docs With Response Pg | O9: =COUNTIFS(F2:F36,"<>")
A10: 20260810 HOK ClustR BV.pdf | C10: To Expire | H10: 0.35829616 | K10: Highlighted rows = file(s) not in the annotation sheet; excluded from all metrics above.
A11: 20270801 - Getekende Allonge II Advario BV.pdf | C11: To Expire | H11: 0.9795376 | K11: Validation Rules Example
A12: 240119 HOVK Spoorlaan 446-448 Tilburg signed.pdf | C12: To Expire | H12: 0.35829616 | K12: Manual Data | L12: Response Data | M12: Result
A13: 27001 Rijksvastgoedbedrijf Huurovereenkomst - __27-01-2026_9-07-56.pdf | C13: To Expire | H13: 0.98206751 | K13: 100 | L13: 100 | M13: TP
A14: CBRE_AT_Services_ENG_-_RITUALS_CBRE signed.pdf | C14: To Expire | H14: 0.97435897 | L14: 100 | M14: FP
A15: CBRE_Engagement_Letter_Alnylam_20260525_CLEAN_Version_signed all.pdf | C15: To Expire | H15: 0.35795886 | K15: 100 | L15: 200 | M15: FP
A16: COMPL DEF Huurovereenkomst - Skybox - Pepperl+Fuchs - 20260204.pdf | C16: To Expire | H16: 0.9795376 | K16: 100 | M16: FN
A17: COMPL Huurovereenkomst - Stichting CCE - Kantoorgebouw Metzpoint I Dr. Holtroplaan - Fully Signed.pdf | C17: To Expire | H17: 0.9795376 | M17: TN
A18: COMPL Regel Partners - HOVK - Luchthavenweg 81 - 20260728.pdf | C18: To Expire | H18: 0.98206751
A19: COMPL_-_Onderhuurovereenkomst_Zelfstroom_B.V._-_50five_B.V._-_kantoorgebouw_Riva_-_05032026.pdf | C19: To Expire | H19: 0.98206751 | K19: Field: | L19: Lease_Comp_Details / arrangement_end_action_status_type_desc
A20: Den Bosch, Ruwekampweg 4, HOVK getekend.pdf | C20: To Expire | H20: 0.35726496
A21: FULLY SIGNED - COMPL Huurovereenkomst - Heijmans - Hugo de Grootlaan 23 's-Hertogenbosch V2 30-9-2025.pdf | C21: To Expire | H21: 0.9769684
A22: FULLY SIGNED - DEF_COMPL_Huurovereenkomst_Robo_Charge_-_Campus_Offices_-_20260220.pdf | C22: To Expire | H22: 0.35829616
A23: FULLY SIGNED - Onderhuurovereenkomst Aartshertogenlaan 223, `s-Hertogenbosch - Koning Willem I College B.V. 2606202.pdf | C23: To Expire | H23: 0.98455902
A24: FULLY SIGNED COMPL_DEF_Huurovereenkomst_Bond_Bergschot_Breda.pdf | C24: To Expire | H24: 0.35795886
A25: FullySigned_Allonge_II_Virtual_Vaults_Nederland.pdf | C25: To Expire | H25: 0.44542879
A26: FullySigned_Lease_Agreement_Neste_EDGE_Coolsingel.pdf | C26: To Expire | H26: 0.35795886
A27: HOK Waalhaven Group (signed).pdf | C27: To Expire | H27: 0.9795376
A28: Hovk Avans (3e+4e+5e verd.) 20140425.pdf | C28: To Expire | H28: 0.35829616
A29: HOVK Power4People 2025.pdf | C29: To Expire | H29: 0.9795376
A30: Huurovereenkomst (Semmie Group B.V.) - Wilhelminasingel 19, Breda.pdf | C30: To Expire | H30: 0.35829616
A31: Huurovereenkomst - proces-verbaal van oplevering - sleuteloverdracht - Kennedyplein 101 - getekend.pdf | C31: To Expire | H31: 0.98206751
... A36: MWO CBRE SPA (ITALY) CBRE_090724.pdf | C36: To Expire | H36: 0.9795376

Sheet Field 6
A1: Doc Name | B1: Manual Data | C1: Response Data | D1: Result | E1: Manual Pg | F1: Response Pg No | G1: Pg Result | H1: Confidence | K1: SUMMARY SHEET | N1: PAGE SUMMARY SHEET
A2: 20181204 Huurovereenkomst (GETEKEND).PDF | C2: 12/31/33 | H2: 0.98206751 | K2: Metrics | L2: Percentage | N2: Metrics | O2: Percentage
A3: 2024.10.30_Office Rental Agreement Labs_Gruyter Fabriek.pdf | C3: 12/31/29 | H3: 0.98206751 | K3: Precision | L3: =IFERROR(COUNTIFS(D2:D36,"TP")/(COUNTIFS(D2:D36,"TP")+COUNTIFS(D2:D36,"FP")),0) | N3: Precision | O3: =IFERROR(COUNTIFS(G2:G36,"TP")/(COUNTIFS(G2:G36,"TP")+COUNTIFS(G2:G36,"FP")),0)
A4: 20240606_HOK AKD - EDGE Eindhoven execution version.pdf | C4: 06/30/36 | H4: 0.92898348 | K4: Recall | L4: =IFERROR(COUNTIFS(D2:D36,"TP")/(COUNTIFS(D2:D36,"TP")+COUNTIFS(D2:D36,"FN")),0) | N4: Recall | O4: =IFERROR(COUNTIFS(G2:G36,"TP")/(COUNTIFS(G2:G36,"TP")+COUNTIFS(G2:G36,"FN")),0)
A5: 20250117_HOK Duke Strategies - Hambaken A.05.09 DEF FULLY SIGNED.pdf | C5: 02/16/26 | H5: 0.9795376 | K5: F1 Score | L5: =IFERROR(2*COUNTIFS(D2:D36,"TP")/(2*COUNTIFS(D2:D36,"TP")+COUNTIFS(D2:D36,"FP")+COUNTIFS(D2:D36,"FN")),0) | N5: F1 Score | O5: =IFERROR(2*COUNTIFS(G2:G36,"TP")/(2*COUNTIFS(G2:G36,"TP")+COUNTIFS(G2:G36,"FP")+COUNTIFS(G2:G36,"FN")),0)
A6: 20251216 Lease agreement ASPEN - signed.pdf | C6: 10/31/37 | H6: 0.93475936 | K6: Accuracy % (With Not Exist) | L6: =IFERROR((COUNTIF(D2:D36,"TP")+COUNTIF(D2:D36,"TN"))/SUM(COUNTIF(D2:D36,{"TP","TN","FP","FN"})),0) | N6: Accuracy % (With Not Exist) | O6: =IFERROR((COUNTIF(G2:G36,"TP")+COUNTIF(G2:G36,"TN"))/SUM(COUNTIF(G2:G36,{"TP","TN","FP","FN"})),0)
A7: 20260220 Huurovereenkomst signed 20-02-2026.pdf | C7: 03/01/28 | H7: 0.98206751 | K7: Total Docs Tested | L7: =COUNTA(A2:A36) | N7: Total Docs Tested | O7: =COUNTA(A2:A36)
A8: 20260629 HOK ADHDcentraal BV (1).pdf | C8: 08/31/30 | H8: 0.85993161 | K8: No Of Docs With Data | L8: =COUNTIFS(B2:B36,"<>",B2:B36,"<>N/A",B2:B36,"<>Not Present In the Document",B2:B36,"<>Not Found",B2:B36,"<>i dont know",B2:B36,"<>i don't know") | N8: No Of Docs With Manual Pg | O8: =COUNTIFS(E2:E36,"<>",E2:E36,"<>N/A",E2:E36,"<>Not Present In the Document",E2:E36,"<>Not Found",E2:E36,"<>i dont know",E2:E36,"<>i don't know")
A9: 20260807_Happy_Village_B.V._Lease_Maasstadweg_tekenversie_incl._bijlagen en-GB.pdf | C9: 01/01/34 | H9: 0.9795376 | K9: No Of Docs With Response | L9: =COUNTIFS(C2:C36,"<>") | N9: No Of Docs With Response Pg | O9: =COUNTIFS(F2:F36,"<>")
A10: 20260810 HOK ClustR BV.pdf | C10: 09/30/28 | H10: 0.83572523 | K10: Highlighted rows = file(s) not in the annotation sheet; excluded from all metrics above.
A11: 20270801 - Getekende Allonge II Advario BV.pdf | C11: 07/31/30 | H11: 0.9235264 | K11: Validation Rules Example
A12: 240119 HOVK Spoorlaan 446-448 Tilburg signed.pdf | C12: 03/31/27 | H12: 0.9795376 | K12: Manual Data | L12: Response Data | M12: Result
A13: 27001 Rijksvastgoedbedrijf Huurovereenkomst - __27-01-2026_9-07-56.pdf | C13: 12/31/27 | H13: 0.95 | K13: 100 | L13: 100 | M13: TP
A14: CBRE_AT_Services_ENG_-_RITUALS_CBRE signed.pdf | L14: 100 | M14: FP
A15: CBRE_Engagement_Letter_Alnylam_20260525_CLEAN_Version_signed all.pdf | C15: 03/06/26 | H15: 0.80545373 | K15: 100 | L15: 200 | M15: FP
A16: COMPL DEF Huurovereenkomst - Skybox - Pepperl+Fuchs - 20260204.pdf | C16: 11/30/31 | H16: 0.98206751 | K16: 100 | M16: FN
A17: COMPL Huurovereenkomst - Stichting CCE - Kantoorgebouw Metzpoint I Dr. Holtroplaan - Fully Signed.pdf | C17: 04/30/35 | H17: 0.96067416 | M17: TN
A18: COMPL Regel Partners - HOVK - Luchthavenweg 81 - 20260728.pdf | C18: 09/30/31 | H18: 0.76224699
A19: COMPL_-_Onderhuurovereenkomst_Zelfstroom_B.V._-_50five_B.V._-_kantoorgebouw_Riva_-_05032026.pdf | C19: 06/01/26 | H19: 0.98206751 | K19: Field: | L19: Lease_Comp_Details / arrangement_end_future_action_date
A20: Den Bosch, Ruwekampweg 4, HOVK getekend.pdf | C20: 12/31/21 | H20: 0.9235264
A21: FULLY SIGNED - COMPL Huurovereenkomst - Heijmans - Hugo de Grootlaan 23 's-Hertogenbosch V2 30-9-2025.pdf | C21: 09/30/26 | H21: 0.83195266
A22: FULLY SIGNED - DEF_COMPL_Huurovereenkomst_Robo_Charge_-_Campus_Offices_-_20260220.pdf | C22: 03/31/31 | H22: 0.81302871
A23: FULLY SIGNED - Onderhuurovereenkomst Aartshertogenlaan 223, `s-Hertogenbosch - Koning Willem I College B.V. 2606202.pdf | C23: 11/01/28 | H23: 0.73986755
A24: FULLY SIGNED COMPL_DEF_Huurovereenkomst_Bond_Bergschot_Breda.pdf | C24: 12/31/28 | H24: 0.98206751
A25: FullySigned_Allonge_II_Virtual_Vaults_Nederland.pdf | C25: 10/31/27 | H25: 0.97435897
A26: FullySigned_Lease_Agreement_Neste_EDGE_Coolsingel.pdf | C26: 07/31/37 | H26: 0.9235264
A27: HOK Waalhaven Group (signed).pdf | C27: 08/31/31 | H27: 0.65864874
A28: Hovk Avans (3e+4e+5e verd.) 20140425.pdf | C28: 06/30/19 | H28: 0.83572523
A29: HOVK Power4People 2025.pdf | C29: 06/30/26 | H29: 0.87268423
A30: Huurovereenkomst (Semmie Group B.V.) - Wilhelminasingel 19, Breda.pdf | C30: 04/30/29 | H30: 0.80784562
A31: Huurovereenkomst - proces-verbaal van oplevering - sleuteloverdracht - Kennedyplein 101 - getekend.pdf | C31: 02/28/29 | H31: 0.9795376
... A36: MWO CBRE SPA (ITALY) CBRE_090724.pdf | C36: 09/24/24 | H36: 0.90497238

Sheet Field 7
A1: Doc Name | B1: Manual Data | C1: Response Data | D1: Result | E1: Manual Pg | F1: Response Pg No | G1: Pg Result | H1: Confidence | K1: SUMMARY SHEET | N1: PAGE SUMMARY SHEET
A2: 20181204 Huurovereenkomst (GETEKEND).PDF | C2: To Be Revisited | H2: 0.96901563 | K2: Metrics | L2: Percentage | N2: Metrics | O2: Percentage
A3: 2024.10.30_Office Rental Agreement Labs_Gruyter Fabriek.pdf | C3: To Be Revisited | H3: 0.98455902 | K3: Precision | L3: =IFERROR(COUNTIFS(D2:D36,"TP")/(COUNTIFS(D2:D36,"TP")+COUNTIFS(D2:D36,"FP")),0) | N3: Precision | O3: =IFERROR(COUNTIFS(G2:G36,"TP")/(COUNTIFS(G2:G36,"TP")+COUNTIFS(G2:G36,"FP")),0)
A4: 20240606_HOK AKD - EDGE Eindhoven execution version.pdf | C4: To Be Revisited | H4: 0.9795376 | K4: Recall | L4: =IFERROR(COUNTIFS(D2:D36,"TP")/(COUNTIFS(D2:D36,"TP")+COUNTIFS(D2:D36,"FN")),0) | N4: Recall | O4: =IFERROR(COUNTIFS(G2:G36,"TP")/(COUNTIFS(G2:G36,"TP")+COUNTIFS(G2:G36,"FN")),0)
A5: 20250117_HOK Duke Strategies - Hambaken A.05.09 DEF FULLY SIGNED.pdf | C5: To Be Revisited | H5: 0.97435897 | K5: F1 Score | L5: =IFERROR(2*COUNTIFS(D2:D36,"TP")/(2*COUNTIFS(D2:D36,"TP")+COUNTIFS(D2:D36,"FP")+COUNTIFS(D2:D36,"FN")),0) | N5: F1 Score | O5: =IFERROR(2*COUNTIFS(G2:G36,"TP")/(2*COUNTIFS(G2:G36,"TP")+COUNTIFS(G2:G36,"FP")+COUNTIFS(G2:G36,"FN")),0)
A6: 20251216 Lease agreement ASPEN - signed.pdf | C6: To Be Revisited | H6: 0.98206751 | K6: Accuracy % (With Not Exist) | L6: =IFERROR((COUNTIF(D2:D36,"TP")+COUNTIF(D2:D36,"TN"))/SUM(COUNTIF(D2:D36,{"TP","TN","FP","FN"})),0) | N6: Accuracy % (With Not Exist) | O6: =IFERROR((COUNTIF(G2:G36,"TP")+COUNTIF(G2:G36,"TN"))/SUM(COUNTIF(G2:G36,{"TP","TN","FP","FN"})),0)
A7: 20260220 Huurovereenkomst signed 20-02-2026.pdf | C7: New Break Date | H7: 0.9795376 | K7: Total Docs Tested | L7: =COUNTA(A2:A36) | N7: Total Docs Tested | O7: =COUNTA(A2:A36)
A8: 20260629 HOK ADHDcentraal BV (1).pdf | C8: To Be Revisited | H8: 0.95287958 | K8: No Of Docs With Data | L8: =COUNTIFS(B2:B36,"<>",B2:B36,"<>N/A",B2:B36,"<>Not Present In the Document",B2:B36,"<>Not Found",B2:B36,"<>i dont know",B2:B36,"<>i don't know") | N8: No Of Docs With Manual Pg | O8: =COUNTIFS(E2:E36,"<>",E2:E36,"<>N/A",E2:E36,"<>Not Present In the Document",E2:E36,"<>Not Found",E2:E36,"<>i dont know",E2:E36,"<>i don't know")
A9: 20260807_Happy_Village_B.V._Lease_Maasstadweg_tekenversie_incl._bijlagen en-GB.pdf | C9: New Break Date | H9: 0.98455902 | K9: No Of Docs With Response | L9: =COUNTIFS(C2:C36,"<>") | N9: No Of Docs With Response Pg | O9: =COUNTIFS(F2:F36,"<>")
A10: 20260810 HOK ClustR BV.pdf | C10: To Be Revisited | H10: 0.98455902 | K10: Highlighted rows = file(s) not in the annotation sheet; excluded from all metrics above.
A11: 20270801 - Getekende Allonge II Advario BV.pdf | C11: To Be Revisited | H11: 0.59202899 | K11: Validation Rules Example
A12: 240119 HOVK Spoorlaan 446-448 Tilburg signed.pdf | C12: To Be Revisited | H12: 0.59202899 | K12: Manual Data | L12: Response Data | M12: Result
A13: 27001 Rijksvastgoedbedrijf Huurovereenkomst - __27-01-2026_9-07-56.pdf | C13: To Be Revisited | H13: 0.9795376 | K13: 100 | L13: 100 | M13: TP
A14: CBRE_AT_Services_ENG_-_RITUALS_CBRE signed.pdf | C14: To Be Revisited | H14: 0.97435897 | L14: 100 | M14: FP
A15: CBRE_Engagement_Letter_Alnylam_20260525_CLEAN_Version_signed all.pdf | C15: To Be Revisited | H15: 0.49178439 | K15: 100 | L15: 200 | M15: FP
A16: COMPL DEF Huurovereenkomst - Skybox - Pepperl+Fuchs - 20260204.pdf | C16: To Be Revisited | H16: 0.9795376 | K16: 100 | M16: FN
A17: COMPL Huurovereenkomst - Stichting CCE - Kantoorgebouw Metzpoint I Dr. Holtroplaan - Fully Signed.pdf | C17: To Be Revisited | H17: 0.98206751 | M17: TN
A18: COMPL Regel Partners - HOVK - Luchthavenweg 81 - 20260728.pdf | C18: To Be Revisited | H18: 0.9795376
A19: COMPL_-_Onderhuurovereenkomst_Zelfstroom_B.V._-_50five_B.V._-_kantoorgebouw_Riva_-_05032026.pdf | C19: To Be Revisited | H19: 0.98206751 | K19: Field: | L19: Lease_Comp_Details / arrangement_end_future_action_type_desc
A20: Den Bosch, Ruwekampweg 4, HOVK getekend.pdf | C20: New Break Date | H20: 0.98206751
A21: FULLY SIGNED - COMPL Huurovereenkomst - Heijmans - Hugo de Grootlaan 23 's-Hertogenbosch V2 30-9-2025.pdf | C21: To Be Revisited | H21: 0.9795376
A22: FULLY SIGNED - DEF_COMPL_Huurovereenkomst_Robo_Charge_-_Campus_Offices_-_20260220.pdf | C22: To Be Revisited | H22: 0.59486608
A23: FULLY SIGNED - Onderhuurovereenkomst Aartshertogenlaan 223, `s-Hertogenbosch - Koning Willem I College B.V. 2606202.pdf | C23: To Be Revisited | H23: 0.96627971
A24: FULLY SIGNED COMPL_DEF_Huurovereenkomst_Bond_Bergschot_Breda.pdf | C24: To Be Revisited | H24: 0.98206751
A25: FullySigned_Allonge_II_Virtual_Vaults_Nederland.pdf | C25: To Be Revisited | H25: 0.9795376
A26: FullySigned_Lease_Agreement_Neste_EDGE_Coolsingel.pdf | C26: To Be Revisited | H26: 0.49240838
A27: HOK Waalhaven Group (signed).pdf | C27: To Be Revisited | H27: 0.9795376
A28: Hovk Avans (3e+4e+5e verd.) 20140425.pdf | C28: To Be Revisited | H28: 0.59202899
A29: HOVK Power4People 2025.pdf | C29: To Be Revisited | H29: 0.98206751
A30: Huurovereenkomst (Semmie Group B.V.) - Wilhelminasingel 19, Breda.pdf | C30: To Be Revisited | H30: 0.98206751
A31: Huurovereenkomst - proces-verbaal van oplevering - sleuteloverdracht - Kennedyplein 101 - getekend.pdf | C31: To Be Revisited | H31: 0.9795376
... A36: MWO CBRE SPA (ITALY) CBRE_090724.pdf | C36: To Be Revisited | H36: 0.9795376

Sheet Field 8
A1: Doc Name | B1: Manual Data | C1: Response Data | D1: Result | E1: Manual Pg | F1: Response Pg No | G1: Pg Result | H1: Confidence | K1: SUMMARY SHEET | N1: PAGE SUMMARY SHEET
A2: 20181204 Huurovereenkomst (GETEKEND).PDF | C2: New Establishment | H2: 0.51365517 | K2: Metrics | L2: Percentage | N2: Metrics | O2: Percentage
A3: 2024.10.30_Office Rental Agreement Labs_Gruyter Fabriek.pdf | C3: New Establishment | H3: 0.24370013 | K3: Precision | L3: =IFERROR(COUNTIFS(D2:D36,"TP")/(COUNTIFS(D2:D36,"TP")+COUNTIFS(D2:D36,"FP")),0) | N3: Precision | O3: =IFERROR(COUNTIFS(G2:G36,"TP")/(COUNTIFS(G2:G36,"TP")+COUNTIFS(G2:G36,"FP")),0)
A4: 20240606_HOK AKD - EDGE Eindhoven execution version.pdf | C4: Business Continuity | H4: 0.56552771 | K4: Recall | L4: =IFERROR(COUNTIFS(D2:D36,"TP")/(COUNTIFS(D2:D36,"TP")+COUNTIFS(D2:D36,"FN")),0) | N4: Recall | O4: =IFERROR(COUNTIFS(G2:G36,"TP")/(COUNTIFS(G2:G36,"TP")+COUNTIFS(G2:G36,"FN")),0)
A5: 20250117_HOK Duke Strategies - Hambaken A.05.09 DEF FULLY SIGNED.pdf | C5: New Establishment | H5: 0.50774125 | K5: F1 Score | L5: =IFERROR(2*COUNTIFS(D2:D36,"TP")/(2*COUNTIFS(D2:D36,"TP")+COUNTIFS(D2:D36,"FP")+COUNTIFS(D2:D36,"FN")),0) | N5: F1 Score | O5: =IFERROR(2*COUNTIFS(G2:G36,"TP")/(2*COUNTIFS(G2:G36,"TP")+COUNTIFS(G2:G36,"FP")+COUNTIFS(G2:G36,"FN")),0)
A6: 20251216 Lease agreement ASPEN - signed.pdf | C6: Relocation | H6: 0.98206751 | K6: Accuracy % (With Not Exist) | L6: =IFERROR((COUNTIF(D2:D36,"TP")+COUNTIF(D2:D36,"TN"))/SUM(COUNTIF(D2:D36,{"TP","TN","FP","FN"})),0) | N6: Accuracy % (With Not Exist) | O6: =IFERROR((COUNTIF(G2:G36,"TP")+COUNTIF(G2:G36,"TN"))/SUM(COUNTIF(G2:G36,{"TP","TN","FP","FN"})),0)
A7: 20260220 Huurovereenkomst signed 20-02-2026.pdf | C7: New Establishment | H7: 0.96349958 | K7: Total Docs Tested | L7: =COUNTA(A2:A36) | N7: Total Docs Tested | O7: =COUNTA(A2:A36)
A8: 20260629 HOK ADHDcentraal BV (1).pdf | C8: Business Continuity | H8: 0.44435484 | K8: No Of Docs With Data | L8: =COUNTIFS(B2:B36,"<>",B2:B36,"<>N/A",B2:B36,"<>Not Present In the Document",B2:B36,"<>Not Found",B2:B36,"<>i dont know",B2:B36,"<>i don't know") | N8: No Of Docs With Manual Pg | O8: =COUNTIFS(E2:E36,"<>",E2:E36,"<>N/A",E2:E36,"<>Not Present In the Document",E2:E36,"<>Not Found",E2:E36,"<>i dont know",E2:E36,"<>i don't know")
A9: 20260807_Happy_Village_B.V._Lease_Maasstadweg_tekenversie_incl._bijlagen en-GB.pdf | C9: Unknown | H9: 0.24266667 | K9: No Of Docs With Response | L9: =COUNTIFS(C2:C36,"<>") | N9: No Of Docs With Response Pg | O9: =COUNTIFS(F2:F36,"<>")
A10: 20260810 HOK ClustR BV.pdf | C10: New Establishment | H10: 0.9769684 | K10: Highlighted rows = file(s) not in the annotation sheet; excluded from all metrics above.
A11: 20270801 - Getekende Allonge II Advario BV.pdf | C11: Business Continuity | H11: 0.9795376 | K11: Validation Rules Example
A12: 240119 HOVK Spoorlaan 446-448 Tilburg signed.pdf | C12: New Establishment | H12: 0.24352672 | K12: Manual Data | L12: Response Data | M12: Result
A13: 27001 Rijksvastgoedbedrijf Huurovereenkomst - __27-01-2026_9-07-56.pdf | C13: Business Continuity | H13: 0.98455902 | K13: 100 | L13: 100 | M13: TP
A14: CBRE_AT_Services_ENG_-_RITUALS_CBRE signed.pdf | C14: New Establishment | H14: 0.44595119 | L14: 100 | M14: FP
A15: CBRE_Engagement_Letter_Alnylam_20260525_CLEAN_Version_signed all.pdf | C15: Relocation | H15: 0.9795376 | K15: 100 | L15: 200 | M15: FP
A16: COMPL DEF Huurovereenkomst - Skybox - Pepperl+Fuchs - 20260204.pdf | C16: Unknown | H16: 0.24266667 | K16: 100 | M16: FN
A17: COMPL Huurovereenkomst - Stichting CCE - Kantoorgebouw Metzpoint I Dr. Holtroplaan - Fully Signed.pdf | C17: New Establishment | H17: 0.2440367 | M17: TN
A18: COMPL Regel Partners - HOVK - Luchthavenweg 81 - 20260728.pdf | C18: Business Continuity | H18: 0.4426669
A19: COMPL_-_Onderhuurovereenkomst_Zelfstroom_B.V._-_50five_B.V._-_kantoorgebouw_Riva_-_05032026.pdf | C19: Business Continuity | H19: 0.97435897 | K19: Field: | L19: Lease_Comp_Details / lease_arrangement_reason_type_desc
A20: Den Bosch, Ruwekampweg 4, HOVK getekend.pdf | C20: Business Continuity | H20: 0.44435484
A21: FULLY SIGNED - COMPL Huurovereenkomst - Heijmans - Hugo de Grootlaan 23 's-Hertogenbosch V2 30-9-2025.pdf | C21: Unknown | H21: 0.43983333
A22: FULLY SIGNED - DEF_COMPL_Huurovereenkomst_Robo_Charge_-_Campus_Offices_-_20260220.pdf | C22: New Establishment | H22: 0.2440367
A23: FULLY SIGNED - Onderhuurovereenkomst Aartshertogenlaan 223, `s-Hertogenbosch - Koning Willem I College B.V. 2606202.pdf | C23: Business Continuity | H23: 0.97435897
A24: FULLY SIGNED COMPL_DEF_Huurovereenkomst_Bond_Bergschot_Breda.pdf | C24: Unknown | H24: 0.24266667
A25: FullySigned_Allonge_II_Virtual_Vaults_Nederland.pdf | C25: Business Continuity | H25: 0.98455902
A26: FullySigned_Lease_Agreement_Neste_EDGE_Coolsingel.pdf | C26: Unknown | H26: 0.24266667
A27: HOK Waalhaven Group (signed).pdf | C27: Unknown | H27: 0.43983333
A28: Hovk Avans (3e+4e+5e verd.) 20140425.pdf | C28: Business Continuity | H28: 0.44542879
A29: HOVK Power4People 2025.pdf | C29: New Establishment | H29: 0.98206751
A30: Huurovereenkomst (Semmie Group B.V.) - Wilhelminasingel 19, Breda.pdf | C30: New Establishment | H30: 0.2440367
A31: Huurovereenkomst - proces-verbaal van oplevering - sleuteloverdracht - Kennedyplein 101 - getekend.pdf | C31: Business Continuity | H31: 0.9795376
... A36: MWO CBRE SPA (ITALY) CBRE_090724.pdf | C36: New Establishment | H36: 0.96901563

Sheet Field 9
A1: Doc Name | B1: Manual Data | C1: Response Data | D1: Result | E1: Manual Pg | F1: Response Pg No | G1: Pg Result | H1: Confidence | K1: SUMMARY SHEET | N1: PAGE SUMMARY SHEET
A2: 20181204 Huurovereenkomst (GETEKEND).PDF | C2: New Lease | H2: 0.98455902 | K2: Metrics | L2: Percentage | N2: Metrics | O2: Percentage
A3: 2024.10.30_Office Rental Agreement Labs_Gruyter Fabriek.pdf | C3: New Lease | H3: 0.98455902 | K3: Precision | L3: =IFERROR(COUNTIFS(D2:D36,"TP")/(COUNTIFS(D2:D36,"TP")+COUNTIFS(D2:D36,"FP")),0) | N3: Precision | O3: =IFERROR(COUNTIFS(G2:G36,"TP")/(COUNTIFS(G2:G36,"TP")+COUNTIFS(G2:G36,"FP")),0)
A4: 20240606_HOK AKD - EDGE Eindhoven execution version.pdf | C4: Pre-Lease | H4: 0.98206751 | K4: Recall | L4: =IFERROR(COUNTIFS(D2:D36,"TP")/(COUNTIFS(D2:D36,"TP")+COUNTIFS(D2:D36,"FN")),0) | N4: Recall | O4: =IFERROR(COUNTIFS(G2:G36,"TP")/(COUNTIFS(G2:G36,"TP")+COUNTIFS(G2:G36,"FN")),0)
A5: 20250117_HOK Duke Strategies - Hambaken A.05.09 DEF FULLY SIGNED.pdf | C5: New Lease | H5: 0.98206751 | K5: F1 Score | L5: =IFERROR(2*COUNTIFS(D2:D36,"TP")/(2*COUNTIFS(D2:D36,"TP")+COUNTIFS(D2:D36,"FP")+COUNTIFS(D2:D36,"FN")),0) | N5: F1 Score | O5: =IFERROR(2*COUNTIFS(G2:G36,"TP")/(2*COUNTIFS(G2:G36,"TP")+COUNTIFS(G2:G36,"FP")+COUNTIFS(G2:G36,"FN")),0)
A6: 20251216 Lease agreement ASPEN - signed.pdf | C6: Pre-Lease | H6: 0.98206751 | K6: Accuracy % (With Not Exist) | L6: =IFERROR((COUNTIF(D2:D36,"TP")+COUNTIF(D2:D36,"TN"))/SUM(COUNTIF(D2:D36,{"TP","TN","FP","FN"})),0) | N6: Accuracy % (With Not Exist) | O6: =IFERROR((COUNTIF(G2:G36,"TP")+COUNTIF(G2:G36,"TN"))/SUM(COUNTIF(G2:G36,{"TP","TN","FP","FN"})),0)
A7: 20260220 Huurovereenkomst signed 20-02-2026.pdf | C7: New Lease | H7: 0.98206751 | K7: Total Docs Tested | L7: =COUNTA(A2:A36) | N7: Total Docs Tested | O7: =COUNTA(A2:A36)
A8: 20260629 HOK ADHDcentraal BV (1).pdf | C8: New Lease | H8: 0.98206751 | K8: No Of Docs With Data | L8: =COUNTIFS(B2:B36,"<>",B2:B36,"<>N/A",B2:B36,"<>Not Present In the Document",B2:B36,"<>Not Found",B2:B36,"<>i dont know",B2:B36,"<>i don't know") | N8: No Of Docs With Manual Pg | O8: =COUNTIFS(E2:E36,"<>",E2:E36,"<>N/A",E2:E36,"<>Not Present In the Document",E2:E36,"<>Not Found",E2:E36,"<>i dont know",E2:E36,"<>i don't know")
A9: 20260807_Happy_Village_B.V._Lease_Maasstadweg_tekenversie_incl._bijlagen en-GB.pdf | C9: New Lease | H9: 0.98455902 | K9: No Of Docs With Response | L9: =COUNTIFS(C2:C36,"<>") | N9: No Of Docs With Response Pg | O9: =COUNTIFS(F2:F36,"<>")
A10: 20260810 HOK ClustR BV.pdf | C10: New Lease | H10: 0.98206751 | K10: Highlighted rows = file(s) not in the annotation sheet; excluded from all metrics above.
A11: 20270801 - Getekende Allonge II Advario BV.pdf | C11: Renewal | H11: 0.98455902 | K11: Validation Rules Example
A12: 240119 HOVK Spoorlaan 446-448 Tilburg signed.pdf | C12: New Lease | H12: 0.98455902 | K12: Manual Data | L12: Response Data | M12: Result
A13: 27001 Rijksvastgoedbedrijf Huurovereenkomst - __27-01-2026_9-07-56.pdf | C13: New Lease | H13: 0.98455902 | K13: 100 | L13: 100 | M13: TP
A14: CBRE_AT_Services_ENG_-_RITUALS_CBRE signed.pdf | C14: New Lease | H14: 0.98206751 | L14: 100 | M14: FP
A15: CBRE_Engagement_Letter_Alnylam_20260525_CLEAN_Version_signed all.pdf | C15: New Lease | H15: 0.98206751 | K15: 100 | L15: 200 | M15: FP
A16: COMPL DEF Huurovereenkomst - Skybox - Pepperl+Fuchs - 20260204.pdf | C16: New Lease | H16: 0.98455902 | K16: 100 | M16: FN
A17: COMPL Huurovereenkomst - Stichting CCE - Kantoorgebouw Metzpoint I Dr. Holtroplaan - Fully Signed.pdf | C17: New Lease | H17: 0.98455902 | M17: TN
A18: COMPL Regel Partners - HOVK - Luchthavenweg 81 - 20260728.pdf | C18: New Lease | H18: 0.98455902
A19: COMPL_-_Onderhuurovereenkomst_Zelfstroom_B.V._-_50five_B.V._-_kantoorgebouw_Riva_-_05032026.pdf | C19: New Lease | H19: 0.98455902 | K19: Field: | L19: Lease_Comp_Details / ref_lease_activity_type_desc
A20: Den Bosch, Ruwekampweg 4, HOVK getekend.pdf | C20: New Lease | H20: 0.98206751
A21: FULLY SIGNED - COMPL Huurovereenkomst - Heijmans - Hugo de Grootlaan 23 's-Hertogenbosch V2 30-9-2025.pdf | C21: New Lease | H21: 0.98455902
A22: FULLY SIGNED - DEF_COMPL_Huurovereenkomst_Robo_Charge_-_Campus_Offices_-_20260220.pdf | C22: New Lease | H22: 0.98455902
A23: FULLY SIGNED - Onderhuurovereenkomst Aartshertogenlaan 223, `s-Hertogenbosch - Koning Willem I College B.V. 2606202.pdf | C23: New Lease | H23: 0.98206751
A24: FULLY SIGNED COMPL_DEF_Huurovereenkomst_Bond_Bergschot_Breda.pdf | C24: New Lease | H24: 0.98455902
A25: FullySigned_Allonge_II_Virtual_Vaults_Nederland.pdf | C25: Renewal | H25: 0.98455902
A26: FullySigned_Lease_Agreement_Neste_EDGE_Coolsingel.pdf | C26: New Lease | H26: 0.98455902
A27: HOK Waalhaven Group (signed).pdf | C27: New Lease | H27: 0.98455902
A28: Hovk Avans (3e+4e+5e verd.) 20140425.pdf | C28: New Lease | H28: 0.9795376
A29: HOVK Power4People 2025.pdf | C29: New Lease | H29: 0.98455902
A30: Huurovereenkomst (Semmie Group B.V.) - Wilhelminasingel 19, Breda.pdf | C30: New Lease | H30: 0.98455902
A31: Huurovereenkomst - proces-verbaal van oplevering - sleuteloverdracht - Kennedyplein 101 - getekend.pdf | C31: New Lease | H31: 0.98206751
... A36: MWO CBRE SPA (ITALY) CBRE_090724.pdf | C36: New Lease | H36: 0.81624977

Sheet Field 10
A1: Doc Name | B1: Manual Data | C1: Response Data | D1: Result | E1: Manual Pg | F1: Response Pg No | G1: Pg Result | H1: Confidence | K1: SUMMARY SHEET | N1: PAGE SUMMARY SHEET
A2: 20181204 Huurovereenkomst (GETEKEND).PDF | C2: Direct | H2: 0.98455902 | K2: Metrics | L2: Percentage | N2: Metrics | O2: Percentage
A3: 2024.10.30_Office Rental Agreement Labs_Gruyter Fabriek.pdf | C3: Direct | H3: 0.97435897 | K3: Precision | L3: =IFERROR(COUNTIFS(D2:D36,"TP")/(COUNTIFS(D2:D36,"TP")+COUNTIFS(D2:D36,"FP")),0) | N3: Precision | O3: =IFERROR(COUNTIFS(G2:G36,"TP")/(COUNTIFS(G2:G36,"TP")+COUNTIFS(G2:G36,"FP")),0)
A4: 20240606_HOK AKD - EDGE Eindhoven execution version.pdf | C4: Direct | H4: 0.97435897 | K4: Recall | L4: =IFERROR(COUNTIFS(D2:D36,"TP")/(COUNTIFS(D2:D36,"TP")+COUNTIFS(D2:D36,"FN")),0) | N4: Recall | O4: =IFERROR(COUNTIFS(G2:G36,"TP")/(COUNTIFS(G2:G36,"TP")+COUNTIFS(G2:G36,"FN")),0)
A5: 20250117_HOK Duke Strategies - Hambaken A.05.09 DEF FULLY SIGNED.pdf | C5: Direct | H5: 0.2892799 | K5: F1 Score | L5: =IFERROR(2*COUNTIFS(D2:D36,"TP")/(2*COUNTIFS(D2:D36,"TP")+COUNTIFS(D2:D36,"FP")+COUNTIFS(D2:D36,"FN")),0) | N5: F1 Score | O5: =IFERROR(2*COUNTIFS(G2:G36,"TP")/(2*COUNTIFS(G2:G36,"TP")+COUNTIFS(G2:G36,"FP")+COUNTIFS(G2:G36,"FN")),0)
A6: 20251216 Lease agreement ASPEN - signed.pdf | C6: Direct | H6: 0.98455902 | K6: Accuracy % (With Not Exist) | L6: =IFERROR((COUNTIF(D2:D36,"TP")+COUNTIF(D2:D36,"TN"))/SUM(COUNTIF(D2:D36,{"TP","TN","FP","FN"})),0) | N6: Accuracy % (With Not Exist) | O6: =IFERROR((COUNTIF(G2:G36,"TP")+COUNTIF(G2:G36,"TN"))/SUM(COUNTIF(G2:G36,{"TP","TN","FP","FN"})),0)
A7: 20260220 Huurovereenkomst signed 20-02-2026.pdf | C7: Direct | H7: 0.97435897 | K7: Total Docs Tested | L7: =COUNTA(A2:A36) | N7: Total Docs Tested | O7: =COUNTA(A2:A36)
A8: 20260629 HOK ADHDcentraal BV (1).pdf | C8: Direct | H8: 0.2892799 | K8: No Of Docs With Data | L8: =COUNTIFS(B2:B36,"<>",B2:B36,"<>N/A",B2:B36,"<>Not Present In the Document",B2:B36,"<>Not Found",B2:B36,"<>i dont know",B2:B36,"<>i don't know") | N8: No Of Docs With Manual Pg | O8: =COUNTIFS(E2:E36,"<>",E2:E36,"<>N/A",E2:E36,"<>Not Present In the Document",E2:E36,"<>Not Found",E2:E36,"<>i dont know",E2:E36,"<>i don't know")
A9: 20260807_Happy_Village_B.V._Lease_Maasstadweg_tekenversie_incl._bijlagen en-GB.pdf | C9: Direct | H9: 0.97435897 | K9: No Of Docs With Response | L9: =COUNTIFS(C2:C36,"<>") | N9: No Of Docs With Response Pg | O9: =COUNTIFS(F2:F36,"<>")
A10: 20260810 HOK ClustR BV.pdf | C10: Direct | H10: 0.2892799 | K10: Highlighted rows = file(s) not in the annotation sheet; excluded from all metrics above.
A11: 20270801 - Getekende Allonge II Advario BV.pdf | C11: Direct | H11: 0.98206751 | K11: Validation Rules Example
A12: 240119 HOVK Spoorlaan 446-448 Tilburg signed.pdf | C12: Direct | H12: 0.97435897 | K12: Manual Data | L12: Response Data | M12: Result
A13: 27001 Rijksvastgoedbedrijf Huurovereenkomst - __27-01-2026_9-07-56.pdf | C13: Direct | H13: 0.98455902 | K13: 100 | L13: 100 | M13: TP
A14: CBRE_AT_Services_ENG_-_RITUALS_CBRE signed.pdf | C14: Direct | H14: 0.9795376 | L14: 100 | M14: FP
A15: CBRE_Engagement_Letter_Alnylam_20260525_CLEAN_Version_signed all.pdf | C15: Direct | H15: 0.97435897 | K15: 100 | L15: 200 | M15: FP
A16: COMPL DEF Huurovereenkomst - Skybox - Pepperl+Fuchs - 20260204.pdf | C16: Direct | H16: 0.98455902 | K16: 100 | M16: FN
A17: COMPL Huurovereenkomst - Stichting CCE - Kantoorgebouw Metzpoint I Dr. Holtroplaan - Fully Signed.pdf | C17: Direct | H17: 0.97435897 | M17: TN
A18: COMPL Regel Partners - HOVK - Luchthavenweg 81 - 20260728.pdf | C18: Direct | H18: 0.98455902
A19: COMPL_-_Onderhuurovereenkomst_Zelfstroom_B.V._-_50five_B.V._-_kantoorgebouw_Riva_-_05032026.pdf | C19: SubLease | H19: 0.97435897 | K19: Field: | L19: Lease_Comp_Details / ref_lease_arrangement_type_desc
A20: Den Bosch, Ruwekampweg 4, HOVK getekend.pdf | C20: Direct | H20: 0.98455902
A21: FULLY SIGNED - COMPL Huurovereenkomst - Heijmans - Hugo de Grootlaan 23 's-Hertogenbosch V2 30-9-2025.pdf | C21: SubLease | H21: 0.98455902
A22: FULLY SIGNED - DEF_COMPL_Huurovereenkomst_Robo_Charge_-_Campus_Offices_-_20260220.pdf | C22: Direct | H22: 0.98455902
A23: FULLY SIGNED - Onderhuurovereenkomst Aartshertogenlaan 223, `s-Hertogenbosch - Koning Willem I College B.V. 2606202.pdf | C23: SubLease | H23: 0.98455902
A24: FULLY SIGNED COMPL_DEF_Huurovereenkomst_Bond_Bergschot_Breda.pdf | C24: Direct | H24: 0.98455902
A25: FullySigned_Allonge_II_Virtual_Vaults_Nederland.pdf | C25: Assignment | H25: 0.49240838
A26: FullySigned_Lease_Agreement_Neste_EDGE_Coolsingel.pdf | C26: Direct | H26: 0.98455902
A27: HOK Waalhaven Group (signed).pdf | C27: Direct | H27: 0.98455902
A28: Hovk Avans (3e+4e+5e verd.) 20140425.pdf | C28: Direct | H28: 0.98455902
A29: HOVK Power4People 2025.pdf | C29: Flex Lease | H29: 0.97347236
A30: Huurovereenkomst (Semmie Group B.V.) - Wilhelminasingel 19, Breda.pdf | C30: Direct | H30: 0.97435897
A31: Huurovereenkomst - proces-verbaal van oplevering - sleuteloverdracht - Kennedyplein 101 - getekend.pdf | C31: Direct | H31: 0.98206751
... A36: MWO CBRE SPA (ITALY) CBRE_090724.pdf | C36: Direct | H36: 0.98206751

Sheet Field 11
A1: Doc Name | B1: Manual Data | C1: Response Data | D1: Result | E1: Manual Pg | F1: Response Pg No | G1: Pg Result | H1: Confidence | K1: SUMMARY SHEET | N1: PAGE SUMMARY SHEET
A2: 20181204 Huurovereenkomst (GETEKEND).PDF | C2: SqM | H2: 0.96476684 | K2: Metrics | L2: Percentage | N2: Metrics | O2: Percentage
A3: 2024.10.30_Office Rental Agreement Labs_Gruyter Fabriek.pdf | C3: SqM | H3: 0.97435897 | K3: Precision | L3: =IFERROR(COUNTIFS(D2:D36,"TP")/(COUNTIFS(D2:D36,"TP")+COUNTIFS(D2:D36,"FP")),0) | N3: Precision | O3: =IFERROR(COUNTIFS(G2:G36,"TP")/(COUNTIFS(G2:G36,"TP")+COUNTIFS(G2:G36,"FP")),0)
A4: 20240606_HOK AKD - EDGE Eindhoven execution version.pdf | C4: SqM | H4: 0.97435897 | K4: Recall | L4: =IFERROR(COUNTIFS(D2:D36,"TP")/(COUNTIFS(D2:D36,"TP")+COUNTIFS(D2:D36,"FN")),0) | N4: Recall | O4: =IFERROR(COUNTIFS(G2:G36,"TP")/(COUNTIFS(G2:G36,"TP")+COUNTIFS(G2:G36,"FN")),0)
A5: 20250117_HOK Duke Strategies - Hambaken A.05.09 DEF FULLY SIGNED.pdf | C5: SqM | H5: 0.98455902 | K5: F1 Score | L5: =IFERROR(2*COUNTIFS(D2:D36,"TP")/(2*COUNTIFS(D2:D36,"TP")+COUNTIFS(D2:D36,"FP")+COUNTIFS(D2:D36,"FN")),0) | N5: F1 Score | O5: =IFERROR(2*COUNTIFS(G2:G36,"TP")/(2*COUNTIFS(G2:G36,"TP")+COUNTIFS(G2:G36,"FP")+COUNTIFS(G2:G36,"FN")),0)
A6: 20251216 Lease agreement ASPEN - signed.pdf | C6: SqM | H6: 0.97435897 | K6: Accuracy % (With Not Exist) | L6: =IFERROR((COUNTIF(D2:D36,"TP")+COUNTIF(D2:D36,"TN"))/SUM(COUNTIF(D2:D36,{"TP","TN","FP","FN"})),0) | N6: Accuracy % (With Not Exist) | O6: =IFERROR((COUNTIF(G2:G36,"TP")+COUNTIF(G2:G36,"TN"))/SUM(COUNTIF(G2:G36,{"TP","TN","FP","FN"})),0)
A7: 20260220 Huurovereenkomst signed 20-02-2026.pdf | C7: SqM | H7: 0.97435897 | K7: Total Docs Tested | L7: =COUNTA(A2:A36) | N7: Total Docs Tested | O7: =COUNTA(A2:A36)
A8: 20260629 HOK ADHDcentraal BV (1).pdf | C8: SqM | H8: 0.98455902 | K8: No Of Docs With Data | L8: =COUNTIFS(B2:B36,"<>",B2:B36,"<>N/A",B2:B36,"<>Not Present In the Document",B2:B36,"<>Not Found",B2:B36,"<>i dont know",B2:B36,"<>i don't know") | N8: No Of Docs With Manual Pg | O8: =COUNTIFS(E2:E36,"<>",E2:E36,"<>N/A",E2:E36,"<>Not Present In the Document",E2:E36,"<>Not Found",E2:E36,"<>i dont know",E2:E36,"<>i don't know")
A9: 20260807_Happy_Village_B.V._Lease_Maasstadweg_tekenversie_incl._bijlagen en-GB.pdf | C9: SqM | H9: 0.98455902 | K9: No Of Docs With Response | L9: =COUNTIFS(C2:C36,"<>") | N9: No Of Docs With Response Pg | O9: =COUNTIFS(F2:F36,"<>")
A10: 20260810 HOK ClustR BV.pdf | C10: SqM | H10: 0.97435897 | K10: Highlighted rows = file(s) not in the annotation sheet; excluded from all metrics above.
A11: 20270801 - Getekende Allonge II Advario BV.pdf | C11: SqM | H11: 0.97435897 | K11: Validation Rules Example
A12: 240119 HOVK Spoorlaan 446-448 Tilburg signed.pdf | C12: SqM | H12: 0.98455902 | K12: Manual Data | L12: Response Data | M12: Result
A13: 27001 Rijksvastgoedbedrijf Huurovereenkomst - __27-01-2026_9-07-56.pdf | C13: SqM | H13: 0.97435897 | K13: 100 | L13: 100 | M13: TP
A14: CBRE_AT_Services_ENG_-_RITUALS_CBRE signed.pdf | C14: SqM | H14: 0.98455902 | L14: 100 | M14: FP
A15: CBRE_Engagement_Letter_Alnylam_20260525_CLEAN_Version_signed all.pdf | C15: SqM | H15: 0.98455902 | K15: 100 | L15: 200 | M15: FP
A16: COMPL DEF Huurovereenkomst - Skybox - Pepperl+Fuchs - 20260204.pdf | C16: SqM | H16: 0.97435897 | K16: 100 | M16: FN
A17: COMPL Huurovereenkomst - Stichting CCE - Kantoorgebouw Metzpoint I Dr. Holtroplaan - Fully Signed.pdf | C17: SqM | H17: 0.98455902 | M17: TN
A18: COMPL Regel Partners - HOVK - Luchthavenweg 81 - 20260728.pdf | C18: SqM | H18: 0.97435897
A19: COMPL_-_Onderhuurovereenkomst_Zelfstroom_B.V._-_50five_B.V._-_kantoorgebouw_Riva_-_05032026.pdf | C19: SqM | H19: 0.98455902 | K19: Field: | L19: Lease_Comp_Details / ref_total_leased_space_uom_desc
A20: Den Bosch, Ruwekampweg 4, HOVK getekend.pdf | C20: SqM | H20: 0.97435897
A21: FULLY SIGNED - COMPL Huurovereenkomst - Heijmans - Hugo de Grootlaan 23 's-Hertogenbosch V2 30-9-2025.pdf | C21: SqM | H21: 0.98455902
A22: FULLY SIGNED - DEF_COMPL_Huurovereenkomst_Robo_Charge_-_Campus_Offices_-_20260220.pdf | C22: SqM | H22: 0.98455902
A23: FULLY SIGNED - Onderhuurovereenkomst Aartshertogenlaan 223, `s-Hertogenbosch - Koning Willem I College B.V. 2606202.pdf | C23: SqM | H23: 0.98455902
A24: FULLY SIGNED COMPL_DEF_Huurovereenkomst_Bond_Bergschot_Breda.pdf | C24: SqM | H24: 0.97435897
A25: FullySigned_Allonge_II_Virtual_Vaults_Nederland.pdf | C25: SqM | H25: 0.98455902
A26: FullySigned_Lease_Agreement_Neste_EDGE_Coolsingel.pdf | C26: SqM | H26: 0.97435897
A27: HOK Waalhaven Group (signed).pdf | C27: SqM | H27: 0.97435897
A28: Hovk Avans (3e+4e+5e verd.) 20140425.pdf | C28: SqM | H28: 0.97435897
A29: HOVK Power4People 2025.pdf | C29: SqM | H29: 0.94497354
A30: Huurovereenkomst (Semmie Group B.V.) - Wilhelminasingel 19, Breda.pdf | C30: SqM | H30: 0.97435897
A31: Huurovereenkomst - proces-verbaal van oplevering - sleuteloverdracht - Kennedyplein 101 - getekend.pdf | C31: SqM | H31: 0.98455902
... A36: MWO CBRE SPA (ITALY) CBRE_090724.pdf | C36: SqM | H36: 0.95

Sheet Field 12
A1: Doc Name | B1: Manual Data | C1: Response Data | D1: Result | E1: Manual Pg | F1: Response Pg No | G1: Pg Result | H1: Confidence | K1: SUMMARY SHEET | N1: PAGE SUMMARY SHEET
A2: 20181204 Huurovereenkomst (GETEKEND).PDF | C2: Core And Shell | H2: 0.45657071 | K2: Metrics | L2: Percentage | N2: Metrics | O2: Percentage
A3: 2024.10.30_Office Rental Agreement Labs_Gruyter Fabriek.pdf | C3: Fitted Out | H3: 0.97435897 | K3: Precision | L3: =IFERROR(COUNTIFS(D2:D36,"TP")/(COUNTIFS(D2:D36,"TP")+COUNTIFS(D2:D36,"FP")),0) | N3: Precision | O3: =IFERROR(COUNTIFS(G2:G36,"TP")/(COUNTIFS(G2:G36,"TP")+COUNTIFS(G2:G36,"FP")),0)
A4: 20240606_HOK AKD - EDGE Eindhoven execution version.pdf | C4: Core And Shell | H4: 0.9795376 | K4: Recall | L4: =IFERROR(COUNTIFS(D2:D36,"TP")/(COUNTIFS(D2:D36,"TP")+COUNTIFS(D2:D36,"FN")),0) | N4: Recall | O4: =IFERROR(COUNTIFS(G2:G36,"TP")/(COUNTIFS(G2:G36,"TP")+COUNTIFS(G2:G36,"FN")),0)
A5: 20250117_HOK Duke Strategies - Hambaken A.05.09 DEF FULLY SIGNED.pdf | C5: Fitted Out | H5: 0.98206751 | K5: F1 Score | L5: =IFERROR(2*COUNTIFS(D2:D36,"TP")/(2*COUNTIFS(D2:D36,"TP")+COUNTIFS(D2:D36,"FP")+COUNTIFS(D2:D36,"FN")),0) | N5: F1 Score | O5: =IFERROR(2*COUNTIFS(G2:G36,"TP")/(2*COUNTIFS(G2:G36,"TP")+COUNTIFS(G2:G36,"FP")+COUNTIFS(G2:G36,"FN")),0)
A6: 20251216 Lease agreement ASPEN - signed.pdf | C6: Fitted Out | H6: 0.21282746 | K6: Accuracy % (With Not Exist) | L6: =IFERROR((COUNTIF(D2:D36,"TP")+COUNTIF(D2:D36,"TN"))/SUM(COUNTIF(D2:D36,{"TP","TN","FP","FN"})),0) | N6: Accuracy % (With Not Exist) | O6: =IFERROR((COUNTIF(G2:G36,"TP")+COUNTIF(G2:G36,"TN"))/SUM(COUNTIF(G2:G36,{"TP","TN","FP","FN"})),0)
A7: 20260220 Huurovereenkomst signed 20-02-2026.pdf | C7: Fitted Out | H7: 0.98455902 | K7: Total Docs Tested | L7: =COUNTA(A2:A36) | N7: Total Docs Tested | O7: =COUNTA(A2:A36)
A8: 20260629 HOK ADHDcentraal BV (1).pdf | C8: Fitted Out | H8: 0.9795376 | K8: No Of Docs With Data | L8: =COUNTIFS(B2:B36,"<>",B2:B36,"<>N/A",B2:B36,"<>Not Present In the Document",B2:B36,"<>Not Found",B2:B36,"<>i dont know",B2:B36,"<>i don't know") | N8: No Of Docs With Manual Pg | O8: =COUNTIFS(E2:E36,"<>",E2:E36,"<>N/A",E2:E36,"<>Not Present In the Document",E2:E36,"<>Not Found",E2:E36,"<>i dont know",E2:E36,"<>i don't know")
A9: 20260807_Happy_Village_B.V._Lease_Maasstadweg_tekenversie_incl._bijlagen en-GB.pdf | C9: Fitted Out | H9: 0.96901563 | K9: No Of Docs With Response | L9: =COUNTIFS(C2:C36,"<>") | N9: No Of Docs With Response Pg | O9: =COUNTIFS(F2:F36,"<>")
A10: 20260810 HOK ClustR BV.pdf | C10: Fitted Out | H10: 0.97435897 | K10: Highlighted rows = file(s) not in the annotation sheet; excluded from all metrics above.
A11: 20270801 - Getekende Allonge II Advario BV.pdf | C11: Fitted Out | H11: 0.45482625 | K11: Validation Rules Example
A12: 240119 HOVK Spoorlaan 446-448 Tilburg signed.pdf | C12: Fitted Out | H12: 0.98206751 | K12: Manual Data | L12: Response Data | M12: Result
A13: 27001 Rijksvastgoedbedrijf Huurovereenkomst - __27-01-2026_9-07-56.pdf | C13: Fitted Out | H13: 0.9769684 | K13: 100 | L13: 100 | M13: TP
A14: CBRE_AT_Services_ENG_-_RITUALS_CBRE signed.pdf | C14: Core And Shell | H14: 0.97435897 | L14: 100 | M14: FP
A15: CBRE_Engagement_Letter_Alnylam_20260525_CLEAN_Version_signed all.pdf | C15: To Be Agreed Upon | H15: 0.95287958 | K15: 100 | L15: 200 | M15: FP
A16: COMPL DEF Huurovereenkomst - Skybox - Pepperl+Fuchs - 20260204.pdf | C16: Turn-Key | H16: 0.98455902 | K16: 100 | M16: FN
A17: COMPL Huurovereenkomst - Stichting CCE - Kantoorgebouw Metzpoint I Dr. Holtroplaan - Fully Signed.pdf | C17: Fitted Out | H17: 0.456 | M17: TN
A18: COMPL Regel Partners - HOVK - Luchthavenweg 81 - 20260728.pdf | C18: Turn-Key | H18: 0.98206751
A19: COMPL_-_Onderhuurovereenkomst_Zelfstroom_B.V._-_50five_B.V._-_kantoorgebouw_Riva_-_05032026.pdf | C19: Fitted Out | H19: 0.96067416 | K19: Field: | L19: Lease_Comp_Details / space_condition_type_desc
A20: Den Bosch, Ruwekampweg 4, HOVK getekend.pdf | C20: Turn-Key | H20: 0.98455902
A21: FULLY SIGNED - COMPL Huurovereenkomst - Heijmans - Hugo de Grootlaan 23 's-Hertogenbosch V2 30-9-2025.pdf | C21: Fitted Out | H21: 0.97435897
A22: FULLY SIGNED - DEF_COMPL_Huurovereenkomst_Robo_Charge_-_Campus_Offices_-_20260220.pdf | C22: Fitted Out | H22: 0.98206751
A23: FULLY SIGNED - Onderhuurovereenkomst Aartshertogenlaan 223, `s-Hertogenbosch - Koning Willem I College B.V. 2606202.pdf | C23: Fitted Out | H23: 0.9795376
A24: FULLY SIGNED COMPL_DEF_Huurovereenkomst_Bond_Bergschot_Breda.pdf | C24: Fitted Out | H24: 0.9795376
A25: FullySigned_Allonge_II_Virtual_Vaults_Nederland.pdf | C25: Fitted Out | H25: 0.9795376
A26: FullySigned_Lease_Agreement_Neste_EDGE_Coolsingel.pdf | C26: Core And Shell | H26: 0.98455902
A27: HOK Waalhaven Group (signed).pdf | C27: Fitted Out | H27: 0.96901563
A28: Hovk Avans (3e+4e+5e verd.) 20140425.pdf | C28: Fitted Out | H28: 0.456
A29: HOVK Power4People 2025.pdf | C29: Turn-Key | H29: 0.21333076
A30: Huurovereenkomst (Semmie Group B.V.) - Wilhelminasingel 19, Breda.pdf | C30: Fitted Out | H30: 0.21333076
A31: Huurovereenkomst - proces-verbaal van oplevering - sleuteloverdracht - Kennedyplein 101 - getekend.pdf | C31: Fitted Out | H31: 0.98455902
... A36: MWO CBRE SPA (ITALY) CBRE_090724.pdf | C36: Core And Shell | H36: 0.95011601

Sheet Field 13
A1: Doc Name | B1: Manual Data | C1: Response Data | D1: Result | E1: Manual Pg | F1: Response Pg No | G1: Pg Result | H1: Confidence | K1: SUMMARY SHEET | N1: PAGE SUMMARY SHEET
A2: 20181204 Huurovereenkomst (GETEKEND).PDF | C2: N | H2: 0.97435897 | K2: Metrics | L2: Percentage | N2: Metrics | O2: Percentage
A3: 2024.10.30_Office Rental Agreement Labs_Gruyter Fabriek.pdf | C3: N | H3: 0.98455902 | K3: Precision | L3: =IFERROR(COUNTIFS(D2:D36,"TP")/(COUNTIFS(D2:D36,"TP")+COUNTIFS(D2:D36,"FP")),0) | N3: Precision | O3: =IFERROR(COUNTIFS(G2:G36,"TP")/(COUNTIFS(G2:G36,"TP")+COUNTIFS(G2:G36,"FP")),0)
A4: 20240606_HOK AKD - EDGE Eindhoven execution version.pdf | C4: N | H4: 0.98455902 | K4: Recall | L4: =IFERROR(COUNTIFS(D2:D36,"TP")/(COUNTIFS(D2:D36,"TP")+COUNTIFS(D2:D36,"FN")),0) | N4: Recall | O4: =IFERROR(COUNTIFS(G2:G36,"TP")/(COUNTIFS(G2:G36,"TP")+COUNTIFS(G2:G36,"FN")),0)
A5: 20250117_HOK Duke Strategies - Hambaken A.05.09 DEF FULLY SIGNED.pdf | C5: N | H5: 0.97435897 | K5: F1 Score | L5: =IFERROR(2*COUNTIFS(D2:D36,"TP")/(2*COUNTIFS(D2:D36,"TP")+COUNTIFS(D2:D36,"FP")+COUNTIFS(D2:D36,"FN")),0) | N5: F1 Score | O5: =IFERROR(2*COUNTIFS(G2:G36,"TP")/(2*COUNTIFS(G2:G36,"TP")+COUNTIFS(G2:G36,"FP")+COUNTIFS(G2:G36,"FN")),0)
A6: 20251216 Lease agreement ASPEN - signed.pdf | C6: N | H6: 0.98206751 | K6: Accuracy % (With Not Exist) | L6: =IFERROR((COUNTIF(D2:D36,"TP")+COUNTIF(D2:D36,"TN"))/SUM(COUNTIF(D2:D36,{"TP","TN","FP","FN"})),0) | N6: Accuracy % (With Not Exist) | O6: =IFERROR((COUNTIF(G2:G36,"TP")+COUNTIF(G2:G36,"TN"))/SUM(COUNTIF(G2:G36,{"TP","TN","FP","FN"})),0)
A7: 20260220 Huurovereenkomst signed 20-02-2026.pdf | C7: N | H7: 0.98455902 | K7: Total Docs Tested | L7: =COUNTA(A2:A36) | N7: Total Docs Tested | O7: =COUNTA(A2:A36)
A8: 20260629 HOK ADHDcentraal BV (1).pdf | C8: N | H8: 0.98206751 | K8: No Of Docs With Data | L8: =COUNTIFS(B2:B36,"<>",B2:B36,"<>N/A",B2:B36,"<>Not Present In the Document",B2:B36,"<>Not Found",B2:B36,"<>i dont know",B2:B36,"<>i don't know") | N8: No Of Docs With Manual Pg | O8: =COUNTIFS(E2:E36,"<>",E2:E36,"<>N/A",E2:E36,"<>Not Present In the Document",E2:E36,"<>Not Found",E2:E36,"<>i dont know",E2:E36,"<>i don't know")
A9: 20260807_Happy_Village_B.V._Lease_Maasstadweg_tekenversie_incl._bijlagen en-GB.pdf | C9: N | H9: 0.98455902 | K9: No Of Docs With Response | L9: =COUNTIFS(C2:C36,"<>") | N9: No Of Docs With Response Pg | O9: =COUNTIFS(F2:F36,"<>")
A10: 20260810 HOK ClustR BV.pdf | C10: N | H10: 0.98206751 | K10: Highlighted rows = file(s) not in the annotation sheet; excluded from all metrics above.
A11: 20270801 - Getekende Allonge II Advario BV.pdf | C11: N | H11: 0.9795376 | K11: Validation Rules Example
A12: 240119 HOVK Spoorlaan 446-448 Tilburg signed.pdf | C12: N | H12: 0.98455902 | K12: Manual Data | L12: Response Data | M12: Result
A13: 27001 Rijksvastgoedbedrijf Huurovereenkomst - __27-01-2026_9-07-56.pdf | C13: N | H13: 0.98455902 | K13: 100 | L13: 100 | M13: TP
A14: CBRE_AT_Services_ENG_-_RITUALS_CBRE signed.pdf | C14: N | H14: 0.98206751 | L14: 100 | M14: FP
A15: CBRE_Engagement_Letter_Alnylam_20260525_CLEAN_Version_signed all.pdf | C15: N | H15: 0.98206751 | K15: 100 | L15: 200 | M15: FP
A16: COMPL DEF Huurovereenkomst - Skybox - Pepperl+Fuchs - 20260204.pdf | C16: N | H16: 0.98455902 | K16: 100 | M16: FN
A17: COMPL Huurovereenkomst - Stichting CCE - Kantoorgebouw Metzpoint I Dr. Holtroplaan - Fully Signed.pdf | C17: N | H17: 0.98206751 | M17: TN
A18: COMPL Regel Partners - HOVK - Luchthavenweg 81 - 20260728.pdf | C18: N | H18: 0.98206751
A19: COMPL_-_Onderhuurovereenkomst_Zelfstroom_B.V._-_50five_B.V._-_kantoorgebouw_Riva_-_05032026.pdf | C19: Y | H19: 0.97435897 | K19: Field: | L19: Lease_Comp_Details / sublease_f
A20: Den Bosch, Ruwekampweg 4, HOVK getekend.pdf | C20: N | H20: 0.98455902
A21: FULLY SIGNED - COMPL Huurovereenkomst - Heijmans - Hugo de Grootlaan 23 's-Hertogenbosch V2 30-9-2025.pdf | C21: Y | H21: 0.97435897
A22: FULLY SIGNED - DEF_COMPL_Huurovereenkomst_Robo_Charge_-_Campus_Offices_-_20260220.pdf | C22: N | H22: 0.98455902
A23: FULLY SIGNED - Onderhuurovereenkomst Aartshertogenlaan 223, `s-Hertogenbosch - Koning Willem I College B.V. 2606202.pdf | C23: Y | H23: 0.97435897
A24: FULLY SIGNED COMPL_DEF_Huurovereenkomst_Bond_Bergschot_Breda.pdf | C24: N | H24: 0.98455902
A25: FullySigned_Allonge_II_Virtual_Vaults_Nederland.pdf | C25: N | H25: 0.98206751
A26: FullySigned_Lease_Agreement_Neste_EDGE_Coolsingel.pdf | C26: N | H26: 0.98455902
A27: HOK Waalhaven Group (signed).pdf | C27: N | H27: 0.98206751
A28: Hovk Avans (3e+4e+5e verd.) 20140425.pdf | C28: N | H28: 0.98455902
A29: HOVK Power4People 2025.pdf | C29: N | H29: 0.98206751
A30: Huurovereenkomst (Semmie Group B.V.) - Wilhelminasingel 19, Breda.pdf | C30: N | H30: 0.98455902
A31: Huurovereenkomst - proces-verbaal van oplevering - sleuteloverdracht - Kennedyplein 101 - getekend.pdf | C31: N | H31: 0.98206751
... A36: MWO CBRE SPA (ITALY) CBRE_090724.pdf | C36: N | H36: 0.98455902

Sheet Field 14
A1: Doc Name | B1: Manual Data | C1: Response Data | D1: Result | E1: Manual Pg | F1: Response Pg No | G1: Pg Result | H1: Confidence | K1: SUMMARY SHEET | N1: PAGE SUMMARY SHEET
A2: 20181204 Huurovereenkomst (GETEKEND).PDF | C2: Occupying | H2: 0.98455902 | K2: Metrics | L2: Percentage | N2: Metrics | O2: Percentage
A3: 2024.10.30_Office Rental Agreement Labs_Gruyter Fabriek.pdf | C3: Occupying | H3: 0.2892799 | K3: Precision | L3: =IFERROR(COUNTIFS(D2:D36,"TP")/(COUNTIFS(D2:D36,"TP")+COUNTIFS(D2:D36,"FP")),0) | N3: Precision | O3: =IFERROR(COUNTIFS(G2:G36,"TP")/(COUNTIFS(G2:G36,"TP")+COUNTIFS(G2:G36,"FP")),0)
A4: 20240606_HOK AKD - EDGE Eindhoven execution version.pdf | C4: Future | H4: 0.97435897 | K4: Recall | L4: =IFERROR(COUNTIFS(D2:D36,"TP")/(COUNTIFS(D2:D36,"TP")+COUNTIFS(D2:D36,"FN")),0) | N4: Recall | O4: =IFERROR(COUNTIFS(G2:G36,"TP")/(COUNTIFS(G2:G36,"TP")+COUNTIFS(G2:G36,"FN")),0)
A5: 20250117_HOK Duke Strategies - Hambaken A.05.09 DEF FULLY SIGNED.pdf | C5: Future | H5: 0.98206751 | K5: F1 Score | L5: =IFERROR(2*COUNTIFS(D2:D36,"TP")/(2*COUNTIFS(D2:D36,"TP")+COUNTIFS(D2:D36,"FP")+COUNTIFS(D2:D36,"FN")),0) | N5: F1 Score | O5: =IFERROR(2*COUNTIFS(G2:G36,"TP")/(2*COUNTIFS(G2:G36,"TP")+COUNTIFS(G2:G36,"FP")+COUNTIFS(G2:G36,"FN")),0)
A6: 20251216 Lease agreement ASPEN - signed.pdf | C6: Occupying | H6: 0.98206751 | K6: Accuracy % (With Not Exist) | L6: =IFERROR((COUNTIF(D2:D36,"TP")+COUNTIF(D2:D36,"TN"))/SUM(COUNTIF(D2:D36,{"TP","TN","FP","FN"})),0) | N6: Accuracy % (With Not Exist) | O6: =IFERROR((COUNTIF(G2:G36,"TP")+COUNTIF(G2:G36,"TN"))/SUM(COUNTIF(G2:G36,{"TP","TN","FP","FN"})),0)
A7: 20260220 Huurovereenkomst signed 20-02-2026.pdf | C7: Occupying | H7: 0.98206751 | K7: Total Docs Tested | L7: =COUNTA(A2:A36) | N7: Total Docs Tested | O7: =COUNTA(A2:A36)
A8: 20260629 HOK ADHDcentraal BV (1).pdf | C8: Occupying | H8: 0.98455902 | K8: No Of Docs With Data | L8: =COUNTIFS(B2:B36,"<>",B2:B36,"<>N/A",B2:B36,"<>Not Present In the Document",B2:B36,"<>Not Found",B2:B36,"<>i dont know",B2:B36,"<>i don't know") | N8: No Of Docs With Manual Pg | O8: =COUNTIFS(E2:E36,"<>",E2:E36,"<>N/A",E2:E36,"<>Not Present In the Document",E2:E36,"<>Not Found",E2:E36,"<>i dont know",E2:E36,"<>i don't know")
A9: 20260807_Happy_Village_B.V._Lease_Maasstadweg_tekenversie_incl._bijlagen en-GB.pdf | C9: Future | H9: 0.98206751 | K9: No Of Docs With Response | L9: =COUNTIFS(C2:C36,"<>") | N9: No Of Docs With Response Pg | O9: =COUNTIFS(F2:F36,"<>")
A10: 20260810 HOK ClustR BV.pdf | C10: Occupying | H10: 0.28906443 | K10: Highlighted rows = file(s) not in the annotation sheet; excluded from all metrics above.
A11: 20270801 - Getekende Allonge II Advario BV.pdf | C11: Occupying | H11: 0.98455902 | K11: Validation Rules Example
A12: 240119 HOVK Spoorlaan 446-448 Tilburg signed.pdf | C12: Occupying | H12: 0.98455902 | K12: Manual Data | L12: Response Data | M12: Result
A13: 27001 Rijksvastgoedbedrijf Huurovereenkomst - __27-01-2026_9-07-56.pdf | C13: Occupying | H13: 0.98455902 | K13: 100 | L13: 100 | M13: TP
A14: CBRE_AT_Services_ENG_-_RITUALS_CBRE signed.pdf | C14: Occupying | F14: 19 | H14: 0.24266667 | L14: 100 | M14: FP
A15: CBRE_Engagement_Letter_Alnylam_20260525_CLEAN_Version_signed all.pdf | C15: Occupying | H15: 0.24248705 | K15: 100 | L15: 200 | M15: FP
A16: COMPL DEF Huurovereenkomst - Skybox - Pepperl+Fuchs - 20260204.pdf | C16: Future | H16: 0.2892799 | K16: 100 | M16: FN
A17: COMPL Huurovereenkomst - Stichting CCE - Kantoorgebouw Metzpoint I Dr. Holtroplaan - Fully Signed.pdf | C17: Future | H17: 0.97435897 | M17: TN
A18: COMPL Regel Partners - HOVK - Luchthavenweg 81 - 20260728.pdf | C18: Occupying | H18: 0.98455902
A19: COMPL_-_Onderhuurovereenkomst_Zelfstroom_B.V._-_50five_B.V._-_kantoorgebouw_Riva_-_05032026.pdf | C19: Expired | H19: 0.48984375 | K19: Field: | L19: Lease_Comp_Details / tenant_status_type_desc
A20: Den Bosch, Ruwekampweg 4, HOVK getekend.pdf | C20: Occupying | H20: 0.98206751
A21: FULLY SIGNED - COMPL Huurovereenkomst - Heijmans - Hugo de Grootlaan 23 's-Hertogenbosch V2 30-9-2025.pdf | C21: Future | H21: 0.2892799
A22: FULLY SIGNED - DEF_COMPL_Huurovereenkomst_Robo_Charge_-_Campus_Offices_-_20260220.pdf | C22: Future | H22: 0.98455902
A23: FULLY SIGNED - Onderhuurovereenkomst Aartshertogenlaan 223, `s-Hertogenbosch - Koning Willem I College B.V. 2606202.pdf | C23: Occupying | H23: 0.98206751
A24: FULLY SIGNED COMPL_DEF_Huurovereenkomst_Bond_Bergschot_Breda.pdf | C24: Occupying | H24: 0.98455902
A25: FullySigned_Allonge_II_Virtual_Vaults_Nederland.pdf | C25: Occupying | H25: 0.98206751
A26: FullySigned_Lease_Agreement_Neste_EDGE_Coolsingel.pdf | C26: Future | H26: 0.98455902
A27: HOK Waalhaven Group (signed).pdf | C27: Future | H27: 0.98455902
A28: Hovk Avans (3e+4e+5e verd.) 20140425.pdf | C28: Occupying | H28: 0.98455902
A29: HOVK Power4People 2025.pdf | C29: Future | H29: 0.98206751
A30: Huurovereenkomst (Semmie Group B.V.) - Wilhelminasingel 19, Breda.pdf | C30: Future | H30: 0.98455902
A31: Huurovereenkomst - proces-verbaal van oplevering - sleuteloverdracht - Kennedyplein 101 - getekend.pdf | C31: Future | H31: 0.98455902
... A36: MWO CBRE SPA (ITALY) CBRE_090724.pdf | C36: Occupying | H36: 0.24266667

Sheet Field 15
A1: Doc Name | B1: Manual Data | C1: Response Data | D1: Result | E1: Manual Pg | F1: Response Pg No | G1: Pg Result | H1: Confidence | K1: SUMMARY SHEET | N1: PAGE SUMMARY SHEET
A2: 20181204 Huurovereenkomst (GETEKEND).PDF | C2: 10 | H2: 0.98206751 | K2: Metrics | L2: Percentage | N2: Metrics | O2: Percentage
A3: 2024.10.30_Office Rental Agreement Labs_Gruyter Fabriek.pdf | C3: 558 | H3: 0.98455902 | K3: Precision | L3: =IFERROR(COUNTIFS(D2:D36,"TP")/(COUNTIFS(D2:D36,"TP")+COUNTIFS(D2:D36,"FP")),0) | N3: Precision | O3: =IFERROR(COUNTIFS(G2:G36,"TP")/(COUNTIFS(G2:G36,"TP")+COUNTIFS(G2:G36,"FP")),0)
A4: 20240606_HOK AKD - EDGE Eindhoven execution version.pdf | C4: 2590 | H4: 0.71661321 | K4: Recall | L4: =IFERROR(COUNTIFS(D2:D36,"TP")/(COUNTIFS(D2:D36,"TP")+COUNTIFS(D2:D36,"FN")),0) | N4: Recall | O4: =IFERROR(COUNTIFS(G2:G36,"TP")/(COUNTIFS(G2:G36,"TP")+COUNTIFS(G2:G36,"FN")),0)
A5: 20250117_HOK Duke Strategies - Hambaken A.05.09 DEF FULLY SIGNED.pdf | C5: 31.5 | H5: 0.98206751 | K5: F1 Score | L5: =IFERROR(2*COUNTIFS(D2:D36,"TP")/(2*COUNTIFS(D2:D36,"TP")+COUNTIFS(D2:D36,"FP")+COUNTIFS(D2:D36,"FN")),0) | N5: F1 Score | O5: =IFERROR(2*COUNTIFS(G2:G36,"TP")/(2*COUNTIFS(G2:G36,"TP")+COUNTIFS(G2:G36,"FP")+COUNTIFS(G2:G36,"FN")),0)
A6: 20251216 Lease agreement ASPEN - signed.pdf | C6: 3253 | H6: 0.98206751 | K6: Accuracy % (With Not Exist) | L6: =IFERROR((COUNTIF(D2:D36,"TP")+COUNTIF(D2:D36,"TN"))/SUM(COUNTIF(D2:D36,{"TP","TN","FP","FN"})),0) | N6: Accuracy % (With Not Exist) | O6: =IFERROR((COUNTIF(G2:G36,"TP")+COUNTIF(G2:G36,"TN"))/SUM(COUNTIF(G2:G36,{"TP","TN","FP","FN"})),0)
A7: 20260220 Huurovereenkomst signed 20-02-2026.pdf | C7: 139 | H7: 0.98455902 | K7: Total Docs Tested | L7: =COUNTA(A2:A36) | N7: Total Docs Tested | O7: =COUNTA(A2:A36)
A8: 20260629 HOK ADHDcentraal BV (1).pdf | C8: 218.7 | H8: 0.98206751 | K8: No Of Docs With Data | L8: =COUNTIFS(B2:B36,"<>",B2:B36,"<>N/A",B2:B36,"<>Not Present In the Document",B2:B36,"<>Not Found",B2:B36,"<>i dont know",B2:B36,"<>i don't know") | N8: No Of Docs With Manual Pg | O8: =COUNTIFS(E2:E36,"<>",E2:E36,"<>N/A",E2:E36,"<>Not Present In the Document",E2:E36,"<>Not Found",E2:E36,"<>i dont know",E2:E36,"<>i don't know")
A9: 20260807_Happy_Village_B.V._Lease_Maasstadweg_tekenversie_incl._bijlagen en-GB.pdf | C9: 1579.8 | H9: 0.98206751 | K9: No Of Docs With Response | L9: =COUNTIFS(C2:C36,"<>") | N9: No Of Docs With Response Pg | O9: =COUNTIFS(F2:F36,"<>")
A10: 20260810 HOK ClustR BV.pdf | C10: 154.4 | H10: 0.98455902 | K10: Highlighted rows = file(s) not in the annotation sheet; excluded from all metrics above.
A11: 20270801 - Getekende Allonge II Advario BV.pdf | C11: 1176.48 | H11: 0.90276243 | K11: Validation Rules Example
A12: 240119 HOVK Spoorlaan 446-448 Tilburg signed.pdf | C12: 2645 | H12: 0.98206751 | K12: Manual Data | L12: Response Data | M12: Result
A13: 27001 Rijksvastgoedbedrijf Huurovereenkomst - __27-01-2026_9-07-56.pdf | C13: 7867 | H13: 0.98455902 | K13: 100 | L13: 100 | M13: TP
A14: CBRE_AT_Services_ENG_-_RITUALS_CBRE signed.pdf | L14: 100 | M14: FP
A15: CBRE_Engagement_Letter_Alnylam_20260525_CLEAN_Version_signed all.pdf | C15: 800 | H15: 0.90497238 | K15: 100 | L15: 200 | M15: FP
A16: COMPL DEF Huurovereenkomst - Skybox - Pepperl+Fuchs - 20260204.pdf | C16: 370 | H16: 0.98206751 | K16: 100 | M16: FN
A17: COMPL Huurovereenkomst - Stichting CCE - Kantoorgebouw Metzpoint I Dr. Holtroplaan - Fully Signed.pdf | C17: 293.2 | H17: 0.98455902 | M17: TN
A18: COMPL Regel Partners - HOVK - Luchthavenweg 81 - 20260728.pdf | C18: 419.10 | H18: 0.98455902
A19: COMPL_-_Onderhuurovereenkomst_Zelfstroom_B.V._-_50five_B.V._-_kantoorgebouw_Riva_-_05032026.pdf | C19: 1013.23 | H19: 0.98455902 | K19: Field: | L19: Lease_Comp_Details / total_leased_space
A20: Den Bosch, Ruwekampweg 4, HOVK getekend.pdf | C20: 2230 | H20: 0.98455902
A21: FULLY SIGNED - COMPL Huurovereenkomst - Heijmans - Hugo de Grootlaan 23 's-Hertogenbosch V2 30-9-2025.pdf | C21: 400 | H21: 0.98206751
A22: FULLY SIGNED - DEF_COMPL_Huurovereenkomst_Robo_Charge_-_Campus_Offices_-_20260220.pdf | C22: 357.2 | H22: 0.97435897
A23: FULLY SIGNED - Onderhuurovereenkomst Aartshertogenlaan 223, `s-Hertogenbosch - Koning Willem I College B.V. 2606202.pdf | C23: 1227 | H23: 0.98206751
A24: FULLY SIGNED COMPL_DEF_Huurovereenkomst_Bond_Bergschot_Breda.pdf | C24: 1001.08 | H24: 0.98455902
A25: FullySigned_Allonge_II_Virtual_Vaults_Nederland.pdf | C25: 1130.98 | H25: 0.98455902
A26: FullySigned_Lease_Agreement_Neste_EDGE_Coolsingel.pdf | C26: 1335 | H26: 0.98455902
A27: HOK Waalhaven Group (signed).pdf | C27: 672 | H27: 0.98455902
A28: Hovk Avans (3e+4e+5e verd.) 20140425.pdf | C28: 1612 | H28: 0.98206751
A29: HOVK Power4People 2025.pdf
A30: Huurovereenkomst (Semmie Group B.V.) - Wilhelminasingel 19, Breda.pdf | C30: 61.4 | H30: 0.98455902
A31: Huurovereenkomst - proces-verbaal van oplevering - sleuteloverdracht - Kennedyplein 101 - getekend.pdf | C31: 360.81 | H31: 0.98206751
A32: Huurovereenkomst Bijster 5 te Breda getekend.pdf | C32: 435 | H32: 0.98455902
A33: Huurovereenkomst Catena Pand Son - Skymark (Son en Breugel - NLD).pdf
A34: Huurovereenkomst KPN Opstelpunt Parallelweg 64 20130313.pdf
A35: Huurovereenkomst PBG Parallelweg 64 (beg.grond) 20121008.pdf | C35: 808 | H35: 0.98455902
A36: MWO CBRE SPA (ITALY) CBRE_090724.pdf

Sheet Field 16
A1: Doc Name | B1: Manual Data | C1: Response Data | D1: Result | E1: Manual Pg | F1: Response Pg No | G1: Pg Result | H1: Confidence | K1: SUMMARY SHEET | N1: PAGE SUMMARY SHEET
A2: 20181204 Huurovereenkomst (GETEKEND).PDF | C2: Assumed | H2: 0.97435897 | K2: Metrics | L2: Percentage | N2: Metrics | O2: Percentage
A3: 2024.10.30_Office Rental Agreement Labs_Gruyter Fabriek.pdf | C3: Actual | H3: 0.96901563 | K3: Precision | L3: =IFERROR(COUNTIFS(D2:D36,"TP")/(COUNTIFS(D2:D36,"TP")+COUNTIFS(D2:D36,"FP")),0) | N3: Precision | O3: =IFERROR(COUNTIFS(G2:G36,"TP")/(COUNTIFS(G2:G36,"TP")+COUNTIFS(G2:G36,"FP")),0)
A4: 20240606_HOK AKD - EDGE Eindhoven execution version.pdf | C4: Assumed | H4: 0.9795376 | K4: Recall | L4: =IFERROR(COUNTIFS(D2:D36,"TP")/(COUNTIFS(D2:D36,"TP")+COUNTIFS(D2:D36,"FN")),0) | N4: Recall | O4: =IFERROR(COUNTIFS(G2:G36,"TP")/(COUNTIFS(G2:G36,"TP")+COUNTIFS(G2:G36,"FN")),0)
A5: 20250117_HOK Duke Strategies - Hambaken A.05.09 DEF FULLY SIGNED.pdf | C5: Actual | H5: 0.9769684 | K5: F1 Score | L5: =IFERROR(2*COUNTIFS(D2:D36,"TP")/(2*COUNTIFS(D2:D36,"TP")+COUNTIFS(D2:D36,"FP")+COUNTIFS(D2:D36,"FN")),0) | N5: F1 Score | O5: =IFERROR(2*COUNTIFS(G2:G36,"TP")/(2*COUNTIFS(G2:G36,"TP")+COUNTIFS(G2:G36,"FP")+COUNTIFS(G2:G36,"FN")),0)
A6: 20251216 Lease agreement ASPEN - signed.pdf | C6: Assumed | H6: 0.49178439 | K6: Accuracy % (With Not Exist) | L6: =IFERROR((COUNTIF(D2:D36,"TP")+COUNTIF(D2:D36,"TN"))/SUM(COUNTIF(D2:D36,{"TP","TN","FP","FN"})),0) | N6: Accuracy % (With Not Exist) | O6: =IFERROR((COUNTIF(G2:G36,"TP")+COUNTIF(G2:G36,"TN"))/SUM(COUNTIF(G2:G36,{"TP","TN","FP","FN"})),0)
A7: 20260220 Huurovereenkomst signed 20-02-2026.pdf | C7: Actual | H7: 0.97435897 | K7: Total Docs Tested | L7: =COUNTA(A2:A36) | N7: Total Docs Tested | O7: =COUNTA(A2:A36)
A8: 20260629 HOK ADHDcentraal BV (1).pdf | C8: Actual | H8: 0.97435897 | K8: No Of Docs With Data | L8: =COUNTIFS(B2:B36,"<>",B2:B36,"<>N/A",B2:B36,"<>Not Present In the Document",B2:B36,"<>Not Found",B2:B36,"<>i dont know",B2:B36,"<>i don't know") | N8: No Of Docs With Manual Pg | O8: =COUNTIFS(E2:E36,"<>",E2:E36,"<>N/A",E2:E36,"<>Not Present In the Document",E2:E36,"<>Not Found",E2:E36,"<>i dont know",E2:E36,"<>i don't know")
A9: 20260807_Happy_Village_B.V._Lease_Maasstadweg_tekenversie_incl._bijlagen en-GB.pdf | C9: Actual | H9: 0.98455902 | K9: No Of Docs With Response | L9: =COUNTIFS(C2:C36,"<>") | N9: No Of Docs With Response Pg | O9: =COUNTIFS(F2:F36,"<>")
A10: 20260810 HOK ClustR BV.pdf | C10: Actual | H10: 0.96627971 | K10: Highlighted rows = file(s) not in the annotation sheet; excluded from all metrics above.
A11: 20270801 - Getekende Allonge II Advario BV.pdf | C11: Assumed | H11: 0.49240838 | K11: Validation Rules Example
A12: 240119 HOVK Spoorlaan 446-448 Tilburg signed.pdf | C12: Assumed | H12: 0.97435897 | K12: Manual Data | L12: Response Data | M12: Result
A13: 27001 Rijksvastgoedbedrijf Huurovereenkomst - __27-01-2026_9-07-56.pdf | C13: Actual | H13: 0.48984375 | K13: 100 | L13: 100 | M13: TP
A14: CBRE_AT_Services_ENG_-_RITUALS_CBRE signed.pdf | C14: Assumed | H14: 0.97435897 | L14: 100 | M14: FP
A15: CBRE_Engagement_Letter_Alnylam_20260525_CLEAN_Version_signed all.pdf | C15: Assumed | H15: 0.98455902 | K15: 100 | L15: 200 | M15: FP
A16: COMPL DEF Huurovereenkomst - Skybox - Pepperl+Fuchs - 20260204.pdf | C16: Assumed | H16: 0.98455902 | K16: 100 | M16: FN
A17: COMPL Huurovereenkomst - Stichting CCE - Kantoorgebouw Metzpoint I Dr. Holtroplaan - Fully Signed.pdf | C17: Actual | H17: 0.98455902 | M17: TN
A18: COMPL Regel Partners - HOVK - Luchthavenweg 81 - 20260728.pdf | C18: Actual | H18: 0.49240838
A19: COMPL_-_Onderhuurovereenkomst_Zelfstroom_B.V._-_50five_B.V._-_kantoorgebouw_Riva_-_05032026.pdf | C19: Actual | H19: 0.98455902 | K19: Field: | L19: Lease_Comp_Details / total_leased_space_estimated_f
A20: Den Bosch, Ruwekampweg 4, HOVK getekend.pdf | C20: Assumed | H20: 0.97435897
A21: FULLY SIGNED - COMPL Huurovereenkomst - Heijmans - Hugo de Grootlaan 23 's-Hertogenbosch V2 30-9-2025.pdf | C21: Actual | H21: 0.98455902
A22: FULLY SIGNED - DEF_COMPL_Huurovereenkomst_Robo_Charge_-_Campus_Offices_-_20260220.pdf | C22: Actual | H22: 0.98455902
A23: FULLY SIGNED - Onderhuurovereenkomst Aartshertogenlaan 223, `s-Hertogenbosch - Koning Willem I College B.V. 2606202.pdf | C23: Actual | H23: 0.98455902
A24: FULLY SIGNED COMPL_DEF_Huurovereenkomst_Bond_Bergschot_Breda.pdf | C24: Actual | H24: 0.98455902
A25: FullySigned_Allonge_II_Virtual_Vaults_Nederland.pdf | C25: Actual | H25: 0.98455902
A26: FullySigned_Lease_Agreement_Neste_EDGE_Coolsingel.pdf | C26: Assumed | H26: 0.9795376
A27: HOK Waalhaven Group (signed).pdf | C27: Assumed | H27: 0.97435897
A28: Hovk Avans (3e+4e+5e verd.) 20140425.pdf | C28: Assumed | H28: 0.49178439
A29: HOVK Power4People 2025.pdf | C29: Actual | H29: 0.48363978
A30: Huurovereenkomst (Semmie Group B.V.) - Wilhelminasingel 19, Breda.pdf | C30: Assumed | H30: 0.98206751
A31: Huurovereenkomst - proces-verbaal van oplevering - sleuteloverdracht - Kennedyplein 101 - getekend.pdf | C31: Actual | H31: 0.98455902
... A36: MWO CBRE SPA (ITALY) CBRE_090724.pdf | C36: Actual | H36: 0.49114916

Sheet Field 17
A1: Doc Name | B1: Manual Data | C1: Response Data | D1: Result | E1: Manual Pg | F1: Response Pg No | G1: Pg Result | H1: Confidence | K1: SUMMARY SHEET | N1: PAGE SUMMARY SHEET
A2: 20181204 Huurovereenkomst (GETEKEND).PDF | K2: Metrics | L2: Percentage | N2: Metrics | O2: Percentage
A3: 2024.10.30_Office Rental Agreement Labs_Gruyter Fabriek.pdf | C3: De Gruyter Fabriek | H3: 0.98455902 | K3: Precision | L3: =IFERROR(COUNTIFS(D2:D36,"TP")/(COUNTIFS(D2:D36,"TP")+COUNTIFS(D2:D36,"FP")),0) | N3: Precision | O3: =IFERROR(COUNTIFS(G2:G36,"TP")/(COUNTIFS(G2:G36,"TP")+COUNTIFS(G2:G36,"FP")),0)
A4: 20240606_HOK AKD - EDGE Eindhoven execution version.pdf | C4: EDGE Eindhoven | H4: 0.98455902 | K4: Recall | L4: =IFERROR(COUNTIFS(D2:D36,"TP")/(COUNTIFS(D2:D36,"TP")+COUNTIFS(D2:D36,"FN")),0) | N4: Recall | O4: =IFERROR(COUNTIFS(G2:G36,"TP")/(COUNTIFS(G2:G36,"TP")+COUNTIFS(G2:G36,"FN")),0)
A5: 20250117_HOK Duke Strategies - Hambaken A.05.09 DEF FULLY SIGNED.pdf | C5: Campus Hambaken | H5: 0.9795376 | K5: F1 Score | L5: =IFERROR(2*COUNTIFS(D2:D36,"TP")/(2*COUNTIFS(D2:D36,"TP")+COUNTIFS(D2:D36,"FP")+COUNTIFS(D2:D36,"FN")),0) | N5: F1 Score | O5: =IFERROR(2*COUNTIFS(G2:G36,"TP")/(2*COUNTIFS(G2:G36,"TP")+COUNTIFS(G2:G36,"FP")+COUNTIFS(G2:G36,"FN")),0)
A6: 20251216 Lease agreement ASPEN - signed.pdf | C6: Panther | H6: 0.98206751 | K6: Accuracy % (With Not Exist) | L6: =IFERROR((COUNTIF(D2:D36,"TP")+COUNTIF(D2:D36,"TN"))/SUM(COUNTIF(D2:D36,{"TP","TN","FP","FN"})),0) | N6: Accuracy % (With Not Exist) | O6: =IFERROR((COUNTIF(G2:G36,"TP")+COUNTIF(G2:G36,"TN"))/SUM(COUNTIF(G2:G36,{"TP","TN","FP","FN"})),0)
A7: 20260220 Huurovereenkomst signed 20-02-2026.pdf | C7: Bond Park | H7: 0.98455902 | K7: Total Docs Tested | L7: =COUNTA(A2:A36) | N7: Total Docs Tested | O7: =COUNTA(A2:A36)
A8: 20260629 HOK ADHDcentraal BV (1).pdf | C8: Campus Hambaken Offices | H8: 0.9795376 | K8: No Of Docs With Data | L8: =COUNTIFS(B2:B36,"<>",B2:B36,"<>N/A",B2:B36,"<>Not Present In the Document",B2:B36,"<>Not Found",B2:B36,"<>i dont know",B2:B36,"<>i don't know") | N8: No Of Docs With Manual Pg | O8: =COUNTIFS(E2:E36,"<>",E2:E36,"<>N/A",E2:E36,"<>Not Present In the Document",E2:E36,"<>Not Found",E2:E36,"<>i dont know",E2:E36,"<>i don't know")
A9: 20260807_Happy_Village_B.V._Lease_Maasstadweg_tekenversie_incl._bijlagen en-GB.pdf | C9: Arcura Medical Properties | H9: 0.89722222 | K9: No Of Docs With Response | L9: =COUNTIFS(C2:C36,"<>") | N9: No Of Docs With Response Pg | O9: =COUNTIFS(F2:F36,"<>")
A10: 20260810 HOK ClustR BV.pdf | C10: CAMPUS OFFICES | H10: 0.96901563 | K10: Highlighted rows = file(s) not in the annotation sheet; excluded from all metrics above.
A11: 20270801 - Getekende Allonge II Advario BV.pdf | C11: World Trade Center Rotterdam | H11: 0.98455902 | K11: Validation Rules Example
A12: 240119 HOVK Spoorlaan 446-448 Tilburg signed.pdf | K12: Manual Data | L12: Response Data | M12: Result
A13: 27001 Rijksvastgoedbedrijf Huurovereenkomst - __27-01-2026_9-07-56.pdf | C13: Hooghuis | H13: 0.97435897 | K13: 100 | L13: 100 | M13: TP
A14: CBRE_AT_Services_ENG_-_RITUALS_CBRE signed.pdf | L14: 100 | M14: FP
A15: CBRE_Engagement_Letter_Alnylam_20260525_CLEAN_Version_signed all.pdf | K15: 100 | L15: 200 | M15: FP
A16: COMPL DEF Huurovereenkomst - Skybox - Pepperl+Fuchs - 20260204.pdf | C16: Skybox | H16: 0.96067416 | K16: 100 | M16: FN
A17: COMPL Huurovereenkomst - Stichting CCE - Kantoorgebouw Metzpoint I Dr. Holtroplaan - Fully Signed.pdf | C17: Metzpoint | H17: 0.98206751 | M17: TN
A18: COMPL Regel Partners - HOVK - Luchthavenweg 81 - 20260728.pdf | C18: Benkey Eindhoven | H18: 0.98206751
A19: COMPL_-_Onderhuurovereenkomst_Zelfstroom_B.V._-_50five_B.V._-_kantoorgebouw_Riva_-_05032026.pdf | K19: Field: | L19: Property / property_name
A20: Den Bosch, Ruwekampweg 4, HOVK getekend.pdf
A21: FULLY SIGNED - COMPL Huurovereenkomst - Heijmans - Hugo de Grootlaan 23 's-Hertogenbosch V2 30-9-2025.pdf
A22: FULLY SIGNED - DEF_COMPL_Huurovereenkomst_Robo_Charge_-_Campus_Offices_-_20260220.pdf | C22: Campus Hambaken | H22: 0.9795376
A23: FULLY SIGNED - Onderhuurovereenkomst Aartshertogenlaan 223, `s-Hertogenbosch - Koning Willem I College B.V. 2606202.pdf
A24: FULLY SIGNED COMPL_DEF_Huurovereenkomst_Bond_Bergschot_Breda.pdf | C24: Bond Bergschot | H24: 0.9795376
A25: FullySigned_Allonge_II_Virtual_Vaults_Nederland.pdf
A26: FullySigned_Lease_Agreement_Neste_EDGE_Coolsingel.pdf | C26: EDGE Coolsingel | H26: 0.98455902
A27: HOK Waalhaven Group (signed).pdf
A28: Hovk Avans (3e+4e+5e verd.) 20140425.pdf | C28: De Hooge Donken | H28: 0.98206751
A29: HOVK Power4People 2025.pdf | C29: For You Breda | H29: 0.98206751
A30: Huurovereenkomst (Semmie Group B.V.) - Wilhelminasingel 19, Breda.pdf
A31: Huurovereenkomst - proces-verbaal van oplevering - sleuteloverdracht - Kennedyplein 101 - getekend.pdf
A32: Huurovereenkomst Bijster 5 te Breda getekend.pdf | C32: Bijster 5 | H32: 0.94582723
A33: Huurovereenkomst Catena Pand Son - Skymark (Son en Breugel - NLD).pdf | C33: Science Park | H33: 0.94582723
A34: Huurovereenkomst KPN Opstelpunt Parallelweg 64 20130313.pdf
A35: Huurovereenkomst PBG Parallelweg 64 (beg.grond) 20121008.pdf | C35: De Hooge Donken | H35: 0.98455902
A36: MWO CBRE SPA (ITALY) CBRE_090724.pdf

Sheet Field 18
A1: Doc Name | B1: Manual Data | C1: Response Data | D1: Result | E1: Manual Pg | F1: Response Pg No | G1: Pg Result | H1: Confidence | K1: SUMMARY SHEET | N1: PAGE SUMMARY SHEET
A2: 20181204 Huurovereenkomst (GETEKEND).PDF | B2: 31/12/2033 | C2: 31/12/2033 | D2: TP | H2: 0.98455902 | K2: Metrics | L2: Percentage | N2: Metrics | O2: Percentage
A3: 2024.10.30_Office Rental Agreement Labs_Gruyter Fabriek.pdf | B3: 31/12/2029 | C3: 31/12/2029 | D3: TP | H3: 0.97435897 | K3: Precision | L3: =IFERROR(COUNTIFS(D2:D36,"TP")/(COUNTIFS(D2:D36,"TP")+COUNTIFS(D2:D36,"FP")),0) | N3: Precision | O3: =IFERROR(COUNTIFS(G2:G36,"TP")/(COUNTIFS(G2:G36,"TP")+COUNTIFS(G2:G36,"FP")),0)
A4: 20240606_HOK AKD - EDGE Eindhoven execution version.pdf | B4: 30/06/2036 | C4: 30/06/2036 | D4: TP | H4: 0.97435897 | K4: Recall | L4: =IFERROR(COUNTIFS(D2:D36,"TP")/(COUNTIFS(D2:D36,"TP")+COUNTIFS(D2:D36,"FN")),0) | N4: Recall | O4: =IFERROR(COUNTIFS(G2:G36,"TP")/(COUNTIFS(G2:G36,"TP")+COUNTIFS(G2:G36,"FN")),0)
A5: 20250117_HOK Duke Strategies - Hambaken A.05.09 DEF FULLY SIGNED.pdf | B5: 16/02/2026 | C5: 16/02/2026 | D5: TP | H5: 0.98206751 | K5: F1 Score | L5: =IFERROR(2*COUNTIFS(D2:D36,"TP")/(2*COUNTIFS(D2:D36,"TP")+COUNTIFS(D2:D36,"FP")+COUNTIFS(D2:D36,"FN")),0) | N5: F1 Score | O5: =IFERROR(2*COUNTIFS(G2:G36,"TP")/(2*COUNTIFS(G2:G36,"TP")+COUNTIFS(G2:G36,"FP")+COUNTIFS(G2:G36,"FN")),0)
A6: 20251216 Lease agreement ASPEN - signed.pdf | B6: 28/02/2038 | C6: 31/03/2038 | D6: FP | H6: 0.81302871 | K6: Accuracy % (With Not Exist) | L6: =IFERROR((COUNTIF(D2:D36,"TP")+COUNTIF(D2:D36,"TN"))/SUM(COUNTIF(D2:D36,{"TP","TN","FP","FN"})),0) | N6: Accuracy % (With Not Exist) | O6: =IFERROR((COUNTIF(G2:G36,"TP")+COUNTIF(G2:G36,"TN"))/SUM(COUNTIF(G2:G36,{"TP","TN","FP","FN"})),0)
A7: 20260220 Huurovereenkomst signed 20-02-2026.pdf | B7: 28/02/2029 | C7: 28/02/2029 | D7: TP | H7: 0.97435897 | K7: Total Docs Tested | L7: =COUNTA(A2:A36) | N7: Total Docs Tested | O7: =COUNTA(A2:A36)
A8: 20260629 HOK ADHDcentraal BV (1).pdf | B8: 31/08/2028 | C8: 31/08/2028 | D8: TP | H8: 0.98455902 | K8: No Of Docs With Data | L8: =COUNTIFS(B2:B36,"<>",B2:B36,"<>N/A",B2:B36,"<>Not Present In the Document",B2:B36,"<>Not Found",B2:B36,"<>i dont know",B2:B36,"<>i don't know") | N8: No Of Docs With Manual Pg | O8: =COUNTIFS(E2:E36,"<>",E2:E36,"<>N/A",E2:E36,"<>Not Present In the Document",E2:E36,"<>Not Found",E2:E36,"<>i dont know",E2:E36,"<>i don't know")
A9: 20260807_Happy_Village_B.V._Lease_Maasstadweg_tekenversie_incl._bijlagen en-GB.pdf | B9: 31/12/2036 | C9: 31/12/2036 | D9: TP | H9: 0.98455902 | K9: No Of Docs With Response | L9: =COUNTIFS(C2:C36,"<>") | N9: No Of Docs With Response Pg | O9: =COUNTIFS(F2:F36,"<>")
A10: 20260810 HOK ClustR BV.pdf | B10: 30/09/2028 | C10: 30/09/2028 | D10: TP | H10: 0.98455902 | K10: Highlighted rows = file(s) not in the annotation sheet; excluded from all metrics above.
A11: 20270801 - Getekende Allonge II Advario BV.pdf | B11: 31/07/2032 | C11: 31/07/2032 | D11: TP | E11: 3 | H11: 0.98455902 | K11: Validation Rules Example
A12: 240119 HOVK Spoorlaan 446-448 Tilburg signed.pdf | B12: 31/03/2027 | C12: 31/03/2027 | D12: TP | H12: 0.98455902 | K12: Manual Data | L12: Response Data | M12: Result
A13: 27001 Rijksvastgoedbedrijf Huurovereenkomst - __27-01-2026_9-07-56.pdf | B13: 31/12/2026 | C13: 31/12/2026 | D13: TP | H13: 0.98206751 | K13: 100 | L13: 100 | M13: TP
A14: CBRE_AT_Services_ENG_-_RITUALS_CBRE signed.pdf | L14: 100 | M14: FP
A15: CBRE_Engagement_Letter_Alnylam_20260525_CLEAN_Version_signed all.pdf | K15: 100 | L15: 200 | M15: FP
A16: COMPL DEF Huurovereenkomst - Skybox - Pepperl+Fuchs - 20260204.pdf | B16: 30/11/2031 | C16: 30/11/2031 | D16: TP | H16: 0.98455902 | K16: 100 | M16: FN
A17: COMPL Huurovereenkomst - Stichting CCE - Kantoorgebouw Metzpoint I Dr. Holtroplaan - Fully Signed.pdf | B17: 30/04/2035 | C17: 30/04/2035 | D17: TP | H17: 0.98455902 | M17: TN
A18: COMPL Regel Partners - HOVK - Luchthavenweg 81 - 20260728.pdf | B18: 30/09/2031 | C18: 30/09/2031 | D18: TP | H18: 0.97435897
A19: COMPL_-_Onderhuurovereenkomst_Zelfstroom_B.V._-_50five_B.V._-_kantoorgebouw_Riva_-_05032026.pdf | B19: 46028 | C19: 01/06/2026 | D19: TP | H19: 0.97435897 | K19: Field: | L19: Terms / Arrangement_End_Date
A20: Den Bosch, Ruwekampweg 4, HOVK getekend.pdf | B20: 31/12/2026 | C20: 31/12/2026 | D20: TP | H20: 0.97435897
A21: FULLY SIGNED - COMPL Huurovereenkomst - Heijmans - Hugo de Grootlaan 23 's-Hertogenbosch V2 30-9-2025.pdf | B21: 14/10/2026 | C21: 14/10/2026 | D21: TP | H21: 0.98455902
A22: FULLY SIGNED - DEF_COMPL_Huurovereenkomst_Robo_Charge_-_Campus_Offices_-_20260220.pdf | B22: 31/03/2031 | C22: 31/03/2031 | D22: TP | H22: 0.97435897
A23: FULLY SIGNED - Onderhuurovereenkomst Aartshertogenlaan 223, `s-Hertogenbosch - Koning Willem I College B.V. 2606202.pdf | B23: 31/07/2029 | C23: 31/07/2029 | D23: TP | H23: 0.97435897
A24: FULLY SIGNED COMPL_DEF_Huurovereenkomst_Bond_Bergschot_Breda.pdf | B24: 31/12/2028 | C24: 31/12/2028 | D24: TP | H24: 0.98455902
A25: FullySigned_Allonge_II_Virtual_Vaults_Nederland.pdf | B25: 31/10/2032 | C25: 31/10/2027 | D25: TP | H25: 0.98455902
A26: FullySigned_Lease_Agreement_Neste_EDGE_Coolsingel.pdf | B26: 31/07/2032 | C26: 31/07/2032 | D26: TP | H26: 0.98206751
A27: HOK Waalhaven Group (signed).pdf | B27: 31/08/2031 | C27: 31/08/2031 | D27: TP | H27: 0.97435897
A28: Hovk Avans (3e+4e+5e verd.) 20140425.pdf | B28: 30/06/2019 | C28: 30/06/2019 | D28: TP | H28: 0.98455902
A29: HOVK Power4People 2025.pdf | B29: 30/06/2026 | C29: 30/06/2026 | D29: TP | H29: 0.98455902
A30: Huurovereenkomst (Semmie Group B.V.) - Wilhelminasingel 19, Breda.pdf | B30: 30/04/2029 | C30: 30/04/2029 | D30: TP | H30: 0.98455902
A31: Huurovereenkomst - proces-verbaal van oplevering - sleuteloverdracht - Kennedyplein 101 - getekend.pdf | B31: 28/02/2029 | C31: 28/02/2029 | D31: TP | H31: 0.98455902
... A35: Huurovereenkomst PBG Parallelweg 64 (beg.grond) 20121008.pdf | B35: 30/09/2017 | C35: 30/09/2017 | D35: TP | H35: 0.98455902
A36: MWO CBRE SPA (ITALY) CBRE_090724.pdf

Sheet Field 19
A1: Doc Name | B1: Manual Data | C1: Response Data | D1: Result | E1: Manual Pg | F1: Response Pg No | G1: Pg Result | H1: Confidence | K1: SUMMARY SHEET | N1: PAGE SUMMARY SHEET
A2: 20181204 Huurovereenkomst (GETEKEND).PDF | B2: 43202 | C2: 26/11/2010 | D2: FP | H2: 0.94582723 | K2: Metrics | L2: Percentage | N2: Metrics | O2: Percentage
A3: 2024.10.30_Office Rental Agreement Labs_Gruyter Fabriek.pdf | B3: 30/10/2024 | C3: 30/10/2024 | D3: TP | H3: 0.94582723 | K3: Precision | L3: =IFERROR(COUNTIFS(D2:D36,"TP")/(COUNTIFS(D2:D36,"TP")+COUNTIFS(D2:D36,"FP")),0) | N3: Precision | O3: =IFERROR(COUNTIFS(G2:G36,"TP")/(COUNTIFS(G2:G36,"TP")+COUNTIFS(G2:G36,"FP")),0)
A4: 20240606_HOK AKD - EDGE Eindhoven execution version.pdf | B4: 45449 | C4: 06/06/2024 | D4: TP | H4: 0.95543571 | K4: Recall | L4: =IFERROR(COUNTIFS(D2:D36,"TP")/(COUNTIFS(D2:D36,"TP")+COUNTIFS(D2:D36,"FN")),0) | N4: Recall | O4: =IFERROR(COUNTIFS(G2:G36,"TP")/(COUNTIFS(G2:G36,"TP")+COUNTIFS(G2:G36,"FN")),0)
A5: 20250117_HOK Duke Strategies - Hambaken A.05.09 DEF FULLY SIGNED.pdf | B5: 29/01/2025 | C5: 29/01/2025 | D5: TP | H5: 0.95308924 | K5: F1 Score | L5: =IFERROR(2*COUNTIFS(D2:D36,"TP")/(2*COUNTIFS(D2:D36,"TP")+COUNTIFS(D2:D36,"FP")+COUNTIFS(D2:D36,"FN")),0) | N5: F1 Score | O5: =IFERROR(2*COUNTIFS(G2:G36,"TP")/(2*COUNTIFS(G2:G36,"TP")+COUNTIFS(G2:G36,"FP")+COUNTIFS(G2:G36,"FN")),0)
A6: 20251216 Lease agreement ASPEN - signed.pdf | B6: 16/12/2025 | C6: 16/12/2025 | D6: TP | H6: 0.95308924 | K6: Accuracy % (With Not Exist) | L6: =IFERROR((COUNTIF(D2:D36,"TP")+COUNTIF(D2:D36,"TN"))/SUM(COUNTIF(D2:D36,{"TP","TN","FP","FN"})),0) | N6: Accuracy % (With Not Exist) | O6: =IFERROR((COUNTIF(G2:G36,"TP")+COUNTIF(G2:G36,"TN"))/SUM(COUNTIF(G2:G36,{"TP","TN","FP","FN"})),0)
A7: 20260220 Huurovereenkomst signed 20-02-2026.pdf | B7: 20/02/2026 | C7: 20/02/2026 | D7: TP | H7: 0.84705882 | K7: Total Docs Tested | L7: =COUNTA(A2:A36) | N7: Total Docs Tested | O7: =COUNTA(A2:A36)
A8: 20260629 HOK ADHDcentraal BV (1).pdf | B8: 23/07/2026 | C8: 23/07/2026 | D8: TP | H8: 0.95308924 | K8: No Of Docs With Data | L8: =COUNTIFS(B2:B36,"<>",B2:B36,"<>N/A",B2:B36,"<>Not Present In the Document",B2:B36,"<>Not Found",B2:B36,"<>i dont know",B2:B36,"<>i don't know") | N8: No Of Docs With Manual Pg | O8: =COUNTIFS(E2:E36,"<>",E2:E36,"<>N/A",E2:E36,"<>Not Present In the Document",E2:E36,"<>Not Found",E2:E36,"<>i dont know",E2:E36,"<>i don't know")
A9: 20260807_Happy_Village_B.V._Lease_Maasstadweg_tekenversie_incl._bijlagen en-GB.pdf | B9: 19/08/2026 | C9: 19/08/2026 | D9: TP | H9: 0.94582723 | K9: No Of Docs With Response | L9: =COUNTIFS(C2:C36,"<>") | N9: No Of Docs With Response Pg | O9: =COUNTIFS(F2:F36,"<>")
A10: 20260810 HOK ClustR BV.pdf | B10: 13/08/2026 | C10: 13/08/2026 | D10: TP | H10: 0.94582723 | K10: Highlighted rows = file(s) not in the annotation sheet; excluded from all metrics above.
A11: 20270801 - Getekende Allonge II Advario BV.pdf | B11: 01/09/2026 | C11: 01/09/2026 | D11: TP | E11: 7 | H11: 0.94828588 | K11: Validation Rules Example
A12: 240119 HOVK Spoorlaan 446-448 Tilburg signed.pdf | B12: 45600 | C12: 17/01/2024 | D12: FP | H12: 0.84705882 | K12: Manual Data | L12: Response Data | M12: Result
A13: 27001 Rijksvastgoedbedrijf Huurovereenkomst - __27-01-2026_9-07-56.pdf | B13: 43750 | C13: 43750 | D13: TP | H13: 0.84705882 | K13: 100 | L13: 100 | M13: TP
A14: CBRE_AT_Services_ENG_-_RITUALS_CBRE signed.pdf | B14: 44540 | C14: 11/10/2021 | D14: TP | H14: 0.95308924 | L14: 100 | M14: FP
A15: CBRE_Engagement_Letter_Alnylam_20260525_CLEAN_Version_signed all.pdf | B15: 46087 | C15: 03/06/2026 | D15: TP | H15: 0.95543571 | K15: 100 | L15: 200 | M15: FP
A16: COMPL DEF Huurovereenkomst - Skybox - Pepperl+Fuchs - 20260204.pdf | B16: 46328 | C16: 02/11/2026 | D16: TP | H16: 0.79144893 | K16: 100 | M16: FN
A17: COMPL Huurovereenkomst - Stichting CCE - Kantoorgebouw Metzpoint I Dr. Holtroplaan - Fully Signed.pdf | B17: 20/03/2025 | C17: 20/03/2025 | D17: TP | H17: 0.95308924 | M17: TN
A18: COMPL Regel Partners - HOVK - Luchthavenweg 81 - 20260728.pdf | B18: 28/07/2026 | D18: FP
A19: COMPL_-_Onderhuurovereenkomst_Zelfstroom_B.V._-_50five_B.V._-_kantoorgebouw_Riva_-_05032026.pdf | B19: 46329 | C19: 03/11/2026 | D19: TP | H19: 0.94582723 | K19: Field: | L19: Terms / Arrangement_Signed_Date
A20: Den Bosch, Ruwekampweg 4, HOVK getekend.pdf | B20: 29/06/2016 | C20: 29/06/2016 | D20: TP | H20: 0.8849162
A21: FULLY SIGNED - COMPL Huurovereenkomst - Heijmans - Hugo de Grootlaan 23 's-Hertogenbosch V2 30-9-2025.pdf | B21: 45879 | C21: 10/08/2025 | D21: TP | H21: 0.93292683
A22: FULLY SIGNED - DEF_COMPL_Huurovereenkomst_Robo_Charge_-_Campus_Offices_-_20260220.pdf | B22: 46056 | C22: 02/03/2026 | D22: TP | H22: 0.89722222
A23: FULLY SIGNED - Onderhuurovereenkomst Aartshertogenlaan 223, `s-Hertogenbosch - Koning Willem I College B.V. 2606202.pdf | B23: 45845 | C23: 07/07/2025 | D23: TP | H23: 0.94582723
A24: FULLY SIGNED COMPL_DEF_Huurovereenkomst_Bond_Bergschot_Breda.pdf | B24: 21/05/2025 | C24: 21/05/2025 | D24: TP | H24: 0.94582723
A25: FullySigned_Allonge_II_Virtual_Vaults_Nederland.pdf | B25: 17/08/2026 | C25: 16/03/2023 | D25: FP | H25: 0.95308924
A26: FullySigned_Lease_Agreement_Neste_EDGE_Coolsingel.pdf | B26: 18/08/2026 | C26: 18/08/2026 | D26: TP | H26: 0.8
A27: HOK Waalhaven Group (signed).pdf | B27: 46059 | C27: 02/06/2026 | D27: TP | H27: 0.95308924
A28: Hovk Avans (3e+4e+5e verd.) 20140425.pdf | B28: 25/04/2014 | C28: 27/05/2014 | D28: FP | H28: 0.93894487
A29: HOVK Power4People 2025.pdf | B29: 24/06/2025 | C29: 24/06/2025 | D29: TP | H29: 0.91038251
A30: Huurovereenkomst (Semmie Group B.V.) - Wilhelminasingel 19, Breda.pdf | B30: 46000 | C30: 21/01/2026 | D30: FP | H30: 0.89860896
A31: Huurovereenkomst - proces-verbaal van oplevering - sleuteloverdracht - Kennedyplein 101 - getekend.pdf | B31: 21/05/2026 | C31: 21/05/2026 | D31: TP | H31: 0.94582723
A32: Huurovereenkomst Bijster 5 te Breda getekend.pdf | B32: 45939 | C32: 10/09/2025 | D32: TP | H32: 0.94582723
A33: Huurovereenkomst Catena Pand Son - Skymark (Son en Breugel - NLD).pdf | B33: 41677 | C33: 14/07/2014 | D33: FP | H33: 0.84582651
A34: Huurovereenkomst KPN Opstelpunt Parallelweg 64 20130313.pdf | B34: 13/03/2013 | C34: 13/03/2013 | D34: TP | H34: 0.7219263
A35: Huurovereenkomst PBG Parallelweg 64 (beg.grond) 20121008.pdf | B35: 40918 | C35: 17/06/2015 | D35: FP | H35: 0.8
A36: MWO CBRE SPA (ITALY) CBRE_090724.pdf | B36: 24/09/2024 | C36: 24/09/2024 | D36: TP | H36: 0.95543571

Sheet Field 20
A1: Doc Name | B1: Manual Data | C1: Response Data | D1: Result | E1: Manual Pg | F1: Response Pg No | G1: Pg Result | H1: Confidence | K1: SUMMARY SHEET | N1: PAGE SUMMARY SHEET
A2: 20181204 Huurovereenkomst (GETEKEND).PDF | B2: 01/01/2019 | C2: 01/01/2019 | D2: TP | H2: 0.98455902 | K2: Metrics | L2: Percentage | N2: Metrics | O2: Percentage
A3: 2024.10.30_Office Rental Agreement Labs_Gruyter Fabriek.pdf | B3: 01/01/2025 | C3: 01/01/2025 | D3: TP | H3: 0.97435897 | K3: Precision | L3: =IFERROR(COUNTIFS(D2:D36,"TP")/(COUNTIFS(D2:D36,"TP")+COUNTIFS(D2:D36,"FP")),0) | N3: Precision | O3: =IFERROR(COUNTIFS(G2:G36,"TP")/(COUNTIFS(G2:G36,"TP")+COUNTIFS(G2:G36,"FP")),0)
A4: 20240606_HOK AKD - EDGE Eindhoven execution version.pdf | B4: 01/07/2026 | C4: 01/07/2026 | D4: TP | H4: 0.97435897 | K4: Recall | L4: =IFERROR(COUNTIFS(D2:D36,"TP")/(COUNTIFS(D2:D36,"TP")+COUNTIFS(D2:D36,"FN")),0) | N4: Recall | O4: =IFERROR(COUNTIFS(G2:G36,"TP")/(COUNTIFS(G2:G36,"TP")+COUNTIFS(G2:G36,"FN")),0)
A5: 20250117_HOK Duke Strategies - Hambaken A.05.09 DEF FULLY SIGNED.pdf | B5: 17/02/2025 | C5: 17/02/2025 | D5: TP | H5: 0.98206751 | K5: F1 Score | L5: =IFERROR(2*COUNTIFS(D2:D36,"TP")/(2*COUNTIFS(D2:D36,"TP")+COUNTIFS(D2:D36,"FP")+COUNTIFS(D2:D36,"FN")),0) | N5: F1 Score | O5: =IFERROR(2*COUNTIFS(G2:G36,"TP")/(2*COUNTIFS(G2:G36,"TP")+COUNTIFS(G2:G36,"FP")+COUNTIFS(G2:G36,"FN")),0)
A6: 20251216 Lease agreement ASPEN - signed.pdf | B6: 01/05/2025 | C6: 01/05/2025 | D6: TP | H6: 0.97435897 | K6: Accuracy % (With Not Exist) | L6: =IFERROR((COUNTIF(D2:D36,"TP")+COUNTIF(D2:D36,"TN"))/SUM(COUNTIF(D2:D36,{"TP","TN","FP","FN"})),0) | N6: Accuracy % (With Not Exist) | O6: =IFERROR((COUNTIF(G2:G36,"TP")+COUNTIF(G2:G36,"TN"))/SUM(COUNTIF(G2:G36,{"TP","TN","FP","FN"})),0)
A7: 20260220 Huurovereenkomst signed 20-02-2026.pdf | B7: 01/03/2026 | C7: 01/03/2026 | D7: TP | H7: 0.97435897 | K7: Total Docs Tested | L7: =COUNTA(A2:A36) | N7: Total Docs Tested | O7: =COUNTA(A2:A36)
A8: 20260629 HOK ADHDcentraal BV (1).pdf | B8: 01/09/2026 | C8: 01/09/2026 | D8: TP | H8: 0.98455902 | K8: No Of Docs With Data | L8: =COUNTIFS(B2:B36,"<>",B2:B36,"<>N/A",B2:B36,"<>Not Present In the Document",B2:B36,"<>Not Found",B2:B36,"<>i dont know",B2:B36,"<>i don't know") | N8: No Of Docs With Manual Pg | O8: =COUNTIFS(E2:E36,"<>",E2:E36,"<>N/A",E2:E36,"<>Not Present In the Document",E2:E36,"<>Not Found",E2:E36,"<>i dont know",E2:E36,"<>i don't know")
A9: 20260807_Happy_Village_B.V._Lease_Maasstadweg_tekenversie_incl._bijlagen en-GB.pdf | B9: 01/01/2027 | C9: 01/01/2027 | D9: TP | H9: 0.98455902 | K9: No Of Docs With Response | L9: =COUNTIFS(C2:C36,"<>") | N9: No Of Docs With Response Pg | O9: =COUNTIFS(F2:F36,"<>")
A10: 20260810 HOK ClustR BV.pdf | B10: 01/10/2026 | C10: 01/10/2026 | D10: TP | H10: 0.98206751 | K10: Highlighted rows = file(s) not in the annotation sheet; excluded from all metrics above.
A11: 20270801 - Getekende Allonge II Advario BV.pdf | B11: 01/08/2022 | C11: 01/08/2022 | D11: TP | H11: 0.93349876 | K11: Validation Rules Example
A12: 240119 HOVK Spoorlaan 446-448 Tilburg signed.pdf | B12: 01/04/2024 | C12: 01/04/2024 | D12: TP | H12: 0.97435897 | K12: Manual Data | L12: Response Data | M12: Result
A13: 27001 Rijksvastgoedbedrijf Huurovereenkomst - __27-01-2026_9-07-56.pdf | B13: 01/09/2019 | C13: 01/09/2019 | D13: TP | H13: 0.97435897 | K13: 100 | L13: 100 | M13: TP
A14: CBRE_AT_Services_ENG_-_RITUALS_CBRE signed.pdf | B14: i dont know | D14: FN | L14: 100 | M14: FP
A15: CBRE_Engagement_Letter_Alnylam_20260525_CLEAN_Version_signed all.pdf | B15: 03/06/2026 | C15: 03/06/2026 | D15: TP | H15: 0.89722222 | K15: 100 | L15: 200 | M15: FP
A16: COMPL DEF Huurovereenkomst - Skybox - Pepperl+Fuchs - 20260204.pdf | B16: 01/12/2026 | C16: 01/12/2026 | D16: TP | H16: 0.97435897 | K16: 100 | M16: FN
A17: COMPL Huurovereenkomst - Stichting CCE - Kantoorgebouw Metzpoint I Dr. Holtroplaan - Fully Signed.pdf | B17: 01/05/2025 | C17: 01/05/2025 | D17: TP | H17: 0.98455902 | M17: TN
A18: COMPL Regel Partners - HOVK - Luchthavenweg 81 - 20260728.pdf | B18: 01/10/2026 | C18: 01/10/2026 | D18: TP | H18: 0.98455902
A19: COMPL_-_Onderhuurovereenkomst_Zelfstroom_B.V._-_50five_B.V._-_kantoorgebouw_Riva_-_05032026.pdf | B19: 01/04/2026 | C19: 01/04/2026 | D19: TP | H19: 0.97435897 | K19: Field: | L19: Terms / Arrangement_Start_Date
A20: Den Bosch, Ruwekampweg 4, HOVK getekend.pdf | B20: 01/01/2017 | C20: 01/01/2017 | D20: TP | H20: 0.97435897
A21: FULLY SIGNED - COMPL Huurovereenkomst - Heijmans - Hugo de Grootlaan 23 's-Hertogenbosch V2 30-9-2025.pdf | B21: 15/10/2025 | C21: 15/10/2025 | D21: TP | H21: 0.98455902
A22: FULLY SIGNED - DEF_COMPL_Huurovereenkomst_Robo_Charge_-_Campus_Offices_-_20260220.pdf | B22: 01/04/2026 | C22: 01/04/2026 | D22: TP | H22: 0.98455902
A23: FULLY SIGNED - Onderhuurovereenkomst Aartshertogenlaan 223, `s-Hertogenbosch - Koning Willem I College B.V. 2606202.pdf | B23: 01/08/2025 | C23: 01/08/2025 | D23: TP | H23: 0.97435897
A24: FULLY SIGNED COMPL_DEF_Huurovereenkomst_Bond_Bergschot_Breda.pdf | B24: 01/07/2025 | C24: 01/07/2025 | D24: TP | H24: 0.97435897
A25: FullySigned_Allonge_II_Virtual_Vaults_Nederland.pdf | B25: 01/11/2018 | C25: 01/11/2018 | D25: TP | H25: 0.97435897
A26: FullySigned_Lease_Agreement_Neste_EDGE_Coolsingel.pdf | B26: 01/08/2027 | C26: 01/08/2027 | D26: TP | H26: 0.97435897
A27: HOK Waalhaven Group (signed).pdf | B27: 01/09/2026 | C27: 01/09/2026 | D27: TP | H27: 0.97435897
A28: Hovk Avans (3e+4e+5e verd.) 20140425.pdf | B28: 01/05/2014 | C28: 01/05/2014 | D28: TP | H28: 0.97435897
A29: HOVK Power4People 2025.pdf | B29: 01/07/2025 | C29: 01/07/2025 | D29: TP | H29: 0.98206751
A30: Huurovereenkomst (Semmie Group B.V.) - Wilhelminasingel 19, Breda.pdf | B30: 15/01/2026 | C30: 15/01/2026 | D30: TP | H30: 0.97435897
A31: Huurovereenkomst - proces-verbaal van oplevering - sleuteloverdracht - Kennedyplein 101 - getekend.pdf | B31: 01/03/2026 | C31: 01/03/2026 | D31: TP | H31: 0.98455902
... A36: MWO CBRE SPA (ITALY) CBRE_090724.pdf | B36: 24/09/2024 | C36: 24/09/2024 | D36: TP | H36: 0.94285714

Sheet Field 21
A1: Doc Name | B1: Manual Data | C1: Response Data | D1: Result | E1: Manual Pg | F1: Response Pg No | G1: Pg Result | H1: Confidence | K1: SUMMARY SHEET | N1: PAGE SUMMARY SHEET
A2: 20181204 Huurovereenkomst (GETEKEND).PDF | B2: 583.33 | C2: 583.33 | D2: TP | H2: 0.95543571 | K2: Metrics | L2: Percentage | N2: Metrics | O2: Percentage
A3: 2024.10.30_Office Rental Agreement Labs_Gruyter Fabriek.pdf | B3: 8835 | C3: 8835 | D3: TP | H3: 0.95543571 | K3: Precision | L3: =IFERROR(COUNTIFS(D2:D36,"TP")/(COUNTIFS(D2:D36,"TP")+COUNTIFS(D2:D36,"FP")),0) | N3: Precision | O3: =IFERROR(COUNTIFS(G2:G36,"TP")/(COUNTIFS(G2:G36,"TP")+COUNTIFS(G2:G36,"FP")),0)
A4: 20240606_HOK AKD - EDGE Eindhoven execution version.pdf | B4: 59465.83 | C4: 713590 | D4: FP | H4: 0.95543571 | K4: Recall | L4: =IFERROR(COUNTIFS(D2:D36,"TP")/(COUNTIFS(D2:D36,"TP")+COUNTIFS(D2:D36,"FN")),0) | N4: Recall | O4: =IFERROR(COUNTIFS(G2:G36,"TP")/(COUNTIFS(G2:G36,"TP")+COUNTIFS(G2:G36,"FN")),0)
A5: 20250117_HOK Duke Strategies - Hambaken A.05.09 DEF FULLY SIGNED.pdf | B5: 982.33 | C5: 652.25 | D5: FP | H5: 0.95308924 | K5: F1 Score | L5: =IFERROR(2*COUNTIFS(D2:D36,"TP")/(2*COUNTIFS(D2:D36,"TP")+COUNTIFS(D2:D36,"FP")+COUNTIFS(D2:D36,"FN")),0) | N5: F1 Score | O5: =IFERROR(2*COUNTIFS(G2:G36,"TP")/(2*COUNTIFS(G2:G36,"TP")+COUNTIFS(G2:G36,"FP")+COUNTIFS(G2:G36,"FN")),0)
A6: 20251216 Lease agreement ASPEN - signed.pdf | B6: 245000 | C6: 245000 | D6: TP | H6: 0.91891892 | K6: Accuracy % (With Not Exist) | L6: =IFERROR((COUNTIF(D2:D36,"TP")+COUNTIF(D2:D36,"TN"))/SUM(COUNTIF(D2:D36,{"TP","TN","FP","FN"})),0) | N6: Accuracy % (With Not Exist) | O6: =IFERROR((COUNTIF(G2:G36,"TP")+COUNTIF(G2:G36,"TN"))/SUM(COUNTIF(G2:G36,{"TP","TN","FP","FN"})),0)
A7: 20260220 Huurovereenkomst signed 20-02-2026.pdf | B7: 2267.92 | C7: 2267.92 | D7: TP | H7: 0.95543571 | K7: Total Docs Tested | L7: =COUNTA(A2:A36) | N7: Total Docs Tested | O7: =COUNTA(A2:A36)
A8: 20260629 HOK ADHDcentraal BV (1).pdf | B8: 4695.61 | C8: 3380.74 | D8: FP | H8: 0.94582723 | K8: No Of Docs With Data | L8: =COUNTIFS(B2:B36,"<>",B2:B36,"<>N/A",B2:B36,"<>Not Present In the Document",B2:B36,"<>Not Found",B2:B36,"<>i dont know",B2:B36,"<>i don't know") | N8: No Of Docs With Manual Pg | O8: =COUNTIFS(E2:E36,"<>",E2:E36,"<>N/A",E2:E36,"<>Not Present In the Document",E2:E36,"<>Not Found",E2:E36,"<>i dont know",E2:E36,"<>i don't know")
A9: 20260807_Happy_Village_B.V._Lease_Maasstadweg_tekenversie_incl._bijlagen en-GB.pdf | B9: 22733.67 | C9: 22733.67 | H9: 0.95543571 | K9: No Of Docs With Response | L9: =COUNTIFS(C2:C36,"<>") | N9: No Of Docs With Response Pg | O9: =COUNTIFS(F2:F36,"<>")
A10: 20260810 HOK ClustR BV.pdf | B10: 3325.13 | C10: 1865.67 | D10: FP | H10: 0.95543571 | K10: Highlighted rows = file(s) not in the annotation sheet; excluded from all metrics above.
A11: 20270801 - Getekende Allonge II Advario BV.pdf | B11: 24420.89 | C11: 24357.08 | D11: TP | E11: 3 | H11: 0.82067021 | K11: Validation Rules Example
A12: 240119 HOVK Spoorlaan 446-448 Tilburg signed.pdf | B12: 33750 | C12: 33750 | D12: TP | H12: 0.95543571 | K12: Manual Data | L12: Response Data | M12: Result
A13: 27001 Rijksvastgoedbedrijf Huurovereenkomst - __27-01-2026_9-07-56.pdf | B13: 66497.37 | C13: 66497.36 | D13: TP | H13: 0.897002 | K13: 100 | L13: 100 | M13: TP
A14: CBRE_AT_Services_ENG_-_RITUALS_CBRE signed.pdf | B14: i dont know | C14: 41666.67 | D14: TP | H14: 0.87428571 | L14: 100 | M14: FP
A15: CBRE_Engagement_Letter_Alnylam_20260525_CLEAN_Version_signed all.pdf | B15: i dont know | D15: FP | K15: 100 | L15: 200 | M15: FP
A16: COMPL DEF Huurovereenkomst - Skybox - Pepperl+Fuchs - 20260204.pdf | B16: 5360.83 | C16: 4902.5 | D16: FP | H16: 0.44037715 | K16: 100 | M16: FN
A17: COMPL Huurovereenkomst - Stichting CCE - Kantoorgebouw Metzpoint I Dr. Holtroplaan - Fully Signed.pdf | B17: 3759.5 | C17: 3759.5 | D17: TP | H17: 0.95543571 | M17: TN
A18: COMPL Regel Partners - HOVK - Luchthavenweg 81 - 20260728.pdf | B18: 4292.13 | C18: 4275.46 | D18: TP | H18: 0.77371795
A19: COMPL_-_Onderhuurovereenkomst_Zelfstroom_B.V._-_50five_B.V._-_kantoorgebouw_Riva_-_05032026.pdf | B19: 17620.63 | C19: 17620.63 | D19: TP | H19: 0.91891892 | K19: Field: | L19: Terms / Asking_Rent_Monthly
A20: Den Bosch, Ruwekampweg 4, HOVK getekend.pdf | B20: 7916.67 | C20: 7916.67 | D20: TP | H20: 0.95543571
A21: FULLY SIGNED - COMPL Huurovereenkomst - Heijmans - Hugo de Grootlaan 23 's-Hertogenbosch V2 30-9-2025.pdf | B21: 5368.99 | C21: 5352.32 | D21: TP | H21: 0.58498909
A22: FULLY SIGNED - DEF_COMPL_Huurovereenkomst_Robo_Charge_-_Campus_Offices_-_20260220.pdf | B22: 4628.67 | C22: 4628.67 | D22: TP | H22: 0.95308924
A23: FULLY SIGNED - Onderhuurovereenkomst Aartshertogenlaan 223, `s-Hertogenbosch - Koning Willem I College B.V. 2606202.pdf | B23: 9514.74 | C23: 9514.74 | D23: TP | H23: 0.95543571
A24: FULLY SIGNED COMPL_DEF_Huurovereenkomst_Bond_Bergschot_Breda.pdf | B24: 15014.85 | C24: 15014.85 | D24: TP | H24: 0.95308924
A25: FullySigned_Allonge_II_Virtual_Vaults_Nederland.pdf | B25: 19322.22 | C25: 19226.66 | D25: TP | H25: 0.64656166
A26: FullySigned_Lease_Agreement_Neste_EDGE_Coolsingel.pdf | B26: 37825 | C26: 37825 | D26: TP | H26: 0.95543571
A27: HOK Waalhaven Group (signed).pdf | B27: 10707.5 | C27: 10707.5 | D27: TP | H27: 0.91891892
A28: Hovk Avans (3e+4e+5e verd.) 20140425.pdf | B28: 16702.5 | C28: 16702.5 | D28: TP | H28: 0.95543571
A29: HOVK Power4People 2025.pdf | B29: 2020 | C29: 1170 | D29: FP | H29: 0.95308924
A30: Huurovereenkomst (Semmie Group B.V.) - Wilhelminasingel 19, Breda.pdf | B30: 2455.79 | C30: 2117.5 | D30: FP | H30: 0.95543571
A31: Huurovereenkomst - proces-verbaal van oplevering - sleuteloverdracht - Kennedyplein 101 - getekend.pdf | B31: 6013.5 | C31: 6013.5 | D31: TP | H31: 0.95543571
... A35: Huurovereenkomst PBG Parallelweg 64 (beg.grond) 20121008.pdf | B35: 8219.17 | C35: 8219.17 | D35: TP | H35: 0.95543571
A36: MWO CBRE SPA (ITALY) CBRE_090724.pdf | B36: i dont know | D36: FP

Sheet Field 22
A1: Doc Name | B1: Manual Data | C1: Response Data | D1: Result | E1: Manual Pg | F1: Response Pg No | G1: Pg Result | H1: Confidence | K1: SUMMARY SHEET | N1: PAGE SUMMARY SHEET
A2: 20181204 Huurovereenkomst (GETEKEND).PDF | B2: 7000 | C2: 7000 | H2: 0.91891892 | K2: Metrics | L2: Percentage | N2: Metrics | O2: Percentage
A3: 2024.10.30_Office Rental Agreement Labs_Gruyter Fabriek.pdf | B3: 106020 | C3: 106020 | H3: 0.95543571 | K3: Precision | L3: =IFERROR(COUNTIFS(D2:D36,"TP")/(COUNTIFS(D2:D36,"TP")+COUNTIFS(D2:D36,"FP")),0) | N3: Precision | O3: =IFERROR(COUNTIFS(G2:G36,"TP")/(COUNTIFS(G2:G36,"TP")+COUNTIFS(G2:G36,"FP")),0)
A4: 20240606_HOK AKD - EDGE Eindhoven execution version.pdf | B4: 713590 | C4: 713590 | H4: 0.93894487 | K4: Recall | L4: =IFERROR(COUNTIFS(D2:D36,"TP")/(COUNTIFS(D2:D36,"TP")+COUNTIFS(D2:D36,"FN")),0) | N4: Recall | O4: =IFERROR(COUNTIFS(G2:G36,"TP")/(COUNTIFS(G2:G36,"TP")+COUNTIFS(G2:G36,"FN")),0)
A5: 20250117_HOK Duke Strategies - Hambaken A.05.09 DEF FULLY SIGNED.pdf | B5: 11788 | C5: 7827 | H5: 0.95543571 | K5: F1 Score | L5: =IFERROR(2*COUNTIFS(D2:D36,"TP")/(2*COUNTIFS(D2:D36,"TP")+COUNTIFS(D2:D36,"FP")+COUNTIFS(D2:D36,"FN")),0) | N5: F1 Score | O5: =IFERROR(2*COUNTIFS(G2:G36,"TP")/(2*COUNTIFS(G2:G36,"TP")+COUNTIFS(G2:G36,"FP")+COUNTIFS(G2:G36,"FN")),0)
A6: 20251216 Lease agreement ASPEN - signed.pdf | B6: 2940000 | C6: 2940000 | H6: 0.64656166 | K6: Accuracy % (With Not Exist) | L6: =IFERROR((COUNTIF(D2:D36,"TP")+COUNTIF(D2:D36,"TN"))/SUM(COUNTIF(D2:D36,{"TP","TN","FP","FN"})),0) | N6: Accuracy % (With Not Exist) | O6: =IFERROR((COUNTIF(G2:G36,"TP")+COUNTIF(G2:G36,"TN"))/SUM(COUNTIF(G2:G36,{"TP","TN","FP","FN"})),0)
A7: 20260220 Huurovereenkomst signed 20-02-2026.pdf | B7: 27215 | C7: 25715 | H7: 0.95543571 | K7: Total Docs Tested | L7: =COUNTA(A2:A36) | N7: Total Docs Tested | O7: =COUNTA(A2:A36)
A8: 20260629 HOK ADHDcentraal BV (1).pdf | B8: 56347.35 | C8: 40568.85 | H8: 0.95308924 | K8: No Of Docs With Data | L8: =COUNTIFS(B2:B36,"<>",B2:B36,"<>N/A",B2:B36,"<>Not Present In the Document",B2:B36,"<>Not Found",B2:B36,"<>i dont know",B2:B36,"<>i don't know") | N8: No Of Docs With Manual Pg | O8: =COUNTIFS(E2:E36,"<>",E2:E36,"<>N/A",E2:E36,"<>Not Present In the Document",E2:E36,"<>Not Found",E2:E36,"<>i dont know",E2:E36,"<>i don't know")
A9: 20260807_Happy_Village_B.V._Lease_Maasstadweg_tekenversie_incl._bijlagen en-GB.pdf | B9: 272804 | C9: 272804 | H9: 0.91891892 | K9: No Of Docs With Response | L9: =COUNTIFS(C2:C36,"<>") | N9: No Of Docs With Response Pg | O9: =COUNTIFS(F2:F36,"<>")
A10: 20260810 HOK ClustR BV.pdf | B10: 39901.6 | C10: 22388 | H10: 0.95070626 | K10: Highlighted rows = file(s) not in the annotation sheet; excluded from all metrics above.
A11: 20270801 - Getekende Allonge II Advario BV.pdf | B11: 293050.69 | C11: 291685 | E11: 3 | H11: 0.48501441 | K11: Validation Rules Example
A12: 240119 HOVK Spoorlaan 446-448 Tilburg signed.pdf | B12: 405000 | C12: 405000 | H12: 0.93894487 | K12: Manual Data | L12: Response Data | M12: Result
A13: 27001 Rijksvastgoedbedrijf Huurovereenkomst - __27-01-2026_9-07-56.pdf | B13: 797968.38 | C13: 797968.38 | H13: 0.95543571 | K13: 100 | L13: 100 | M13: TP
A14: CBRE_AT_Services_ENG_-_RITUALS_CBRE signed.pdf | B14: i dont know | C14: 500000 | H14: 0.90356594 | L14: 100 | M14: FP
A15: CBRE_Engagement_Letter_Alnylam_20260525_CLEAN_Version_signed all.pdf | B15: i dont know | K15: 100 | L15: 200 | M15: FP
A16: COMPL DEF Huurovereenkomst - Skybox - Pepperl+Fuchs - 20260204.pdf | B16: 64330 | C16: 58830 | H16: 0.95543571 | K16: 100 | M16: FN
A17: COMPL Huurovereenkomst - Stichting CCE - Kantoorgebouw Metzpoint I Dr. Holtroplaan - Fully Signed.pdf | B17: 45114 | C17: 45114 | H17: 0.95543571 | M17: TN
A18: COMPL Regel Partners - HOVK - Luchthavenweg 81 - 20260728.pdf | B18: 51505.5 | C18: 51505.5 | H18: 0.95543571
A19: COMPL_-_Onderhuurovereenkomst_Zelfstroom_B.V._-_50five_B.V._-_kantoorgebouw_Riva_-_05032026.pdf | B19: 211447.56 | C19: 211447.56 | H19: 0.94582723 | K19: Field: | L19: Terms / Asking_Rent_Yearly
A20: Den Bosch, Ruwekampweg 4, HOVK getekend.pdf | B20: 95000 | C20: 95000 | H20: 0.91891892
A21: FULLY SIGNED - COMPL Huurovereenkomst - Heijmans - Hugo de Grootlaan 23 's-Hertogenbosch V2 30-9-2025.pdf | B21: 64427.84 | C21: 64427.84 | H21: 0.95543571
A22: FULLY SIGNED - DEF_COMPL_Huurovereenkomst_Robo_Charge_-_Campus_Offices_-_20260220.pdf | B22: 55544 | C22: 55544 | H22: 0.91891892
A23: FULLY SIGNED - Onderhuurovereenkomst Aartshertogenlaan 223, `s-Hertogenbosch - Koning Willem I College B.V. 2606202.pdf | B23: 114176.88 | C23: 114176.88 | H23: 0.94109059
A24: FULLY SIGNED COMPL_DEF_Huurovereenkomst_Bond_Bergschot_Breda.pdf | B24: 180178.2 | C24: 180178.2 | H24: 0.91891892
A25: FullySigned_Allonge_II_Virtual_Vaults_Nederland.pdf | B25: 231866.6 | C25: 191575 | H25: 0.95543571
A26: FullySigned_Lease_Agreement_Neste_EDGE_Coolsingel.pdf | B26: 453900 | C26: 453900 | H26: 0.91891892
A27: HOK Waalhaven Group (signed).pdf | B27: 128490 | C27: 128490 | H27: 0.95543571
A28: Hovk Avans (3e+4e+5e verd.) 20140425.pdf | B28: 200430 | C28: 200430 | H28: 0.95543571
A29: HOVK Power4People 2025.pdf | B29: 24240 | C29: 25200 | H29: 0.70344828
A30: Huurovereenkomst (Semmie Group B.V.) - Wilhelminasingel 19, Breda.pdf | B30: 29469.55 | C30: 29469.55 | H30: 0.91891892
A31: Huurovereenkomst - proces-verbaal van oplevering - sleuteloverdracht - Kennedyplein 101 - getekend.pdf | B31: 72162 | C31: 72162 | H31: 0.95543571
... A35: Huurovereenkomst PBG Parallelweg 64 (beg.grond) 20121008.pdf | B35: 98630 | C35: 98630 | H35: 0.91891892
A36: MWO CBRE SPA (ITALY) CBRE_090724.pdf | B36: i dont know

Sheet Field 23
A1: Doc Name | B1: Manual Data | C1: Response Data | D1: Result | E1: Manual Pg | F1: Response Pg No | G1: Pg Result | H1: Confidence | K1: SUMMARY SHEET | N1: PAGE SUMMARY SHEET
A2: 20181204 Huurovereenkomst (GETEKEND).PDF | K2: Metrics | L2: Percentage | N2: Metrics | O2: Percentage
A3: 2024.10.30_Office Rental Agreement Labs_Gruyter Fabriek.pdf | K3: Precision | L3: =IFERROR(COUNTIFS(D2:D36,"TP")/(COUNTIFS(D2:D36,"TP")+COUNTIFS(D2:D36,"FP")),0) | N3: Precision | O3: =IFERROR(COUNTIFS(G2:G36,"TP")/(COUNTIFS(G2:G36,"TP")+COUNTIFS(G2:G36,"FP")),0)
A4: 20240606_HOK AKD - EDGE Eindhoven execution version.pdf | B4: 2300 | C4: 2300 | H4: 0.9622852 | K4: Recall | L4: =IFERROR(COUNTIFS(D2:D36,"TP")/(COUNTIFS(D2:D36,"TP")+COUNTIFS(D2:D36,"FN")),0) | N4: Recall | O4: =IFERROR(COUNTIFS(G2:G36,"TP")/(COUNTIFS(G2:G36,"TP")+COUNTIFS(G2:G36,"FN")),0)
A5: 20250117_HOK Duke Strategies - Hambaken A.05.09 DEF FULLY SIGNED.pdf | B5: 500 | C5: 500 | H5: 0.9622852 | K5: F1 Score | L5: =IFERROR(2*COUNTIFS(D2:D36,"TP")/(2*COUNTIFS(D2:D36,"TP")+COUNTIFS(D2:D36,"FP")+COUNTIFS(D2:D36,"FN")),0) | N5: F1 Score | O5: =IFERROR(2*COUNTIFS(G2:G36,"TP")/(2*COUNTIFS(G2:G36,"TP")+COUNTIFS(G2:G36,"FP")+COUNTIFS(G2:G36,"FN")),0)
A6: 20251216 Lease agreement ASPEN - signed.pdf | K6: Accuracy % (With Not Exist) | L6: =IFERROR((COUNTIF(D2:D36,"TP")+COUNTIF(D2:D36,"TN"))/SUM(COUNTIF(D2:D36,{"TP","TN","FP","FN"})),0) | N6: Accuracy % (With Not Exist) | O6: =IFERROR((COUNTIF(G2:G36,"TP")+COUNTIF(G2:G36,"TN"))/SUM(COUNTIF(G2:G36,{"TP","TN","FP","FN"})),0)
A7: 20260220 Huurovereenkomst signed 20-02-2026.pdf | B7: 750 | C7: 750 | H7: 0.96467722 | K7: Total Docs Tested | L7: =COUNTA(A2:A36) | N7: Total Docs Tested | O7: =COUNTA(A2:A36)
A8: 20260629 HOK ADHDcentraal BV (1).pdf | B8: 750 | C8: 750 | H8: 0.95488292 | K8: No Of Docs With Data | L8: =COUNTIFS(B2:B36,"<>",B2:B36,"<>N/A",B2:B36,"<>Not Present In the Document",B2:B36,"<>Not Found",B2:B36,"<>i dont know",B2:B36,"<>i don't know") | N8: No Of Docs With Manual Pg | O8: =COUNTIFS(E2:E36,"<>",E2:E36,"<>N/A",E2:E36,"<>Not Present In the Document",E2:E36,"<>Not Found",E2:E36,"<>i dont know",E2:E36,"<>i don't know")
A9: 20260807_Happy_Village_B.V._Lease_Maasstadweg_tekenversie_incl._bijlagen en-GB.pdf | K9: No Of Docs With Response | L9: =COUNTIFS(C2:C36,"<>") | N9: No Of Docs With Response Pg | O9: =COUNTIFS(F2:F36,"<>")
A10: 20260810 HOK ClustR BV.pdf | B10: 750 | C10: 750 | H10: 0.96467722 | K10: Highlighted rows = file(s) not in the annotation sheet; excluded from all metrics above.
A11: 20270801 - Getekende Allonge II Advario BV.pdf | K11: Validation Rules Example
A12: 240119 HOVK Spoorlaan 446-448 Tilburg signed.pdf | K12: Manual Data | L12: Response Data | M12: Result
A13: 27001 Rijksvastgoedbedrijf Huurovereenkomst - __27-01-2026_9-07-56.pdf | B13: 1130.48 | C13: 1130.48 | H13: 0.9622852 | K13: 100 | L13: 100 | M13: TP
A14: CBRE_AT_Services_ENG_-_RITUALS_CBRE signed.pdf | L14: 100 | M14: FP
A15: CBRE_Engagement_Letter_Alnylam_20260525_CLEAN_Version_signed all.pdf | K15: 100 | L15: 200 | M15: FP
A16: COMPL DEF Huurovereenkomst - Skybox - Pepperl+Fuchs - 20260204.pdf | B16: 550 | C16: 550 | H16: 0.9622852 | K16: 100 | M16: FN
A17: COMPL Huurovereenkomst - Stichting CCE - Kantoorgebouw Metzpoint I Dr. Holtroplaan - Fully Signed.pdf | B17: 650 | C17: 650 | H17: 0.96467722 | M17: TN
A18: COMPL Regel Partners - HOVK - Luchthavenweg 81 - 20260728.pdf | B18: 750 | C18: 750 | H18: 0.93617021
A19: COMPL_-_Onderhuurovereenkomst_Zelfstroom_B.V._-_50five_B.V._-_kantoorgebouw_Riva_-_05032026.pdf | B19: 1600 | C19: 1600 | H19: 0.9622852 | K19: Field: | L19: Terms / Cost_per_Reserved_Parking_Space
A20: Den Bosch, Ruwekampweg 4, HOVK getekend.pdf
A21: FULLY SIGNED - COMPL Huurovereenkomst - Heijmans - Hugo de Grootlaan 23 's-Hertogenbosch V2 30-9-2025.pdf | B21: 1813.92 | C21: 1813.92 | H21: 0.9622852
A22: FULLY SIGNED - DEF_COMPL_Huurovereenkomst_Robo_Charge_-_Campus_Offices_-_20260220.pdf | B22: 750 | C22: 750 | H22: 0.96467722
A23: FULLY SIGNED - Onderhuurovereenkomst Aartshertogenlaan 223, `s-Hertogenbosch - Koning Willem I College B.V. 2606202.pdf
A24: FULLY SIGNED COMPL_DEF_Huurovereenkomst_Bond_Bergschot_Breda.pdf | B24: 750 | C24: 750 | H24: 0.9622852
A25: FullySigned_Allonge_II_Virtual_Vaults_Nederland.pdf | B25: 1200 | C25: 1200 | H25: 0.96467722
A26: FullySigned_Lease_Agreement_Neste_EDGE_Coolsingel.pdf
A27: HOK Waalhaven Group (signed).pdf | B27: 950 | C27: 950 | H27: 0.96467722
A28: Hovk Avans (3e+4e+5e verd.) 20140425.pdf | B28: 350 | C28: 350 | H28: 0.96467722
A29: HOVK Power4People 2025.pdf | B29: 130 | C29: 130 | H29: 0.95543571
A30: Huurovereenkomst (Semmie Group B.V.) - Wilhelminasingel 19, Breda.pdf
A31: Huurovereenkomst - proces-verbaal van oplevering - sleuteloverdracht - Kennedyplein 101 - getekend.pdf | B31: 0 | C31: 0 | H31: 0.9136612
A32: Huurovereenkomst Bijster 5 te Breda getekend.pdf | B32: 500 | C32: 500 | H32: 0.28732582
A33: Huurovereenkomst Catena Pand Son - Skymark (Son en Breugel - NLD).pdf
A34: Huurovereenkomst KPN Opstelpunt Parallelweg 64 20130313.pdf
A35: Huurovereenkomst PBG Parallelweg 64 (beg.grond) 20121008.pdf | B35: 750 | C35: 750 | H35: 0.87596157
A36: MWO CBRE SPA (ITALY) CBRE_090724.pdf | B36: 20000 | C36: 20000 | H36: 0.86473988

Sheet Field 24
A1: Doc Name | B1: Manual Data | C1: Response Data | D1: Result | E1: Manual Pg | F1: Response Pg No | G1: Pg Result | H1: Confidence | K1: SUMMARY SHEET | N1: PAGE SUMMARY SHEET
A2: 20181204 Huurovereenkomst (GETEKEND).PDF | B2: 583.33 | C2: 583.33 | H2: 0.95308924 | K2: Metrics | L2: Percentage | N2: Metrics | O2: Percentage
A3: 2024.10.30_Office Rental Agreement Labs_Gruyter Fabriek.pdf | B3: 8687.75 | C3: 8835 | E3: 9 | H3: 0.91038251 | K3: Precision | L3: =IFERROR(COUNTIFS(D2:D36,"TP")/(COUNTIFS(D2:D36,"TP")+COUNTIFS(D2:D36,"FP")),0) | N3: Precision | O3: =IFERROR(COUNTIFS(G2:G36,"TP")/(COUNTIFS(G2:G36,"TP")+COUNTIFS(G2:G36,"FP")),0)
A4: 20240606_HOK AKD - EDGE Eindhoven execution version.pdf | B4: 59465.83 | C4: 65453.21 | E4: 4, 8 | H4: 0.90604396 | K4: Recall | L4: =IFERROR(COUNTIFS(D2:D36,"TP")/(COUNTIFS(D2:D36,"TP")+COUNTIFS(D2:D36,"FN")),0) | N4: Recall | O4: =IFERROR(COUNTIFS(G2:G36,"TP")/(COUNTIFS(G2:G36,"TP")+COUNTIFS(G2:G36,"FN")),0)
A5: 20250117_HOK Duke Strategies - Hambaken A.05.09 DEF FULLY SIGNED.pdf | B5: 982.33 | C5: 982.33 | H5: 0.68572498 | K5: F1 Score | L5: =IFERROR(2*COUNTIFS(D2:D36,"TP")/(2*COUNTIFS(D2:D36,"TP")+COUNTIFS(D2:D36,"FP")+COUNTIFS(D2:D36,"FN")),0) | N5: F1 Score | O5: =IFERROR(2*COUNTIFS(G2:G36,"TP")/(2*COUNTIFS(G2:G36,"TP")+COUNTIFS(G2:G36,"FP")+COUNTIFS(G2:G36,"FN")),0)
A6: 20251216 Lease agreement ASPEN - signed.pdf | B6: 245000 | C6: 245000 | H6: 0.95543571 | K6: Accuracy % (With Not Exist) | L6: =IFERROR((COUNTIF(D2:D36,"TP")+COUNTIF(D2:D36,"TN"))/SUM(COUNTIF(D2:D36,{"TP","TN","FP","FN"})),0) | N6: Accuracy % (With Not Exist) | O6: =IFERROR((COUNTIF(G2:G36,"TP")+COUNTIF(G2:G36,"TN"))/SUM(COUNTIF(G2:G36,{"TP","TN","FP","FN"})),0)
A7: 20260220 Huurovereenkomst signed 20-02-2026.pdf | B7: 2267.92 | C7: 2267.92 | H7: 0.95070626 | K7: Total Docs Tested | L7: =COUNTA(A2:A36) | N7: Total Docs Tested | O7: =COUNTA(A2:A36)
A8: 20260629 HOK ADHDcentraal BV (1).pdf | B8: 4108.66 | C8: 4695.61 | E8: 3 | H8: 0.24268026 | K8: No Of Docs With Data | L8: =COUNTIFS(B2:B36,"<>",B2:B36,"<>N/A",B2:B36,"<>Not Present In the Document",B2:B36,"<>Not Found",B2:B36,"<>i dont know",B2:B36,"<>i don't know") | N8: No Of Docs With Manual Pg | O8: =COUNTIFS(E2:E36,"<>",E2:E36,"<>N/A",E2:E36,"<>Not Present In the Document",E2:E36,"<>Not Found",E2:E36,"<>i dont know",E2:E36,"<>i don't know")
A9: 20260807_Happy_Village_B.V._Lease_Maasstadweg_tekenversie_incl._bijlagen en-GB.pdf | B9: 22165.33 | C9: 22733.67 | E9: 10 | F9: 2 | H9: 0.95543571 | K9: No Of Docs With Response | L9: =COUNTIFS(C2:C36,"<>") | N9: No Of Docs With Response Pg | O9: =COUNTIFS(F2:F36,"<>")
A10: 20260810 HOK ClustR BV.pdf | B10: 2909.49 | C10: 3325.13 | E10: 2 | H10: 0.95308924 | K10: Highlighted rows = file(s) not in the annotation sheet; excluded from all metrics above.
A11: 20270801 - Getekende Allonge II Advario BV.pdf | B11: 21990.18 | C11: 33973.54 | E11: 5 | H11: 0.5557965 | K11: Validation Rules Example
A12: 240119 HOVK Spoorlaan 446-448 Tilburg signed.pdf | B12: 8689.58 | C12: 8689.58 | H12: 0.43936972 | K12: Manual Data | L12: Response Data | M12: Result
A13: 27001 Rijksvastgoedbedrijf Huurovereenkomst - __27-01-2026_9-07-56.pdf | B13: 66497.36 | C13: 66497.36 | H13: 0.64656166 | K13: 100 | L13: 100 | M13: TP
A14: CBRE_AT_Services_ENG_-_RITUALS_CBRE signed.pdf | L14: 100 | M14: FP
A15: CBRE_Engagement_Letter_Alnylam_20260525_CLEAN_Version_signed all.pdf | K15: 100 | L15: 200 | M15: FP
A16: COMPL DEF Huurovereenkomst - Skybox - Pepperl+Fuchs - 20260204.pdf | B16: 5319.17 | C16: 5319.17 | H16: 0.58410861 | K16: 100 | M16: FN
A17: COMPL Huurovereenkomst - Stichting CCE - Kantoorgebouw Metzpoint I Dr. Holtroplaan - Fully Signed.pdf | B17: 3759.5 | C17: 3759.5 | H17: 0.95543571 | M17: TN
A18: COMPL Regel Partners - HOVK - Luchthavenweg 81 - 20260728.pdf | B18: 4125.46 | C18: 615.97 | E18: 10 | H18: 0.64548625
A19: COMPL_-_Onderhuurovereenkomst_Zelfstroom_B.V._-_50five_B.V._-_kantoorgebouw_Riva_-_05032026.pdf | B19: 17620.63 | C19: 17620.63 | H19: 0.93894487 | K19: Field: | L19: Terms / Effective_Rent_Monthly
A20: Den Bosch, Ruwekampweg 4, HOVK getekend.pdf | B20: 7216.67 | C20: 7216.67 | H20: 0.69976921
A21: FULLY SIGNED - COMPL Huurovereenkomst - Heijmans - Hugo de Grootlaan 23 's-Hertogenbosch V2 30-9-2025.pdf | B21: 5368.99 | C21: 5368.99 | H21: 0.44037715
A22: FULLY SIGNED - DEF_COMPL_Huurovereenkomst_Robo_Charge_-_Campus_Offices_-_20260220.pdf | B22: 4242.94 | C22: 3873.67 | E22: 9 | H22: 0.4625084
A23: FULLY SIGNED - Onderhuurovereenkomst Aartshertogenlaan 223, `s-Hertogenbosch - Koning Willem I College B.V. 2606202.pdf | B23: 8523.62 | C23: 9514.74 | E23: 8 | H23: 0.95308924
A24: FULLY SIGNED COMPL_DEF_Huurovereenkomst_Bond_Bergschot_Breda.pdf | B24: 14051.23 | C24: 14051.23 | H24: 0.39104116
A25: FullySigned_Allonge_II_Virtual_Vaults_Nederland.pdf | B25: 17720 | C25: 17672.22 | E25: 4 | H25: 0.69337634
A26: FullySigned_Lease_Agreement_Neste_EDGE_Coolsingel.pdf | B26: 32151.25 | C26: 28452.5 | E26: 15 | H26: 0.91467391
A27: HOK Waalhaven Group (signed).pdf | B27: 9458.29 | C27: 9168.75 | E27: 11 | H27: 0.4625084
A28: Hovk Avans (3e+4e+5e verd.) 20140425.pdf | B28: 3973.36 | C28: 3973.36 | H28: 0.58498909
A29: HOVK Power4People 2025.pdf | B29: 2020 | C29: 2020 | E29: 2-3 | H29: 0.43668223
A30: Huurovereenkomst (Semmie Group B.V.) - Wilhelminasingel 19, Breda.pdf | B30: 2235.4 | C30: 2455.79 | E30: 9 | H30: 0.439878
A31: Huurovereenkomst - proces-verbaal van oplevering - sleuteloverdracht - Kennedyplein 101 - getekend.pdf | B31: 5512.38 | C31: 6013.5 | E31: 10 | H31: 0.91038251
A32: Huurovereenkomst Bijster 5 te Breda getekend.pdf | B32: 5133.4 | C32: 5299.44 | E32: 10 | H32: 0.24268026
A33: Huurovereenkomst Catena Pand Son - Skymark (Son en Breugel - NLD).pdf | B33: 20154.17 | C33: 20154.17 | H33: 0.95308924
A34: Huurovereenkomst KPN Opstelpunt Parallelweg 64 20130313.pdf | B34: 356.25 | C34: 356.25 | H34: 0.95308924
A35: Huurovereenkomst PBG Parallelweg 64 (beg.grond) 20121008.pdf | B35: 7849.17 | C35: 7849.17 | H35: 0.6971223
A36: MWO CBRE SPA (ITALY) CBRE_090724.pdf

Sheet Field 25
A1: Doc Name | B1: Manual Data | C1: Response Data | D1: Result | E1: Manual Pg | F1: Response Pg No | G1: Pg Result | H1: Confidence | K1: SUMMARY SHEET | N1: PAGE SUMMARY SHEET
A2: 20181204 Huurovereenkomst (GETEKEND).PDF | B2: 7000 | C2: 7000 | H2: 0.95308924 | K2: Metrics | L2: Percentage | N2: Metrics | O2: Percentage
A3: 2024.10.30_Office Rental Agreement Labs_Gruyter Fabriek.pdf | B3: 104253 | C3: 106020 | E3: 9 | H3: 0.95308924 | K3: Precision | L3: =IFERROR(COUNTIFS(D2:D36,"TP")/(COUNTIFS(D2:D36,"TP")+COUNTIFS(D2:D36,"FP")),0) | N3: Precision | O3: =IFERROR(COUNTIFS(G2:G36,"TP")/(COUNTIFS(G2:G36,"TP")+COUNTIFS(G2:G36,"FP")),0)
A4: 20240606_HOK AKD - EDGE Eindhoven execution version.pdf | B4: 713590 | C4: 624427.3 | E4: 4, 8 | H4: 0.7219263 | K4: Recall | L4: =IFERROR(COUNTIFS(D2:D36,"TP")/(COUNTIFS(D2:D36,"TP")+COUNTIFS(D2:D36,"FN")),0) | N4: Recall | O4: =IFERROR(COUNTIFS(G2:G36,"TP")/(COUNTIFS(G2:G36,"TP")+COUNTIFS(G2:G36,"FN")),0)
A5: 20250117_HOK Duke Strategies - Hambaken A.05.09 DEF FULLY SIGNED.pdf | B5: 11788 | C5: 11788 | H5: 0.83432734 | K5: F1 Score | L5: =IFERROR(2*COUNTIFS(D2:D36,"TP")/(2*COUNTIFS(D2:D36,"TP")+COUNTIFS(D2:D36,"FP")+COUNTIFS(D2:D36,"FN")),0) | N5: F1 Score | O5: =IFERROR(2*COUNTIFS(G2:G36,"TP")/(2*COUNTIFS(G2:G36,"TP")+COUNTIFS(G2:G36,"FP")+COUNTIFS(G2:G36,"FN")),0)
A6: 20251216 Lease agreement ASPEN - signed.pdf | B6: 245000 | C6: 245000 | H6: 0.79780123 | K6: Accuracy % (With Not Exist) | L6: =IFERROR((COUNTIF(D2:D36,"TP")+COUNTIF(D2:D36,"TN"))/SUM(COUNTIF(D2:D36,{"TP","TN","FP","FN"})),0) | N6: Accuracy % (With Not Exist) | O6: =IFERROR((COUNTIF(G2:G36,"TP")+COUNTIF(G2:G36,"TN"))/SUM(COUNTIF(G2:G36,{"TP","TN","FP","FN"})),0)
A7: 20260220 Huurovereenkomst signed 20-02-2026.pdf | B7: 25951.66 | C7: 25951.66 | H7: 0.5361904 | K7: Total Docs Tested | L7: =COUNTA(A2:A36) | N7: Total Docs Tested | O7: =COUNTA(A2:A36)
A8: 20260629 HOK ADHDcentraal BV (1).pdf | B8: 49303.93 | C8: 41834.25 | E8: 3 | H8: 0.66878635 | K8: No Of Docs With Data | L8: =COUNTIFS(B2:B36,"<>",B2:B36,"<>N/A",B2:B36,"<>Not Present In the Document",B2:B36,"<>Not Found",B2:B36,"<>i dont know",B2:B36,"<>i don't know") | N8: No Of Docs With Manual Pg | O8: =COUNTIFS(E2:E36,"<>",E2:E36,"<>N/A",E2:E36,"<>Not Present In the Document",E2:E36,"<>Not Found",E2:E36,"<>i dont know",E2:E36,"<>i don't know")
A9: 20260807_Happy_Village_B.V._Lease_Maasstadweg_tekenversie_incl._bijlagen en-GB.pdf | B9: 265983.9 | C9: 254403.5 | E9: 10 | F9: 2 | H9: 0.59326643 | K9: No Of Docs With Response | L9: =COUNTIFS(C2:C36,"<>") | N9: No Of Docs With Response Pg | O9: =COUNTIFS(F2:F36,"<>")
A10: 20260810 HOK ClustR BV.pdf | B10: 34913.9 | C10: 29926.2 | E10: 2 | H10: 0.3922769 | K10: Highlighted rows = file(s) not in the annotation sheet; excluded from all metrics above.
A11: 20270801 - Getekende Allonge II Advario BV.pdf | B11: 263882.19 | C11: 244685.5 | E11: 5 | H11: 0.59326643 | K11: Validation Rules Example
A12: 240119 HOVK Spoorlaan 446-448 Tilburg signed.pdf | B12: 405000 | C12: 405000 | H12: 0.95308924 | K12: Manual Data | L12: Response Data | M12: Result
A13: 27001 Rijksvastgoedbedrijf Huurovereenkomst - __27-01-2026_9-07-56.pdf | B13: 797968.38 | C13: 797968.38 | H13: 0.95308924 | K13: 100 | L13: 100 | M13: TP
A14: CBRE_AT_Services_ENG_-_RITUALS_CBRE signed.pdf | L14: 100 | M14: FP
A15: CBRE_Engagement_Letter_Alnylam_20260525_CLEAN_Version_signed all.pdf | K15: 100 | L15: 200 | M15: FP
A16: COMPL DEF Huurovereenkomst - Skybox - Pepperl+Fuchs - 20260204.pdf | B16: 58780 | C16: 58780 | H16: 0.90604396 | K16: 100 | M16: FN
A17: COMPL Huurovereenkomst - Stichting CCE - Kantoorgebouw Metzpoint I Dr. Holtroplaan - Fully Signed.pdf | B17: 43220.6 | C17: 43220.6 | H17: 0.5832127 | M17: TN
A18: COMPL Regel Partners - HOVK - Luchthavenweg 81 - 20260728.pdf | B18: 49505.5 | C18: 48441.9 | E18: 10 | H18: 0.5361904
A19: COMPL_-_Onderhuurovereenkomst_Zelfstroom_B.V._-_50five_B.V._-_kantoorgebouw_Riva_-_05032026.pdf | B19: 17620.63 | C19: 17620.63 | H19: 0.8849162 | K19: Field: | L19: Terms / Effective_Rent_Yearly
A20: Den Bosch, Ruwekampweg 4, HOVK getekend.pdf | B20: 85000 | C20: 85000 | H20: 0.85162939
A21: FULLY SIGNED - COMPL Huurovereenkomst - Heijmans - Hugo de Grootlaan 23 's-Hertogenbosch V2 30-9-2025.pdf | B21: 64327.84 | C21: 64327.84 | H21: 0.89493346
A22: FULLY SIGNED - DEF_COMPL_Huurovereenkomst_Robo_Charge_-_Campus_Offices_-_20260220.pdf | B22: 50915.33 | C22: 51111.87 | E22: 9 | H22: 0.39187262
A23: FULLY SIGNED - Onderhuurovereenkomst Aartshertogenlaan 223, `s-Hertogenbosch - Koning Willem I College B.V. 2606202.pdf | B23: 102283.46 | C23: 99923.71 | E23: 8 | H23: 0.21204922
A24: FULLY SIGNED COMPL_DEF_Huurovereenkomst_Bond_Bergschot_Breda.pdf | B24: 164603.2 | C24: 164603.2 | H24: 0.484409
A25: FullySigned_Allonge_II_Virtual_Vaults_Nederland.pdf | B25: 212639.94 | C25: 192266.6 | E25: 4 | H25: 0.95308924
A26: FullySigned_Lease_Agreement_Neste_EDGE_Coolsingel.pdf | B26: 385815 | C26: 292035 | E26: 15 | H26: 0.64548625
A27: HOK Waalhaven Group (signed).pdf | B27: 113499.5 | C27: 109268.5 | E27: 11 | H27: 0.64656166
A28: Hovk Avans (3e+4e+5e verd.) 20140425.pdf | B28: 187930 | C28: 187930 | H28: 0.59326643
A29: HOVK Power4People 2025.pdf | B29: 24240 | C29: 24600 | E29: 2-3 | H29: 0.8
A30: Huurovereenkomst (Semmie Group B.V.) - Wilhelminasingel 19, Breda.pdf | B30: 26824.85 | C30: 267068.98 | E30: 9 | H30: 0.35468915
A31: Huurovereenkomst - proces-verbaal van oplevering - sleuteloverdracht - Kennedyplein 101 - getekend.pdf | B31: 66148.5 | C31: 72000 | E31: 10 | H31: 0.5557965
A32: Huurovereenkomst Bijster 5 te Breda getekend.pdf | B32: 61600.83 | C32: 58561.67 | E32: 10 | H32: 0.72465016
A33: Huurovereenkomst Catena Pand Son - Skymark (Son en Breugel - NLD).pdf | B33: 241850 | C33: 241850 | H33: 0.95308924
A34: Huurovereenkomst KPN Opstelpunt Parallelweg 64 20130313.pdf | B34: 4275 | C34: 4275 | H34: 0.95308924
A35: Huurovereenkomst PBG Parallelweg 64 (beg.grond) 20121008.pdf | B35: 82390.83 | C35: 82390.83 | H35: 0.66996472
A36: MWO CBRE SPA (ITALY) CBRE_090724.pdf

Sheet Field 26
A1: Doc Name | B1: Manual Data | C1: Response Data | D1: Result | E1: Manual Pg | F1: Response Pg No | G1: Pg Result | H1: Confidence | K1: SUMMARY SHEET | N1: PAGE SUMMARY SHEET
A2: 20181204 Huurovereenkomst (GETEKEND).PDF | B2: 180 months | C2: 180 months | H2: 0.97058824 | K2: Metrics | L2: Percentage | N2: Metrics | O2: Percentage
A3: 2024.10.30_Office Rental Agreement Labs_Gruyter Fabriek.pdf | B3: 60 months | C3: 60 months | H3: 0.97058824 | K3: Precision | L3: =IFERROR(COUNTIFS(D2:D36,"TP")/(COUNTIFS(D2:D36,"TP")+COUNTIFS(D2:D36,"FP")),0) | N3: Precision | O3: =IFERROR(COUNTIFS(G2:G36,"TP")/(COUNTIFS(G2:G36,"TP")+COUNTIFS(G2:G36,"FP")),0)
A4: 20240606_HOK AKD - EDGE Eindhoven execution version.pdf | B4: 120 months | C4: 120 months | H4: 0.94736842 | K4: Recall | L4: =IFERROR(COUNTIFS(D2:D36,"TP")/(COUNTIFS(D2:D36,"TP")+COUNTIFS(D2:D36,"FN")),0) | N4: Recall | O4: =IFERROR(COUNTIFS(G2:G36,"TP")/(COUNTIFS(G2:G36,"TP")+COUNTIFS(G2:G36,"FN")),0)
A5: 20250117_HOK Duke Strategies - Hambaken A.05.09 DEF FULLY SIGNED.pdf | B5: 12 months | C5: 12 months | H5: 0.96816685 | K5: F1 Score | L5: =IFERROR(2*COUNTIFS(D2:D36,"TP")/(2*COUNTIFS(D2:D36,"TP")+COUNTIFS(D2:D36,"FP")+COUNTIFS(D2:D36,"FN")),0) | N5: F1 Score | O5: =IFERROR(2*COUNTIFS(G2:G36,"TP")/(2*COUNTIFS(G2:G36,"TP")+COUNTIFS(G2:G36,"FP")+COUNTIFS(G2:G36,"FN")),0)
A6: 20251216 Lease agreement ASPEN - signed.pdf | B6: 154 months | C6: 154 months | H6: 0.94736842 | K6: Accuracy % (With Not Exist) | L6: =IFERROR((COUNTIF(D2:D36,"TP")+COUNTIF(D2:D36,"TN"))/SUM(COUNTIF(D2:D36,{"TP","TN","FP","FN"})),0) | N6: Accuracy % (With Not Exist) | O6: =IFERROR((COUNTIF(G2:G36,"TP")+COUNTIF(G2:G36,"TN"))/SUM(COUNTIF(G2:G36,{"TP","TN","FP","FN"})),0)
A7: 20260220 Huurovereenkomst signed 20-02-2026.pdf | B7: 36 months | C7: 36 months | H7: 0.97058824 | K7: Total Docs Tested | L7: =COUNTA(A2:A36) | N7: Total Docs Tested | O7: =COUNTA(A2:A36)
A8: 20260629 HOK ADHDcentraal BV (1).pdf | B8: 24 months | C8: 24 months | H8: 0.97058824 | K8: No Of Docs With Data | L8: =COUNTIFS(B2:B36,"<>",B2:B36,"<>N/A",B2:B36,"<>Not Present In the Document",B2:B36,"<>Not Found",B2:B36,"<>i dont know",B2:B36,"<>i don't know") | N8: No Of Docs With Manual Pg | O8: =COUNTIFS(E2:E36,"<>",E2:E36,"<>N/A",E2:E36,"<>Not Present In the Document",E2:E36,"<>Not Found",E2:E36,"<>i dont know",E2:E36,"<>i don't know")
A9: 20260807_Happy_Village_B.V._Lease_Maasstadweg_tekenversie_incl._bijlagen en-GB.pdf | B9: 120 months | C9: 120 months | H9: 0.97058824 | K9: No Of Docs With Response | L9: =COUNTIFS(C2:C36,"<>") | N9: No Of Docs With Response Pg | O9: =COUNTIFS(F2:F36,"<>")
A10: 20260810 HOK ClustR BV.pdf | B10: 24 months | C10: 24 months | H10: 0.97058824 | K10: Highlighted rows = file(s) not in the annotation sheet; excluded from all metrics above.
A11: 20270801 - Getekende Allonge II Advario BV.pdf | B11: 60 months | C11: 60 months | E11: 3 | H11: 0.97058824 | K11: Validation Rules Example
A12: 240119 HOVK Spoorlaan 446-448 Tilburg signed.pdf | B12: 36 months | C12: 36 months | H12: 0.97058824 | K12: Manual Data | L12: Response Data | M12: Result
A13: 27001 Rijksvastgoedbedrijf Huurovereenkomst - __27-01-2026_9-07-56.pdf | B13: 88 months | C13: 88 months | H13: 0.97058824 | K13: 100 | L13: 100 | M13: TP
A14: CBRE_AT_Services_ENG_-_RITUALS_CBRE signed.pdf | B14: 6 months | C14: 6 months | H14: 0.97058824 | L14: 100 | M14: FP
A15: CBRE_Engagement_Letter_Alnylam_20260525_CLEAN_Version_signed all.pdf | B15: 12 months | C15: 12 months | H15: 0.89722222 | K15: 100 | L15: 200 | M15: FP
A16: COMPL DEF Huurovereenkomst - Skybox - Pepperl+Fuchs - 20260204.pdf | B16: 60 months | C16: 60 months | H16: 0.97058824 | K16: 100 | M16: FN
A17: COMPL Huurovereenkomst - Stichting CCE - Kantoorgebouw Metzpoint I Dr. Holtroplaan - Fully Signed.pdf | B17: 120 months | C17: 120 months | H17: 0.97058824 | M17: TN
A18: COMPL Regel Partners - HOVK - Luchthavenweg 81 - 20260728.pdf | B18: 60 months | C18: 60 months | H18: 0.95543571
A19: COMPL_-_Onderhuurovereenkomst_Zelfstroom_B.V._-_50five_B.V._-_kantoorgebouw_Riva_-_05032026.pdf | B19: 2 months | C19: 2 months | H19: 0.95543571 | K19: Field: | L19: Terms / Lease_Term
A20: Den Bosch, Ruwekampweg 4, HOVK getekend.pdf | B20: 120 months | C20: 120 months | H20: 0.97058824
A21: FULLY SIGNED - COMPL Huurovereenkomst - Heijmans - Hugo de Grootlaan 23 's-Hertogenbosch V2 30-9-2025.pdf | B21: 12 months | C21: 12 months | H21: 0.94736842
A22: FULLY SIGNED - DEF_COMPL_Huurovereenkomst_Robo_Charge_-_Campus_Offices_-_20260220.pdf | B22: 60 months | C22: 60 months | H22: 0.95543571
A23: FULLY SIGNED - Onderhuurovereenkomst Aartshertogenlaan 223, `s-Hertogenbosch - Koning Willem I College B.V. 2606202.pdf | B23: 48 months | C23: 48 months | H23: 0.94736842
A24: FULLY SIGNED COMPL_DEF_Huurovereenkomst_Bond_Bergschot_Breda.pdf | B24: 42 months | C24: 42 months | H24: 0.97058824
A25: FullySigned_Allonge_II_Virtual_Vaults_Nederland.pdf | B25: 108 months | C25: 108 months | H25: 0.94828588
A26: FullySigned_Lease_Agreement_Neste_EDGE_Coolsingel.pdf | B26: 60 months | C26: 60 months | H26: 0.97058824
A27: HOK Waalhaven Group (signed).pdf | B27: 60 months | C27: 60 months | H27: 0.97058824
A28: Hovk Avans (3e+4e+5e verd.) 20140425.pdf | B28: 62 months | C28: 62 months | H28: 0.97058824
A29: HOVK Power4People 2025.pdf | B29: 12 months | C29: 12 months | H29: 0.96816685
A30: Huurovereenkomst (Semmie Group B.V.) - Wilhelminasingel 19, Breda.pdf | B30: 39 months | C30: 39 months | H30: 0.85185736
A31: Huurovereenkomst - proces-verbaal van oplevering - sleuteloverdracht - Kennedyplein 101 - getekend.pdf | B31: 36 months | C31: 36 months | H31: 0.96816685
... A35: Huurovereenkomst PBG Parallelweg 64 (beg.grond) 20121008.pdf | B35: 60 months | C35: 60 months | H35: 0.94736842
A36: MWO CBRE SPA (ITALY) CBRE_090724.pdf

Sheet Field 27
A1: Doc Name | B1: Manual Data | C1: Response Data | D1: Result | E1: Manual Pg | F1: Response Pg No | G1: Pg Result | H1: Confidence | K1: SUMMARY SHEET | N1: PAGE SUMMARY SHEET
A2: 20181204 Huurovereenkomst (GETEKEND).PDF | B2: 0 | C2: 0 | H2: 0.95543571 | K2: Metrics | L2: Percentage | N2: Metrics | O2: Percentage
A3: 2024.10.30_Office Rental Agreement Labs_Gruyter Fabriek.pdf | B3: 1 | C3: 1 | H3: 0.95308924 | K3: Precision | L3: =IFERROR(COUNTIFS(D2:D36,"TP")/(COUNTIFS(D2:D36,"TP")+COUNTIFS(D2:D36,"FP")),0) | N3: Precision | O3: =IFERROR(COUNTIFS(G2:G36,"TP")/(COUNTIFS(G2:G36,"TP")+COUNTIFS(G2:G36,"FP")),0)
A4: 20240606_HOK AKD - EDGE Eindhoven execution version.pdf | B4: 0 | C4: 0 | H4: 0.95070626 | K4: Recall | L4: =IFERROR(COUNTIFS(D2:D36,"TP")/(COUNTIFS(D2:D36,"TP")+COUNTIFS(D2:D36,"FN")),0) | N4: Recall | O4: =IFERROR(COUNTIFS(G2:G36,"TP")/(COUNTIFS(G2:G36,"TP")+COUNTIFS(G2:G36,"FN")),0)
A5: 20250117_HOK Duke Strategies - Hambaken A.05.09 DEF FULLY SIGNED.pdf | B5: 0 | C5: 0 | H5: 0.95543571 | K5: F1 Score | L5: =IFERROR(2*COUNTIFS(D2:D36,"TP")/(2*COUNTIFS(D2:D36,"TP")+COUNTIFS(D2:D36,"FP")+COUNTIFS(D2:D36,"FN")),0) | N5: F1 Score | O5: =IFERROR(2*COUNTIFS(G2:G36,"TP")/(2*COUNTIFS(G2:G36,"TP")+COUNTIFS(G2:G36,"FP")+COUNTIFS(G2:G36,"FN")),0)
A6: 20251216 Lease agreement ASPEN - signed.pdf | B6: 0 | C6: 0 | H6: 0.91891892 | K6: Accuracy % (With Not Exist) | L6: =IFERROR((COUNTIF(D2:D36,"TP")+COUNTIF(D2:D36,"TN"))/SUM(COUNTIF(D2:D36,{"TP","TN","FP","FN"})),0) | N6: Accuracy % (With Not Exist) | O6: =IFERROR((COUNTIF(G2:G36,"TP")+COUNTIF(G2:G36,"TN"))/SUM(COUNTIF(G2:G36,{"TP","TN","FP","FN"})),0)
A7: 20260220 Huurovereenkomst signed 20-02-2026.pdf | B7: 1 | C7: 1 | H7: 0.95543571 | K7: Total Docs Tested | L7: =COUNTA(A2:A36) | N7: Total Docs Tested | O7: =COUNTA(A2:A36)
A8: 20260629 HOK ADHDcentraal BV (1).pdf | B8: 3 | C8: 3 | H8: 0.95543571 | K8: No Of Docs With Data | L8: =COUNTIFS(B2:B36,"<>",B2:B36,"<>N/A",B2:B36,"<>Not Present In the Document",B2:B36,"<>Not Found",B2:B36,"<>i dont know",B2:B36,"<>i don't know") | N8: No Of Docs With Manual Pg | O8: =COUNTIFS(E2:E36,"<>",E2:E36,"<>N/A",E2:E36,"<>Not Present In the Document",E2:E36,"<>Not Found",E2:E36,"<>i dont know",E2:E36,"<>i don't know")
A9: 20260807_Happy_Village_B.V._Lease_Maasstadweg_tekenversie_incl._bijlagen en-GB.pdf | B9: 3 | C9: 3 | H9: 0.95543571 | K9: No Of Docs With Response | L9: =COUNTIFS(C2:C36,"<>") | N9: No Of Docs With Response Pg | O9: =COUNTIFS(F2:F36,"<>")
A10: 20260810 HOK ClustR BV.pdf | B10: 3 | C10: 3 | H10: 0.91891892 | K10: Highlighted rows = file(s) not in the annotation sheet; excluded from all metrics above.
A11: 20270801 - Getekende Allonge II Advario BV.pdf | B11: 6 | C11: 6 | E11: 5 | H11: 0.95543571 | K11: Validation Rules Example
A12: 240119 HOVK Spoorlaan 446-448 Tilburg signed.pdf | B12: 0 | C12: 0 | H12: 0.95543571 | K12: Manual Data | L12: Response Data | M12: Result
A13: 27001 Rijksvastgoedbedrijf Huurovereenkomst - __27-01-2026_9-07-56.pdf | B13: 0 | C13: 0 | H13: 0.95543571 | K13: 100 | L13: 100 | M13: TP
A14: CBRE_AT_Services_ENG_-_RITUALS_CBRE signed.pdf | B14: 0 | C14: 0 | H14: 0.94582723 | L14: 100 | M14: FP
A15: CBRE_Engagement_Letter_Alnylam_20260525_CLEAN_Version_signed all.pdf | B15: 0 | C15: 0 | H15: 0.95308924 | K15: 100 | L15: 200 | M15: FP
A16: COMPL DEF Huurovereenkomst - Skybox - Pepperl+Fuchs - 20260204.pdf | B16: 0 | C16: 0 | H16: 0.95543571 | K16: 100 | M16: FN
A17: COMPL Huurovereenkomst - Stichting CCE - Kantoorgebouw Metzpoint I Dr. Holtroplaan - Fully Signed.pdf | B17: 2 | C17: 2 | H17: 0.95543571 | M17: TN
A18: COMPL Regel Partners - HOVK - Luchthavenweg 81 - 20260728.pdf | B18: 0 | C18: 0 | H18: 0.95543571
A19: COMPL_-_Onderhuurovereenkomst_Zelfstroom_B.V._-_50five_B.V._-_kantoorgebouw_Riva_-_05032026.pdf | B19: 2 | C19: 2 | H19: 0.91891892 | K19: Field: | L19: Terms / Number_Of_Month_Free_Rent
A20: Den Bosch, Ruwekampweg 4, HOVK getekend.pdf | B20: 0 | C20: 0 | H20: 0.91891892
A21: FULLY SIGNED - COMPL Huurovereenkomst - Heijmans - Hugo de Grootlaan 23 's-Hertogenbosch V2 30-9-2025.pdf | B21: 1 | C21: 1 | H21: 0.95543571
A22: FULLY SIGNED - DEF_COMPL_Huurovereenkomst_Robo_Charge_-_Campus_Offices_-_20260220.pdf | B22: 5 | C22: 5 | H22: 0.95543571
A23: FULLY SIGNED - Onderhuurovereenkomst Aartshertogenlaan 223, `s-Hertogenbosch - Koning Willem I College B.V. 2606202.pdf | B23: 5 | C23: 5 | H23: 0.95543571
A24: FULLY SIGNED COMPL_DEF_Huurovereenkomst_Bond_Bergschot_Breda.pdf | B24: 4 | C24: 4 | H24: 0.95543571
A25: FullySigned_Allonge_II_Virtual_Vaults_Nederland.pdf | B25: 6 | C25: 6 | H25: 0.95543571
A26: FullySigned_Lease_Agreement_Neste_EDGE_Coolsingel.pdf | B26: 9 | C26: 9 | H26: 0.95543571
A27: HOK Waalhaven Group (signed).pdf | B27: 7 | C27: 7 | H27: 0.95543571
A28: Hovk Avans (3e+4e+5e verd.) 20140425.pdf | B28: 0 | C28: 0 | H28: 0.95543571
A29: HOVK Power4People 2025.pdf | B29: 0 | C29: 0 | H29: 0.95543571
A30: Huurovereenkomst (Semmie Group B.V.) - Wilhelminasingel 19, Breda.pdf | B30: 3.5 | C30: 3.5 | H30: 0.95543571
A31: Huurovereenkomst - proces-verbaal van oplevering - sleuteloverdracht - Kennedyplein 101 - getekend.pdf | B31: 3 | C31: 3 | H31: 0.95543571
... A36: MWO CBRE SPA (ITALY) CBRE_090724.pdf | B36: 0 | C36: 0 | H36: 0.95543571

Sheet Field 28
A1: Doc Name | B1: Manual Data | C1: Response Data | D1: Result | E1: Manual Pg | F1: Response Pg No | G1: Pg Result | H1: Confidence | K1: SUMMARY SHEET | N1: PAGE SUMMARY SHEET
A2: 20181204 Huurovereenkomst (GETEKEND).PDF | B2: 1 januari 2019 | C2: 1 januari 2019 | H2: 0.94582723 | K2: Metrics | L2: Percentage | N2: Metrics | O2: Percentage
A3: 2024.10.30_Office Rental Agreement Labs_Gruyter Fabriek.pdf | B3: 01/01/2025 | C3: 01/01/2025 | H3: 0.96570796 | K3: Precision | L3: =IFERROR(COUNTIFS(D2:D36,"TP")/(COUNTIFS(D2:D36,"TP")+COUNTIFS(D2:D36,"FP")),0) | N3: Precision | O3: =IFERROR(COUNTIFS(G2:G36,"TP")/(COUNTIFS(G2:G36,"TP")+COUNTIFS(G2:G36,"FP")),0)
A4: 20240606_HOK AKD - EDGE Eindhoven execution version.pdf | B4: 01/07/2026 | C4: 01/07/2026 | H4: 0.92432432 | K4: Recall | L4: =IFERROR(COUNTIFS(D2:D36,"TP")/(COUNTIFS(D2:D36,"TP")+COUNTIFS(D2:D36,"FN")),0) | N4: Recall | O4: =IFERROR(COUNTIFS(G2:G36,"TP")/(COUNTIFS(G2:G36,"TP")+COUNTIFS(G2:G36,"FN")),0)
A5: 20250117_HOK Duke Strategies - Hambaken A.05.09 DEF FULLY SIGNED.pdf | B5: 17/02/2025 | C5: 17/02/2025 | H5: 0.84705882 | K5: F1 Score | L5: =IFERROR(2*COUNTIFS(D2:D36,"TP")/(2*COUNTIFS(D2:D36,"TP")+COUNTIFS(D2:D36,"FP")+COUNTIFS(D2:D36,"FN")),0) | N5: F1 Score | O5: =IFERROR(2*COUNTIFS(G2:G36,"TP")/(2*COUNTIFS(G2:G36,"TP")+COUNTIFS(G2:G36,"FP")+COUNTIFS(G2:G36,"FN")),0)
A6: 20251216 Lease agreement ASPEN - signed.pdf | B6: 01/05/2025 | C6: 01/05/2025 | H6: 0.7875 | K6: Accuracy % (With Not Exist) | L6: =IFERROR((COUNTIF(D2:D36,"TP")+COUNTIF(D2:D36,"TN"))/SUM(COUNTIF(D2:D36,{"TP","TN","FP","FN"})),0) | N6: Accuracy % (With Not Exist) | O6: =IFERROR((COUNTIF(G2:G36,"TP")+COUNTIF(G2:G36,"TN"))/SUM(COUNTIF(G2:G36,{"TP","TN","FP","FN"})),0)
A7: 20260220 Huurovereenkomst signed 20-02-2026.pdf | B7: 25/02/2026 | C7: 25/02/2026 | H7: 0.94736842 | K7: Total Docs Tested | L7: =COUNTA(A2:A36) | N7: Total Docs Tested | O7: =COUNTA(A2:A36)
A8: 20260629 HOK ADHDcentraal BV (1).pdf | B8: 01/09/2026 | C8: 01/09/2026 | H8: 0.92432432 | K8: No Of Docs With Data | L8: =COUNTIFS(B2:B36,"<>",B2:B36,"<>N/A",B2:B36,"<>Not Present In the Document",B2:B36,"<>Not Found",B2:B36,"<>i dont know",B2:B36,"<>i don't know") | N8: No Of Docs With Manual Pg | O8: =COUNTIFS(E2:E36,"<>",E2:E36,"<>N/A",E2:E36,"<>Not Present In the Document",E2:E36,"<>Not Found",E2:E36,"<>i dont know",E2:E36,"<>i don't know")
A9: 20260807_Happy_Village_B.V._Lease_Maasstadweg_tekenversie_incl._bijlagen en-GB.pdf | B9: 1 January 2027 | C9: 1 January 2027 | H9: 0.87428571 | K9: No Of Docs With Response | L9: =COUNTIFS(C2:C36,"<>") | N9: No Of Docs With Response Pg | O9: =COUNTIFS(F2:F36,"<>")
A10: 20260810 HOK ClustR BV.pdf | B10: 01/10/2026 | C10: 01/10/2026 | H10: 0.96816685 | K10: Highlighted rows = file(s) not in the annotation sheet; excluded from all metrics above.
A11: 20270801 - Getekende Allonge II Advario BV.pdf | B11: 01/08/2022 | C11: 01/08/2022 | H11: 0.45298013 | K11: Validation Rules Example
A12: 240119 HOVK Spoorlaan 446-448 Tilburg signed.pdf | B12: 1 april 2024 | C12: 1 april 2024 | H12: 0.5608903 | K12: Manual Data | L12: Response Data | M12: Result
A13: 27001 Rijksvastgoedbedrijf Huurovereenkomst - __27-01-2026_9-07-56.pdf | B13: 01/09/2019 | C13: 01/09/2019 | H13: 0.56006415 | K13: 100 | L13: 100 | M13: TP
A14: CBRE_AT_Services_ENG_-_RITUALS_CBRE signed.pdf | L14: 100 | M14: FP
A15: CBRE_Engagement_Letter_Alnylam_20260525_CLEAN_Version_signed all.pdf | K15: 100 | L15: 200 | M15: FP
A16: COMPL DEF Huurovereenkomst - Skybox - Pepperl+Fuchs - 20260204.pdf | B16: 01/12/2026 | C16: 01/12/2026 | H16: 0.5557047 | K16: 100 | M16: FN
A17: COMPL Huurovereenkomst - Stichting CCE - Kantoorgebouw Metzpoint I Dr. Holtroplaan - Fully Signed.pdf | B17: 01/03/2025 | C17: 01/03/2025 | H17: 0.55836735 | M17: TN
A18: COMPL Regel Partners - HOVK - Luchthavenweg 81 - 20260728.pdf | B18: 01/10/2026 | C18: 01/10/2026 | H18: 0.96816685
A19: COMPL_-_Onderhuurovereenkomst_Zelfstroom_B.V._-_50five_B.V._-_kantoorgebouw_Riva_-_05032026.pdf | B19: 01/04/2026 | C19: 01/04/2026 | H19: 0.97058824 | K19: Field: | L19: Terms / Occupancy_Date
A20: Den Bosch, Ruwekampweg 4, HOVK getekend.pdf | B20: 1 januari 2017 | C20: 1 januari 2017 | H20: 0.55836735
A21: FULLY SIGNED - COMPL Huurovereenkomst - Heijmans - Hugo de Grootlaan 23 's-Hertogenbosch V2 30-9-2025.pdf | B21: 15/10/2025 | C21: 15/10/2025 | H21: 0.56170213
A22: FULLY SIGNED - DEF_COMPL_Huurovereenkomst_Robo_Charge_-_Campus_Offices_-_20260220.pdf | B22: 01/04/2026 | C22: 01/04/2026 | H22: 0.95543571
A23: FULLY SIGNED - Onderhuurovereenkomst Aartshertogenlaan 223, `s-Hertogenbosch - Koning Willem I College B.V. 2606202.pdf | B23: 01/08/2025 | C23: 01/08/2025 | H23: 0.56170213
A24: FULLY SIGNED COMPL_DEF_Huurovereenkomst_Bond_Bergschot_Breda.pdf | B24: 01/06/2025 | C24: 01/06/2025 | H24: 0.96067416
A25: FullySigned_Allonge_II_Virtual_Vaults_Nederland.pdf | B25: 01/11/2018 | C25: 01/11/2018 | H25: 0.96816685
A26: FullySigned_Lease_Agreement_Neste_EDGE_Coolsingel.pdf | B26: 01/08/2027 | C26: 01/08/2027 | H26: 0.5608903
A27: HOK Waalhaven Group (signed).pdf | B27: 01/09/2026 | C27: 01/09/2026 | H27: 0.96816685
A28: Hovk Avans (3e+4e+5e verd.) 20140425.pdf | B28: 1 mei 2014 | C28: 1 mei 2014 | H28: 0.67738009
A29: HOVK Power4People 2025.pdf | B29: 01/07/2025 | C29: 01/07/2025 | H29: 0.96067416
A30: Huurovereenkomst (Semmie Group B.V.) - Wilhelminasingel 19, Breda.pdf | B30: 15/01/2026 | C30: 15/01/2026 | H30: 0.96570796
A31: Huurovereenkomst - proces-verbaal van oplevering - sleuteloverdracht - Kennedyplein 101 - getekend.pdf | B31: 02/03/2026 | C31: 02/03/2026 | H31: 0.92093023
... A35: Huurovereenkomst PBG Parallelweg 64 (beg.grond) 20121008.pdf | B35: 1 oktober 2012 | C35: 1 oktober 2012 | H35: 0.5608903
A36: MWO CBRE SPA (ITALY) CBRE_090724.pdf

Sheet Field 29
A1: Doc Name | B1: Manual Data | C1: Response Data | D1: Result | E1: Manual Pg | F1: Response Pg No | G1: Pg Result | H1: Confidence | K1: SUMMARY SHEET | N1: PAGE SUMMARY SHEET
A2: 20181204 Huurovereenkomst (GETEKEND).PDF | B2: De huurovereenkomst wordt na de initiëlelooptijd van 15 jaar stilzwijgend verlengd met periodes van telkens 5 jaar onder dezelfde voorwaarden. | C2: De huurovereenkomst wordt na de initiëlelooptijd van 15 jaar stilzwijgend verlengd met periodes van telkens 5 jaar onder dezelfde voorwaarden. | H2: 0.91038251 | K2: Metrics | L2: Percentage | N2: Metrics | O2: Percentage
A3: 2024.10.30_Office Rental Agreement Labs_Gruyter Fabriek.pdf | B3: Na afloop van de eerste huurperiode wordt de huurovereenkomst telkens voortgezet voor een aansluitende periode van 60 maanden. Opzegging met 12 maanden schriftelijke termijn. | C3: Na afloop van de eerste huurperiode wordt de huurovereenkomst telkens voortgezet voor een aansluitende periode van 60 maanden. Opzegging met 12 maanden schriftelijke termijn. | H3: 0.544 | K3: Precision | L3: =IFERROR(COUNTIFS(D2:D36,"TP")/(COUNTIFS(D2:D36,"TP")+COUNTIFS(D2:D36,"FP")),0) | N3: Precision | O3: =IFERROR(COUNTIFS(G2:G36,"TP")/(COUNTIFS(G2:G36,"TP")+COUNTIFS(G2:G36,"FP")),0)
A4: 20240606_HOK AKD - EDGE Eindhoven execution version.pdf | B4: Huurder heeft gedurende eerste huurtermijn optie tot uitbreiding met 8e verdieping; aanbiedingsplicht met recht van eerste weigering bij externe interesse. Huurder kan na oplevering bij leegstand eenmalig optie uitoefenen op zelfde ruimte (min. 3 jaar huur), beide opties tegen markthuurprijs. | C4: Huurder heeft gedurende eerste huurtermijn optie tot uitbreiding met 8e verdieping; aanbiedingsplicht met recht van eerste weigering bij externe interesse. Huurder kan na oplevering bij leegstand eenmalig optie uitoefenen op zelfde ruimte (min. 3 jaar huur), beide opties tegen markthuurprijs. | H4: 0.56620169 | K4: Recall | L4: =IFERROR(COUNTIFS(D2:D36,"TP")/(COUNTIFS(D2:D36,"TP")+COUNTIFS(D2:D36,"FN")),0) | N4: Recall | O4: =IFERROR(COUNTIFS(G2:G36,"TP")/(COUNTIFS(G2:G36,"TP")+COUNTIFS(G2:G36,"FN")),0)
A5: 20250117_HOK Duke Strategies - Hambaken A.05.09 DEF FULLY SIGNED.pdf | B5: Verhuurder mag huurder (tijdelijk) verplaatsen naar een andere ruimte binnen het gebouw zonder prijsconsequenties, mits vergelijkbare of grotere ruimte. | C5: Verhuurder mag huurder (tijdelijk) verplaatsen naar een andere ruimte binnen het gebouw zonder prijsconsequenties, mits vergelijkbare of grotere ruimte. | H5: 0.88820225 | K5: F1 Score | L5: =IFERROR(2*COUNTIFS(D2:D36,"TP")/(2*COUNTIFS(D2:D36,"TP")+COUNTIFS(D2:D36,"FP")+COUNTIFS(D2:D36,"FN")),0) | N5: F1 Score | O5: =IFERROR(2*COUNTIFS(G2:G36,"TP")/(2*COUNTIFS(G2:G36,"TP")+COUNTIFS(G2:G36,"FP")+COUNTIFS(G2:G36,"FN")),0)
A6: 20251216 Lease agreement ASPEN - signed.pdf | B6: After initial period of 12 years 10 months, lease renews for 5-year periods unless terminated with 18 months' notice before period end. Tenant also has rolling break option for first floor after 5 years. | C6: After initial period of 12 years 10 months, lease renews for 5-year periods unless terminated with 18 months' notice before period end. Tenant also has rolling break option for first floor after 5 years. | H6: 0.64548625 | K6: Accuracy % (With Not Exist) | L6: =IFERROR((COUNTIF(D2:D36,"TP")+COUNTIF(D2:D36,"TN"))/SUM(COUNTIF(D2:D36,{"TP","TN","FP","FN"})),0) | N6: Accuracy % (With Not Exist) | O6: =IFERROR((COUNTIF(G2:G36,"TP")+COUNTIF(G2:G36,"TN"))/SUM(COUNTIF(G2:G36,{"TP","TN","FP","FN"})),0)
A7: 20260220 Huurovereenkomst signed 20-02-2026.pdf | B7: Lease auto-extends for 1-year periods after initial 3-year term unless terminated; Tenant has a one-time break option after 2 years with 6-month notice and penalty of 2 months rent. | C7: Lease auto-extends for 1-year periods after initial 3-year term unless terminated; Tenant has a one-time break option after 2 years with 6-month notice and penalty of 2 months rent. | H7: 0.71598499 | K7: Total Docs Tested | L7: =COUNTA(A2:A36) | N7: Total Docs Tested | O7: =COUNTA(A2:A36)
A8: 20260629 HOK ADHDcentraal BV (1).pdf | B8: No explicit renewal, extension, expansion, or option rights for the tenant found in the provided context. | C8: No explicit renewal, extension, expansion, or option rights for the tenant found in the provided context. | H8: 0.85 | K8: No Of Docs With Data | L8: =COUNTIFS(B2:B36,"<>",B2:B36,"<>N/A",B2:B36,"<>Not Present In the Document",B2:B36,"<>Not Found",B2:B36,"<>i dont know",B2:B36,"<>i don't know") | N8: No Of Docs With Manual Pg | O8: =COUNTIFS(E2:E36,"<>",E2:E36,"<>N/A",E2:E36,"<>Not Present In the Document",E2:E36,"<>Not Found",E2:E36,"<>i dont know",E2:E36,"<>i don't know")
A9: 20260807_Happy_Village_B.V._Lease_Maasstadweg_tekenversie_incl._bijlagen en-GB.pdf | B9: Lease auto-renews for 5-year periods unless tenant or landlord gives at least 12 months' notice before end of term. Tenant may break early as of 1 Jan 2034 with 12 months' notice and a fee. | C9: Lease auto-renews for 5-year periods unless tenant or landlord gives at least 12 months' notice before end of term. Tenant may break early as of 1 Jan 2034 with 12 months' notice and a fee. | F9: 2 | H9: 0.65263852 | K9: No Of Docs With Response | L9: =COUNTIFS(C2:C36,"<>") | N9: No Of Docs With Response Pg | O9: =COUNTIFS(F2:F36,"<>")
A10: 20260810 HOK ClustR BV.pdf | K10: Highlighted rows = file(s) not in the annotation sheet; excluded from all metrics above.
A11: 20270801 - Getekende Allonge II Advario BV.pdf | B11: Lease extends 5 years to 31-07-2032, then auto-extends another 5 years unless terminated with 12 months' notice; tenant has break/expansion/first right on adjacent space. | C11: Lease extends 5 years to 31-07-2032, then auto-extends another 5 years unless terminated with 12 months' notice; tenant has break/expansion/first right on adjacent space. | H11: 0.65486381 | K11: Validation Rules Example
A12: 240119 HOVK Spoorlaan 446-448 Tilburg signed.pdf | B12: Na 3 jaar verlengt de huurovereenkomst voor onbepaalde tijd. Huurder kan tot 31-12-2024 kiezen voor een 10-jaarstermijn met aangepaste voorwaarden en huurprijs, dan geldt opzegging met 12 maanden. | C12: Na 3 jaar verlengt de huurovereenkomst voor onbepaalde tijd. Huurder kan tot 31-12-2024 kiezen voor een 10-jaarstermijn met aangepaste voorwaarden en huurprijs, dan geldt opzegging met 12 maanden. | H12: 0.54606883 | K12: Manual Data | L12: Response Data | M12: Result
A13: 27001 Rijksvastgoedbedrijf Huurovereenkomst - __27-01-2026_9-07-56.pdf | B13: Huurder mag de uit deze huurovereenkomst voortvloeiende rechtsverhouding geheel of gedeeltelijk aan een derde overdragen en/of onderverhuren, met toestemming verhuurder niet op onredelijke gronden te onthouden. | C13: Huurder mag de uit deze huurovereenkomst voortvloeiende rechtsverhouding geheel of gedeeltelijk aan een derde overdragen en/of onderverhuren, met toestemming verhuurder niet op onredelijke gronden te onthouden. | H13: 0.5557965 | K13: 100 | L13: 100 | M13: TP
A14: CBRE_AT_Services_ENG_-_RITUALS_CBRE signed.pdf | B14: Agreement renews automatically for 3 months unless Rituals terminates by certified mail (PEC) 1 month prior to contract end. | C14: Agreement renews automatically for 3 months unless Rituals terminates by certified mail (PEC) 1 month prior to contract end. | H14: 0.54606883 | L14: 100 | M14: FP
A15: CBRE_Engagement_Letter_Alnylam_20260525_CLEAN_Version_signed all.pdf | K15: 100 | L15: 200 | M15: FP
A16: COMPL DEF Huurovereenkomst - Skybox - Pepperl+Fuchs - 20260204.pdf | B16: After the initial 5-year term, the lease is automatically extended for periods of 3 years each, unless terminated with 12 months' notice. | C16: After the initial 5-year term, the lease is automatically extended for periods of 3 years each, unless terminated with 12 months' notice. | H16: 0.67112332 | K16: 100 | M16: FN
A17: COMPL Huurovereenkomst - Stichting CCE - Kantoorgebouw Metzpoint I Dr. Holtroplaan - Fully Signed.pdf | B17: Na het verstrijken van de 10 jaar looptijd wordt de huurovereenkomst telkens automatisch verlengd met periodes van 5 jaar, tenzij partijen met 12 maanden opzegtermijn opzeggen. | C17: Na het verstrijken van de 10 jaar looptijd wordt de huurovereenkomst telkens automatisch verlengd met periodes van 5 jaar, tenzij partijen met 12 maanden opzegtermijn opzeggen. | H17: 0.71598499 | M17: TN
A18: COMPL Regel Partners - HOVK - Luchthavenweg 81 - 20260728.pdf | B18: After the 5-year term, the lease is extended for another 5 years unless terminated. After the second 5-year term, it automatically extends for further 5-year periods unless terminated with 12 months' notice. | C18: After the 5-year term, the lease is extended for another 5 years unless terminated. After the second 5-year term, it automatically extends for further 5-year periods unless terminated with 12 months' notice. | H18: 0.68572498
A19: COMPL_-_Onderhuurovereenkomst_Zelfstroom_B.V._-_50five_B.V._-_kantoorgebouw_Riva_-_05032026.pdf | B19: Geen verlengings- of optievoorwaarden; de huurovereenkomst eindigt van rechtswege per 1 juni 2026 zonder verlenging of optie tot verlenging. | C19: Geen verlengings- of optievoorwaarden; de huurovereenkomst eindigt van rechtswege per 1 juni 2026 zonder verlenging of optie tot verlenging. | H19: 0.91467391 | K19: Field: | L19: Terms / Option_Notes
A20: Den Bosch, Ruwekampweg 4, HOVK getekend.pdf | B20: Tenant has the right to break the lease after the fifth year (December 31, 2021) with a fee of €75,000, and after the seventh year (December 31, 2023) with a fee of €55,000. | C20: Tenant has the right to break the lease after the fifth year (December 31, 2021) with a fee of €75,000, and after the seventh year (December 31, 2023) with a fee of €55,000. | H20: 0.53829739
A21: FULLY SIGNED - COMPL Huurovereenkomst - Heijmans - Hugo de Grootlaan 23 's-Hertogenbosch V2 30-9-2025.pdf | B21: Na het eerste jaar wordt de huurovereenkomst telkens automatisch verlengd met 3 maanden, tenzij opgezegd volgens de genoemde termijnen. | C21: Na het eerste jaar wordt de huurovereenkomst telkens automatisch verlengd met 3 maanden, tenzij opgezegd volgens de genoemde termijnen. | H21: 0.91038251
A22: FULLY SIGNED - DEF_COMPL_Huurovereenkomst_Robo_Charge_-_Campus_Offices_-_20260220.pdf | B22: Lease automatically extends with 5-year renewal periods; both parties may terminate with 12 months' notice. Tenant has perpetual first refusal right to rent 2 extra storage rooms (second floor, wing C). | C22: Lease automatically extends with 5-year renewal periods; both parties may terminate with 12 months' notice. Tenant has perpetual first refusal right to rent 2 extra storage rooms (second floor, wing C). | H22: 0.69344433
A23: FULLY SIGNED - Onderhuurovereenkomst Aartshertogenlaan 223, `s-Hertogenbosch - Koning Willem I College B.V. 2606202.pdf | B23: De onderhuurovereenkomst eindigt van rechtswege op 31 juli 2029; er zijn geen verlengings- of optie-rechten opgenomen. | C23: De onderhuurovereenkomst eindigt van rechtswege op 31 juli 2029; er zijn geen verlengings- of optie-rechten opgenomen. | H23: 0.91467391
A24: FULLY SIGNED COMPL_DEF_Huurovereenkomst_Bond_Bergschot_Breda.pdf | B24: After initial 3 years and 6 months, lease renews automatically for extensions of 3 years and 6 months unless terminated with 9 months' notice. Tenant has right of first refusal for the 4th floor, B. | C24: After initial 3 years and 6 months, lease renews automatically for extensions of 3 years and 6 months unless terminated with 9 months' notice. Tenant has right of first refusal for the 4th floor, B. | H24: 0.67112332
A25: FullySigned_Allonge_II_Virtual_Vaults_Nederland.pdf | B25: Lease is extended for 5 years (Nov 2027–Oct 2032), then continues in periods of 5 years unless terminated with 12-month notice; right of first refusal for 3rd floor, building B. | C25: Lease is extended for 5 years (Nov 2027–Oct 2032), then continues in periods of 5 years unless terminated with 12-month notice; right of first refusal for 3rd floor, building B. | H25: 0.56537682
A26: FullySigned_Lease_Agreement_Neste_EDGE_Coolsingel.pdf | B26: Tenant may extend for consecutive 5-year terms; right of first refusal on 5th floor and second refusal on 6th floor if conditions met; competitor clause applies for 6th floor. | C26: Tenant may extend for consecutive 5-year terms; right of first refusal on 5th floor and second refusal on 6th floor if conditions met; competitor clause applies for 6th floor. | H26: 0.67908541
A27: HOK Waalhaven Group (signed).pdf | B27: Lease automatically extends for 5-year periods after initial 5-year term unless terminated by 12-month notice by Tenant or Landlord. | C27: Lease automatically extends for 5-year periods after initial 5-year term unless terminated by 12-month notice by Tenant or Landlord. | H27: 0.58846154
A28: Hovk Avans (3e+4e+5e verd.) 20140425.pdf | B28: Huurder heeft het recht deze huurovereenkomst na afloop van de huurtermijn op 30 juni 2019 te verlengen met een periode van 5 jaar tegen gelijkblijvende condities. | C28: Huurder heeft het recht deze huurovereenkomst na afloop van de huurtermijn op 30 juni 2019 te verlengen met een periode van 5 jaar tegen gelijkblijvende condities. | H28: 0.59417476
A29: HOVK Power4People 2025.pdf | B29: Service agreement renews for 12 months unless written notice is received at least 3 months before end date | C29: Service agreement renews for 12 months unless written notice is received at least 3 months before end date | H29: 0.63709369
A30: Huurovereenkomst (Semmie Group B.V.) - Wilhelminasingel 19, Breda.pdf | B30: Deze huurovereenkomst wordt na de initiële periode automatisch voortgezet voor telkens 1 jaar, tenzij beëindigd door opzegging met 6 maanden opzegtermijn. | C30: Deze huurovereenkomst wordt na de initiële periode automatisch voortgezet voor telkens 1 jaar, tenzij beëindigd door opzegging met 6 maanden opzegtermijn. | H30: 0.91038251
A31: Huurovereenkomst - proces-verbaal van oplevering - sleuteloverdracht - Kennedyplein 101 - getekend.pdf | B31: After initial 3-year term, lease extends for 2 years, then auto-renews for 1 year periods. 12-month notice required for termination. | C31: After initial 3-year term, lease extends for 2 years, then auto-renews for 1 year periods. 12-month notice required for termination. | H31: 0.73051792
... A35: Huurovereenkomst PBG Parallelweg 64 (beg.grond) 20121008.pdf | B35: Na afloop van een huurperiode wordt verlengd met telkens 5 jaar; huurder mag tussentijds beëindigen per 30-09-2017, 30-09-2018 of 30-09-2019 met 6 maanden opzegtermijn | C35: Na afloop van een huurperiode wordt verlengd met telkens 5 jaar; huurder mag tussentijds beëindigen per 30-09-2017, 30-09-2018 of 30-09-2019 met 6 maanden opzegtermijn | H35: 0.59417476
A36: MWO CBRE SPA (ITALY) CBRE_090724.pdf

Sheet Field 30
A1: Doc Name | B1: Manual Data | C1: Response Data | D1: Result | E1: Manual Pg | F1: Response Pg No | G1: Pg Result | H1: Confidence | K1: SUMMARY SHEET | N1: PAGE SUMMARY SHEET
A2: 20181204 Huurovereenkomst (GETEKEND).PDF | B2: EUR | C2: EUR | H2: 0.93894487 | K2: Metrics | L2: Percentage | N2: Metrics | O2: Percentage
